Workbook

Sheet Index
A1: Monkey-Myth Matrix — Index & Reconciliation Map
A2: Spine (essays) <-> Matrix (rows) crosswalk · what's built vs. what the essays promise · what's owed next
A3: Reference map, updated 2026-08-18. Cluster + tier counts are live formulas. Now 84 rows / 18 active codes: 17 evidence clusters plus the AD-01 methodology lens. v0.21 adds an explicit evidence/adaptation boundary.
A5: 1 · The three layers
A6: Layer | B6: Source document(s) | D6: Holds
A7: Doctrine | B7: Handoff Packet | D7: Guardrails; confidence tiers (1 / 2 / 3); model failure-mode list; build steps; keeper lines. The operating manual.
A8: Spine | B8: MFM + Priesthood-Function (both CC0) | D8: Foundational lens; the bulk of Tier 1-2 readings; the Tier-3 speculative branches; the mechanism vocabulary. Richer than the matrix.
A9: Matrix | B9: This workbook (12 data/scaffold sheets) | D9: 84 rows across 17 evidence clusters + AD-01 methodology lens; 18 sheets including Story Bridge, source queues, prompts, validation, and change logs.
A11: 2 · Spine -> Matrix crosswalk (every essay section, where it lives, what's owed)
A12: Spine ref | B12: Covers | C12: Tier | D12: Cluster(s) | E12: Rows present | F12: Status / what's owed
A13: MFM §1-3, 3A | B13: Thesis; monkey-politics lens; myth as processed memory; drift mechanics | C13: 1-2 | D13: lens / method | E13: — | F13: Doctrine & method, not rows.
A14: MFM §4 | B14: Labor revolt: Atrahasis (Igigi revolt -> human worker) | C14: 1 | D14: FM-01, RF-01, TR-01 | E14: FM-001, TR-001 | F14: Atrahasis sits in as a FLOOD row; the labor-revolt angle has no dedicated row. OWED.
A15: MFM §5 | B15: Watchers / Nephilim / hybrid anxiety | C15: 2 | D15: RF-01 | E15: RF-003 | F15: Built.
A16: MFM §5A | B16: The smith & technology taboo | C16: 2 | D16: RF-01 | E16: RF-002, RF-003, RF-006, RF-007, RF-008 | F16: BUILT - Hephaestus + Wayland (captured-maker pole), Tubal-Cain (technology-taboo pole) added this pass
A17: MFM §6 | B17: Succession: gods as ruling houses | C17: 1-2 | D17: SC-01, OO-01 | E17: SC-001/002/003 | F17: OWED: divine-succession cycle (Uranus/Cronus/Zeus, Kumarbi).
A18: MFM §6A | B18: Sacred geography: property law with incense | C18: 2 | D18: SG-01 | E18: SG-001 | F18: Thinnest cluster (1 row). OWED: more land-claim rows.
A19: MFM §6B | B19: Scapegoat engine (Girard, contested) | C19: 2 | D19: SC-01 | E19: (mechanism behind SC) | F19: The motor under SC-01. Caveat: mimetic theory is literary, not primatology.
A20: MFM §7 | B20: Narrative heist: Atrahasis -> Marduk | C20: 1-2 | D20: PB-01, OO-01 | E20: PB-001, OO-001 | F20: Core anchor. Built & strong.
A21: MFM §7A | B21: Covenant as vassal treaty (Hittite -> biblical) | C21: 1-2 | D21: CC-01 | E21: CC-001 | F21: DONE — founding row of CC-01. Tier 1 (form) / Tier 2 (capture-reading & dating).
A22: MFM §8 | B22: The feminine under capture (demonize / split) | C22: 2 | D22: DF-01 | E22: DF-001..005 | F22: Built — now the DEMONIZED/split figures only (Tiamat, Lamashtu, Lilith, Medusa, Coyolxauhqui). Co-opted ones moved to UF-01.
A23: MFM §9 | B23: Inanna/Ishtar/Kali — 'furnace with a face' | C23: 1-2 | D23: UF-01 | E23: UF-001 - UF-006 | F23: DONE - UF-01 now holds 6: Inanna, Kali, Athena, Durga, Sekhmet, Cybele across all 3 sub-types
... A36: PF Counter. | B36: Distributed authority; refusal of closure; non-divisible org; relational/assembler | C36: 1 | D36: anti-capture doctrine | E36: — | F36: Doctrine. The 12-vs-remainder lens is what the date-log numerology violated.
A38: 3 · Rows & clusters still owed (the 'continue forward' menu)
A39: Item | B39: What / where | C39: Tier | D39: Target | E39: From | F39: Priority / note
A40: Covenant / vassal-treaty | B40: Hittite -> biblical covenant as capture | C40: 1-2 | D40: CC-01 (new) | E40: MFM §7A | F40: DONE — CC-001, founding row of CC-01.
A41: Inanna / Ishtar row | B41: The unsplit / co-opted feminine | C41: 1-2 | D41: UF-01 (new) | E41: MFM §9 | F41: DONE — UF-001; DF-01 split into demonized (DF-01) vs co-opted/uncontained (UF-01).
A42: Captured-craftsman rows | B42: Hephaestus, Wayland, Tubal-Cain | C42: 2 | D42: RF-01 | E42: MFM §5A | F42: DONE - RF-006 Hephaestus (crippled-maker), RF-007 Wayland (enslaved-maker), RF-008 Tubal-Cain (marked-lineage); §5A sub-cluster complete
A43: Resurrection-as-refusal | B43: Refusal of administrative closure | C43: 1 | D43: DT-01 | E43: PF Case 3 | F43: DONE - DT-003 Osiris / DT-004 Dumuzi / DT-005 Baal added across 3 sub-types; PF Case 3 now represented
A44: Atrahasis labor row | B44: Revolt -> replacement labor (distinct from flood) | C44: 1 | D44: RF-01 / FM-01 | E44: MFM §4 | F44: MED
A45: Divine-succession cycle | B45: Uranus/Cronus/Zeus; Kumarbi | C45: 1-2 | D45: OO-01 / SC-01 | E45: MFM §6 | F45: MED
A46: Populate UF-01 | B46: Athena (co-opted), Durga, Sekhmet, Cybele | C46: 1-2 | D46: UF-01 | E46: MFM §9 | F46: LARGELY DONE - Athena, Durga (constituted), Sekhmet (uncontained), Cybele (harnessed) added this pass; UF-01 = 6 figures
A47: Sibling rows for CC-01 | B47: Debt-bondage / jubilee; Esarhaddon oath; tamitu | C47: 1-2 | D47: CC-01 | E47: PF §4 | F47: DONE - CC-002 debt-bondage/Jubilee (debt-release), CC-003 Esarhaddon ade (loyalty-oath), CC-004 tamitu (oracular-access) added; CC-01 now 4, sub-type tagged
A48: Expand sacred geography | B48: More land-claim rows | C48: 2 | D48: SG-01 | E48: MFM §6A | F48: LOW-MED — thinnest cluster
A49: Pharisees entry | B49: Distributed remainder after a center falls | C49: 1 | D49: systems | E49: PF Case 2 | F49: DONE - built as DR-01 (new cluster): Pharisees/rabbinic Judaism (DR-001) + Reformation + Buddha
A50: CREATE CT-01 | B50: Celestial / Climate Trauma Signal | C50: 2-3 | D50: new cluster | E50: Handoff | F50: Quarantine; holds the Göbekli pass once done
... A53: CREATE Tier-3 bins | B53: Monster taxonomy (MT-01), cousin-monkey, body-paint | C53: 3 | D53: new cluster(s) | E53: MFM §10A/13/14 | F53: Labeled Tier-3 bins so they can't leak into the Tier 1-2 matrix
A55: 4 · Cluster roster (v0.21 builds 18 active codes: 17 evidence clusters + AD-01 method lens; counts are live)
A56: Code | B56: Name | C56: Status | D56: Rows (live) | E56: Tier home | F56: Note
A57: PB-01 | B57: Primordial Body / Corpse-World | C57: Built | D57: =COUNTIF('Master Matrix'!$B:$B,"PB-01") -> 5 | E57: 1-2 mostly
A58: OO-01 | B58: Ordering Operator / New Boss | C58: Built | D58: =COUNTIF('Master Matrix'!$B:$B,"OO-01") -> 5 | E58: 1-2 mostly
A59: RF-01 | B59: Rebel Blood / Embedded Remainder | C59: Built | D59: =COUNTIF('Master Matrix'!$B:$B,"RF-01") -> 8 | E59: 1-2 mostly | F59: Embedded remainder. Now incl. the §5A captured-craftsman sub-cluster (Hephaestus, Wayland, Tubal-Cain), sub-type tagged; older RF rows untagged pending analysis.
A60: DF-01 | B60: Demonized Feminine / Unadministrable Woman | C60: Built | D60: =COUNTIF('Master Matrix'!$B:$B,"DF-01") -> 5 | E60: 1-2 mostly | F60: Now demonized/split figures only (co-opted ones -> UF-01)
A61: TR-01 | B61: Trickster / Unauthorized Intelligence | C61: Built | D61: =COUNTIF('Master Matrix'!$B:$B,"TR-01") -> 5 | E61: 1-2 mostly
A62: SC-01 | B62: Scapegoat / Founding Violence | C62: Built | D62: =COUNTIF('Master Matrix'!$B:$B,"SC-01") -> 3 | E62: 1-2 mostly
A63: FM-01 | B63: Flood / Reset Memory | C63: Built | D63: =COUNTIF('Master Matrix'!$B:$B,"FM-01") -> 3 | E63: 1-2 mostly
A64: SG-01 | B64: Sacred Geography / Land Claim | C64: Built | D64: =COUNTIF('Master Matrix'!$B:$B,"SG-01") -> 1 | E64: 1-2 mostly
A65: DT-01 | B65: Death-Admin / Refusal of Closure | C65: Built | D65: =COUNTIF('Master Matrix'!$B:$B,"DT-01") -> 6 | E65: 1-2 mostly | F65: FULLY anchored (6 figures): Hero Twins + Persephone now built out from placeholders; Osiris, Dumuzi, Baal, Christian resurrection. Six distinct death-admin / refusal modes.
A66: BW-01 | B66: Birth Threshold / Warding Power | C66: Built | D66: =COUNTIF('Master Matrix'!$B:$B,"BW-01") -> 1 | E66: 1-2 mostly
A67: AD-01 | B67: Asha / Druj Functional Lens | C67: Built | D67: =COUNTIF('Master Matrix'!$B:$B,"AD-01") -> 3 | E67: 1-2 mostly
A68: CC-01 | B68: Sacred Contract / Covenant Capture | C68: Built (new) | D68: =COUNTIF('Master Matrix'!$B:$B,"CC-01") -> 3 | E68: 1-2 | F68: Now 3 mechanisms (tamītu relocated to the new DV-01 divination cluster): vassal-treaty (CC-001), debt-release (CC-002), loyalty-oath (CC-003).
A69: UF-01 | B69: Uncontained / Co-opted Feminine | C69: Built (new) | D69: =COUNTIF('Master Matrix'!$B:$B,"UF-01") -> 8 | E69: 1-2 | F69: Session-built sibling to DF-01. 6 figures across 3 balanced sub-types: constituted (Athena, Durga), harnessed-autonomy (Inanna, Cybele), uncontained (Kali, Sekhmet). Beyond the handoff's 14.
A70: DV-01 | B70: Divination / Gatekeeping Divine Will | C70: Built (new) | D70: =COUNTIF('Master Matrix'!$B:$B,"DV-01") -> 4 | E70: 1-2 | F70: Seeded by tamītu (relocated from CC-01). 4 modes across 4 regions: binary-query (Mesopotamia), ambiguous-utterance (Delphi), state-veto (Rome), royal-monopoly (Shang). Purest priesthood-function; note the writing-from-divination thread.
A71: DR-01 | B71: Distributed Remainder / Center's Fall | C71: Built (new) | D71: =COUNTIF('Master Matrix'!$B:$B,"DR-01") -> 3 | E71: 1-2 | F71: PF Case 2 (formerly homeless) now homed. 3 distribution-triggers: place destroyed (Pharisees), monopoly broken (Reformation), founder dies (Buddha). Key tension: distribution re-concentrates.
A72: VA-01 | B72: Voice / Authorship / Signal Capture | C72: Built (v0.21) | D72: =COUNTIF('Master Matrix'!$B:$B,"VA-01") -> 7 | E72: 1-2 | F72: 7 rows. Separates origination, repetition, recording, credibility, and circulation; includes counterexample Vāc.
A73: TH-01 | B73: Threshold / Exit / Jurisdiction | C73: Built (v0.21) | D73: =COUNTIF('Master Matrix'!$B:$B,"TH-01") -> 8 | E73: 1-2 | F73: 8 rows. Requires a real passage rule or jurisdictional mechanism; Hecate is a carefully bounded partial fit.
A74: CO-01 | B74: Capture by Office / Promotion | C74: Built (v0.21) | D74: =COUNTIF('Master Matrix'!$B:$B,"CO-01") -> 6 | E74: 1-2 | F74: 6 rows. Wukong and Erinyes anchor it; Daniel, Joseph, and Demeter keep promotion from meaning capture by default.
A75: CT-01 | B75: Celestial / Climate Trauma Signal | C75: Not built | D75: =COUNTIF('Master Matrix'!$B:$B,"CT-01") -> 0 | E75: 2-3 | F75: In handoff, not built — quarantine bin (Göbekli, comet claims)
A76: TM-01 | B76: Timekeeping / Instrument Architecture | C76: Not built | D76: =COUNTIF('Master Matrix'!$B:$B,"TM-01") -> 0 | E76: 3 | F76: In handoff, not built — provisional until a physical mechanism is shown
A77: LMF-01 | B77: Live Myth Formation | C77: Not built | D77: =COUNTIF('Master Matrix'!$B:$B,"LMF-01") -> 0 | E77: 3 | F77: In handoff, not built — quarantine for real-time myth (date log lives here as a demo)
A78: MT-01 | B78: Monster Taxonomy | C78: Not built | D78: =COUNTIF('Master Matrix'!$B:$B,"MT-01") -> 0 | E78: Tier 3 | F78: Proposed quarantine container; do not infer one shared monster mechanism.
A80: 5 · Mechanism glossary (the column verbs the matrix uses but never defined)
A81: Term | B81: Plain definition | E81: Spine source | F81: Shows in matrix as
A82: Capture | B82: Wild/emergent activity (refusal, awe, bonds, time) is identified as destabilizing or useful and pulled toward control. | E82: PF §1 | F82: root of 'Priesthood-Function Move'
A83: Canonization | B83: One authorized version is fixed; rival memories are marginalized or erased. | E83: PF §1 | F83: 'Priesthood-Function Move'
A84: Narrative heist | B84: A successful refusal is rewritten so suppressors look heroic and rebels look like chaos. | E84: PF §2 / MFM §7 | F84: 'Priesthood-Function Move'
A85: Co-option | B85: Power too strong to suppress is instead elevated and attached to the order it would have threatened (e.g. Inanna sanctifying kingship). | E85: MFM §9 / PF §1 | F85: UF-01; 'Priesthood-Function Move'
A86: Embedded remainder | B86: The refusal isn't erased — it's subordinated and built into the foundation, where it stays latent. | E86: PF §3 | F86: 'Remainder / What Survives'
A87: Black ledger | B87: Non-transactional life (time, relationship, meaning) is converted into debt the institution tracks and extracts. | E87: PF §4 | F87: subtext of capture rows; seeds CC-01
A88: 12-style vs remainder | B88: Power favors clean divisible units (12 months/signs/tribes); the remainder is what won't divide (13, lunar, primes). | E88: PF §5 | F88: the AD-01 lens; the date-log failure
A89: Priesthood failure modes | B89: Ossification; symbolic monopoly; ritual inflation; choke points; narrative laundering. Capture-by-drift. | E89: MFM §15 | F89: 'Notes / Warnings', 'Overclaim Risk'
A90: Asha / Druj | B90: Coherence/truth-pattern vs distortion/rupture. Lawful order itself becomes druj when bypass is removed. | E90: AD-01 | F90: AD-01 cluster
A91: Tiers 1 / 2 / 3
A93: Legend: amber = owed/homeless · indigo = create-new cluster · green = done. Evidence Mode + Adaptation Boundary now separate source fact from project invention.

Sheet Dashboard
A1: Comparative Monkey-Myth Matrix
A2: Purpose | B2: Track recurring mythic functions as hominid/social systems patterns, while keeping confidence tiers and source status visible.
A3: Guardrail | B3: Not one secret origin story. Compare functions, power mechanics, narrative capture, and remainder. No crown; no mandatory interpreter.
A4: Source spine | B4: Myth as Fossilized Monkey Politics + Priesthood-Function. Treat this as a working matrix to patch, fork, and source-pass.
A5: Created | B5: Updated 2026-08-18 · v0.21
J6: FRAME TEST — can a row fail? | N6: EVIDENCE / ADAPTATION BOUNDARY
A7: Cluster ID | B7: Cluster Name | C7: Starter Rows | D7: Notes | F7: Confidence Tier | G7: Rows | H7: Meaning | J7: Fit Verdict | K7: Rows | N7: Evidence Mode | O7: Rows
A8: PB-01 | B8: Primordial Body / Corpse-World | C8: =COUNTIF('Master Matrix'!$B:$B,A8) -> 5 | D8: Prior living/generative body killed, sacrificed, or disassembled into world/infrastructure. | F8: Tier 1 | G8: =COUNTIF('Master Matrix'!$L:$L,"Tier 1") -> 3 | H8: Grounded textual/social structure or internal framework. | J8: Fits | K8: =COUNTIF('Master Matrix'!$AC:$AC,"Fits") -> 13 | N8: Ancient textual core | O8: =COUNTIF('Master Matrix'!$AE:$AE,N8) -> 15
A9: OO-01 | B9: Ordering Operator / New Boss | C9: =COUNTIF('Master Matrix'!$B:$B,A9) -> 5 | D9: Violent or strategic organizer converts crisis into permanent sovereignty. | F9: Tier 1-2 | G9: =COUNTIF('Master Matrix'!$L:$L,"Tier 1-2") -> 67 | H9: Strong motif with plausible interpretive layer. | J9: Partial fit | K9: =COUNTIF('Master Matrix'!$AC:$AC,"Partial fit") -> 13 | N9: Ancient variant / reception | O9: =COUNTIF('Master Matrix'!$AE:$AE,N9) -> 1
A10: RF-01 | B10: Rebel Blood / Embedded Remainder | C10: =COUNTIF('Master Matrix'!$B:$B,A10) -> 8 | D10: Refusal, rebel material, or unauthorized knowledge becomes built into humans/culture. | F10: Tier 2 | G10: =COUNTIF('Master Matrix'!$L:$L,"Tier 2") -> 14 | H10: Plausible comparative reading; source pass required. | J10: Poor fit | K10: =COUNTIF('Master Matrix'!$AC:$AC,"Poor fit") -> 0 | N10: Medieval / early-modern literary | O10: =COUNTIF('Master Matrix'!$AE:$AE,N10) -> 4
A11: DF-01 | B11: Demonized Feminine / Unadministrable Woman | C11: =COUNTIF('Master Matrix'!$B:$B,A11) -> 5 | D11: Female generative, sexual, birth/death, land, or sovereign power is monstered or split. | F11: Tier 3 | G11: =COUNTIF('Master Matrix'!$L:$L,"Tier 3") -> 0 | H11: Deep speculative rope bridge; do not carry argument alone. | J11: Counterexample | K11: =COUNTIF('Master Matrix'!$AC:$AC,"Counterexample") -> 7 | N11: Later literary reception | O11: =COUNTIF('Master Matrix'!$AE:$AE,N11) -> 1
A12: TR-01 | B12: Trickster / Unauthorized Intelligence | C12: =COUNTIF('Master Matrix'!$B:$B,A12) -> 5 | D12: Boundary-crosser uses cunning, theft, humor, or loopholes to move culture forward. | J12: Not yet tested | K12: =COUNTIF('Master Matrix'!$AC:$AC,"Not yet tested") -> 51 | N12: Mixed — separate layers | O12: =COUNTIF('Master Matrix'!$AE:$AE,N12) -> 10
A13: SC-01 | B13: Scapegoat / Founding Violence | C13: =COUNTIF('Master Matrix'!$B:$B,A13) -> 3 | D13: A body absorbs social violence; murder or expulsion stabilizes the group. | N13: Project invention | O13: =COUNTIF('Master Matrix'!$AE:$AE,N13) -> 0
A14: FM-01 | B14: Flood / Reset Memory | C14: =COUNTIF('Master Matrix'!$B:$B,A14) -> 3 | D14: Water catastrophe or social reset becomes moral/cosmic narrative. | J14: Untested share | K14: =IFERROR(K12/COUNTA('Master Matrix'!$A$2:$A$200),"") -> 0.60714286 | N14: Legacy — not yet tagged | O14: =COUNTIF('Master Matrix'!$AE:$AE,N14) -> 53
A15: SG-01 | B15: Sacred Geography / Land Claim | C15: =COUNTIF('Master Matrix'!$B:$B,A15) -> 1 | D15: Mountain, spring, cave, grove, river, or boundary becomes divine proof of belonging. | J15: Read this block as an audit gap, not a score. A cluster with no Poor fit and no Counterexample has not been tested against anything.
A16: DT-01 | B16: Death-Admin / Refusal of Closure | C16: =COUNTIF('Master Matrix'!$B:$B,A16) -> 6 | D16: Underworld, judgment, resurrection, or return prevents power from having final say. | N16: Legacy rows remain explicitly queued for evidence-mode backfill; they are not silently treated as primary-text core.
A17: BW-01 | B17: Birth Threshold / Warding Power | C17: =COUNTIF('Master Matrix'!$B:$B,A17) -> 1 | D17: Childbirth, infant death, disease, milk, and postpartum danger are personified and ritually managed.
A18: AD-01 | B18: Asha / Druj Functional Lens | C18: =COUNTIF('Master Matrix'!$B:$B,A18) -> 3 | D18: Not good vs evil: coherence/truth-pattern versus distortion/rupture, including lawful distortion.
A19: CC-01 | B19: Sacred Contract / Covenant Capture | C19: =COUNTIF('Master Matrix'!$B:$B,A19) -> 3 | D19: Contract/oath/debt ported into the sacred and made permanent; mandatory interpreter. Founding row CC-001.
A20: UF-01 | B20: Uncontained / Co-opted Feminine | C20: =COUNTIF('Master Matrix'!$B:$B,A20) -> 8 | D20: Power too total to split — venerated, harnessed (sacred-marriage kingship), or left as paradox; the co-option pole DF-01 was conflating. Inanna (UF-001), Kali (UF-002).
A21: DV-01 | B21: Divination / Gatekeeping the Divine Will | C21: =COUNTIF('Master Matrix'!$B:$B,A21) -> 4 | D21: Divination as the mandatory-interpreter gate: tamītu (binary query), Delphi (ambiguous utterance), Rome (state veto), Shang (royal monopoly)
A22: DR-01 | B22: Distributed Remainder / Surviving the Center's Fall | C22: =COUNTIF('Master Matrix'!$B:$B,A22) -> 3 | D22: Counterpoint: signal survives a center's fall by distributing (Pharisees, Reformation, post-Buddha) — then re-concentrates
A23: VA-01 | B23: Voice / Authorship / Signal Capture | C23: =COUNTIF('Master Matrix'!$B:$B,A23) -> 7 | D23: Origin, repetition, transmission, record, credibility, and circulation are separate controls.
A24: TH-01 | B24: Threshold / Exit / Jurisdiction | C24: =COUNTIF('Master Matrix'!$B:$B,A24) -> 8 | D24: Real gates, passage rules, exit costs, route closure, escort, and jurisdiction conflict.
A25: CO-01 | B25: Capture by Office / Promotion | C25: =COUNTIF('Master Matrix'!$B:$B,A25) -> 6 | D25: Prior disruption plus offered title/honor: test neutralization against real inclusion and counterexamples.
A26: Immediate Work Queue
A27: Step | B27: Task | C27: Target Sheet | D27: Done? | E27: Notes
A28: 1 | B28: Run PB-01 cluster through MR-01 and MR-04 | C28: Model Run Prompts | E28: Start with Tiamat/Ymir/Tlaltecuhtli/Purusha/Pangu.
A29: 2 | B29: Do source pass for Enuma Elish + Atrahasis | C29: Source Pass Queue | E29: Lock the strongest Mesopotamian rows first.
A30: 3 | B30: Build Mesoamerican lane | C30: Regional Lanes | E30: Separate Nahua/Mexica from Maya; do not flatten.
A31: 4 | B31: Add source URLs/citations | C31: Master Matrix | E31: Primary source first; secondary source second.
A32: 5 | B32: Downgrade or remove weak parallels | C32: Model Review Log | E32: Counterexamples improve the matrix.

Sheet Master Matrix
A1: ID | B1: Cluster ID | C1: Cluster Name | D1: Sub-type / Capture Mode | E1: Tradition / Region | F1: Figure / Myth | G1: Surface Story | H1: Monkey-Politics Read | I1: Priesthood-Function Move | J1: Remainder / What Survives | K1: Primary Parallels | L1: Confidence Tier | M1: Verification Status | N1: Notes / Warnings | O1: Source Anchor | P1: Primary Text / Artifact to Verify | Q1: Passage / Lines Needed | R1: Secondary Scholarship Lead | S1: Model Review Prompt | T1: Model Notes | U1: Overclaim Risk | V1: Next Action | W1: Source URL / Citation | X1: Last Reviewed | Y1: Motif Evidence Tier | Z1: Interpretation Tier | AA1: Row Status | AB1: Predicted-But-Absent (frame test) | AC1: Fit Verdict | AD1: Strongest Counter-Reading | AE1: Evidence Mode | AF1: Adaptation Boundary / Project Invention | AG1: Secondary Cluster(s)
A2: PB-001 | B2: PB-01 | C2: Primordial Body / Corpse-World | E2: Babylonian / Mesopotamian | F2: Tiamat | G2: Sea/chaos mother defeated by Marduk; her body becomes ordered cosmos. | H2: Prior generative order is demonized and butchered by the new regime. | I2: Narrative heist: violence becomes cosmic order and kingly legitimacy. | J2: Chaos/sea/mother power remains as the buried body of the world. | K2: Ymir; Tlaltecuhtli; Leviathan/Yam; Vritra | L2: Tier 1-2 | M2: Anchored (v0.20); tablet/line refs entered, primary NOT opened in-edition | N2: Use as a structural comparator, not proof of one origin. [v0.20 source-pass] Ee IV is a clean anchor for corpse -> cosmos. The body -> landscape detail sits on Tablet V, the epic's most damaged tablet: do not quote V without checking the lacunae. Tiers untouched. | O2: MFM §7; PF case study 1 | P2: Enuma Elis, Tablet IV (killing and splitting) + Tablet V (body -> cosmic features). Critical edition: Lambert 2013. Translation: Dalley 2000. | Q2: Ee IV 93-104 (net, winds, arrow); IV 129-132 (skull smashed with the mace, arteries severed); IV 135-140 (corpse surveyed, split 'like a dried fish', one half raised as the sky, skin stretched with guards posted to hold the waters back); IV 137-146 attested as the heavens-from-corpse passage. Tablet V for the body -> landscape mapping (rivers from the eyes, mountains from the breasts). IV lines are securely attested; V lines are NOT - Tablet V is the most damaged tablet in the epic and partly reconstructed from a Sultantepe duplicate. Confirm what survives before quoting V. | R2: Lambert, W. G., Babylonian Creation Myths (Eisenbrauns, 2013) = standard critical edition. Dalley, S., Myths from Mesopotamia, rev. ed. (OUP, 2000) = working translation. Talon, SAACT 4. eBL (electronic Babylonian Library) for the composite text and line numbering. | S2: Use MR-01 + MR-03 | U2: Medium until source pass complete | V2: Run model review, then source-pass [v0.20 source-pass] Open Lambert 2013 / eBL and pin exact V lines. Then M -> Sourced. | W2: Lambert 2013, Babylonian Creation Myths, Eisenbrauns | Dalley 2000, Myths from Mesopotamia, OUP: Tablet I at p. 234, Tablet II at pp. 243-244, Tablet VI at p. 261 (pages verified via secondary quotation, not opened in-edition) | X2: 2026-07-29 | Y2: Tier 1 | Z2: Tier 1-2 | AA2: Load-bearing | AB2: None identified. Corpse -> cosmos and the state-ritual use are both present in the primary. | AC2: Fits | AD2: The 'conquest of the feminine' reading is contested. Tiamat may function as an undifferentiated cosmological principle rather than a displaced political predecessor, and she is sympathetic in Tablet I - monstrous only after provocation. That cuts against reading her as demonised from the outset. | AE2: Legacy — not yet tagged
A3: PB-002 | B3: PB-01 | C3: Primordial Body / Corpse-World | E3: Norse | F3: Ymir | G3: Primordial giant killed by Odin and brothers; body becomes world. | H3: Older giant/ancestor body is converted into divine infrastructure. | I3: Embedded remainder: old body becomes foundation of new order. | J3: Jötnar remain kin/enemy; prior order is never fully erased. | K3: Tiamat; Tlaltecuhtli; Purusha; Pangu | L3: Tier 1-2 | M3: Needs source pass | N3: Not the same deity as Tiamat; same function cluster. | O3: Comparative candidate | P3: TBD: identify primary text/artifact | Q3: TBD: exact passage, tablet, chapter, hymn, codex plate, or oral-transcription source | R3: TBD: one reputable secondary source | S3: Use MR-01 + MR-03 | U3: Medium until source pass complete | V3: Run model review, then source-pass | Y3: Tier 1 | Z3: Tier 2 | AA3: Supportive | AB3: No state cult, no ritual re-performance, no institution shown using the Ymir cosmogony for legitimation. PB-01's political-capture half is absent; only the body -> world half is present. | AC3: Partial fit | AD3: Snorri's Gylfaginning is c. 1220 CE, roughly two centuries after Iceland's conversion, and is a Christian antiquarian systematising fragmentary verse. The tidiness of the corpse-world mapping may be Snorri's. Vafthrudnismal is the older witness - check what it actually supports before the row carries weight. | AE3: Legacy — not yet tagged
A4: PB-003 | B4: PB-01 | C4: Primordial Body / Corpse-World | E4: Nahua / Mexica | F4: Tlaltecuhtli | G4: Earth body/monster is torn apart or transformed to form habitable earth. | H4: Living earth-body is converted into land/infrastructure. | I4: Body-world creates ritual debt: the earth must be fed/maintained. | J4: Earth remains alive, hungry, and ritually demanding. | K4: Tiamat; Ymir; Coatlicue; Coyolxauhqui | L4: Tier 1-2 | M4: Partial; Graulich verified; Histoire du Mechique folio owed | N4: Mesoamerican lane: likely crucial for body-world + ritual debt. [v0.19.1 source-pass] Colonial witnesses. Graulich 1983 verified (confirm 'killed vs left alive' detail before quoting); Histoire du Mechique folio still owed. Support: partial. Tier unchanged. | O4: Comparative candidate | P4: Historia de los mexicanos por sus pinturas (Cipactli -> earth -> Tlaltecutli); Histoire du Mechique (de Jonghe ed.) for the tearing-in-two. | Q4: Hist. de los mexicanos ch. 2 paras 22 & 29; Histoire du Mechique folio NOT pinned (still owed). | R4: Graulich, 'Myths of Paradise Lost in Pre-Hispanic Central Mexico,' Current Anthropology 24:5 (1983): 575-588. [VERIFIED - confirm the 'killed vs left alive' point before quoting] | S4: Use MR-01 + MR-03 | U4: Medium until source pass complete | V4: Run model review, then source-pass [v0.19] Source-pass: source via colonial intermediary (Histoyre du Mechique); pin + living-tradition care (Nahua packet). | W4: Graulich 1983, Current Anthropology 24(5):575-588. doi.org/10.1086/203063 | Y4: Tier 2 | Z4: Tier 2 | AA4: Source-pass | AC4: Not yet tested | AE4: Legacy — not yet tagged
A5: PB-004 | B5: PB-01 | C5: Primordial Body / Corpse-World | E5: Vedic | F5: Purusha | G5: Cosmic being sacrificed; world and social order emerge from body. | H5: Sacrificial body becomes cosmos and social hierarchy. | I5: Sacrifice naturalizes order; body-politic becomes sacred structure. | J5: Social divisions persist as parts of a cosmic body. | K5: Ymir; Pangu; Tiamat; caste/body-politic patterns | L5: Tier 1-2 | M5: Needs source pass | N5: Watch caste/order claims carefully; do not overflatten devotional meaning. | O5: Comparative candidate | P5: TBD: identify primary text/artifact | Q5: TBD: exact passage, tablet, chapter, hymn, codex plate, or oral-transcription source | R5: TBD: one reputable secondary source | S5: Use MR-01 + MR-03 | U5: Medium until source pass complete | V5: Run model review, then source-pass [v0.19.1] Raised Source-pass -> Supportive: RV 10.90 anchor is clean enough; interpretation still capped at Tier 2. | Y5: Tier 1 | Z5: Tier 2 | AA5: Supportive | AB5: No conquest, no adversary, no coup. The sacrifice is voluntary and self-generated, so PB-01's 'prior order destroyed by a new regime' element is missing entirely. | AC5: Partial fit | AD5: RV 10.90 is generally held to be among the latest hymns in the Rig Veda. The varna verse may record an emergent ritual homology rather than the codified caste order later read back into it. Verify with a Vedic specialist before this row supports any capture claim. | AE5: Legacy — not yet tagged
A6: PB-005 | B6: PB-01 | C6: Primordial Body / Corpse-World | E6: Chinese | F6: Pangu | G6: Primordial being separates heaven and earth; body becomes world after death. | H6: Cosmic body becomes infrastructure with less overt coup/murder. | I6: Softer body-world form; world-order emerges from prior body. | J6: Body parts persist as features of world. | K6: Ymir; Purusha; Tiamat | L6: Tier 2 | M6: Needs source pass | N6: Lower violence than Tiamat/Ymir; same architecture, different mood. [v0.19] Soft body-world comparator: no murder/coup/demonization - do NOT let it carry the capture argument. | O6: Comparative candidate | P6: TBD: identify primary text/artifact | Q6: TBD: exact passage, tablet, chapter, hymn, codex plate, or oral-transcription source | R6: TBD: one reputable secondary source | S6: Use MR-01 + MR-03 | U6: Medium until source pass complete | V6: Run model review, then source-pass [v0.19.1] Dropped Supportive -> Source-pass (soft comparator only): Interp Tier 3 cannot be Supportive/Load-bearing; must not carry the capture argument. | Y6: Tier 2 | Z6: Tier 3 | AA6: Source-pass | AB6: No murder, no adversary, no subordinated remainder, no legitimated ruler. Every element of PB-01's diagnostic except 'body becomes world' is absent. | AC6: Counterexample | AD6: The honest reading is that body -> world cosmogony does not require a capture event - which is what this row demonstrates. NOTE: the 'same architecture, different mood' gloss in col N absorbs the mismatch instead of scoring it. Treat that gloss as the frame protecting itself. | AE6: Legacy — not yet tagged
A7: OO-001 | B7: OO-01 | C7: Ordering Operator / New Boss | E7: Babylonian / Mesopotamian | F7: Marduk | G7: Defeats Tiamat, organizes cosmos, receives supremacy among gods. | H7: Young military/executive operator converts crisis into permanent sovereignty. | I7: Emergency powers become kingly order; state-temple legitimation. | J7: Defeated older order persists as the world he rules. | K7: Odin; Indra; Baal; Tezcatlipoca/Quetzalcoatl | L7: Tier 1-2 | M7: Anchored (v0.20); STRONG - the irrevocability clause is explicit in the text | N7: Best anchor for narrative heist / hostile takeover reading. [v0.20 source-pass] FINDING: OO-01's core diagnostic ('crisis converted into permanent sovereignty') is explicit in the primary text, not inferred. Marduk's condition includes a no-revocation clause, and the assembly grants it in advance of the battle. Recommend the motif tier be reviewed upward next pass; NOT changed here, per the discipline that a source pass does not re-tier. Akitu recitation supplies the state-ritual context. | O7: MFM §7; PF case study 1 | P7: Enuma Elis, Tablet II (Marduk's terms) + Tablet IV 1-34 (the assembly grants them) + Tablet VI-VII (kingship, Babylon, the fifty names). | Q7: Ee II: Marduk's price - convene the assembly, fix a special fate, 'my own utterance shall fix fate instead of you; whatever I decree of my lips shall never be revoked, never changed' (Dalley pp. 243-244; LINE NUMBERS NOT PINNED). Ee IV 1-34: the assembly agrees before the crisis is resolved - 'your destiny is unequalled, your word has the power of Anu' - and tests his word on a constellation. Ee VI 99: kingship over the gods. Ee VI 55, 72: Babylon and Esagila. Ee VII: the fifty names. Context: the epic was recited at the Akitu New Year festival - annual re-performance of the charter. | R7: Lambert, W. G., Babylonian Creation Myths (Eisenbrauns, 2013) = standard critical edition. Dalley, S., Myths from Mesopotamia, rev. ed. (OUP, 2000) = working translation. Talon, SAACT 4. eBL (electronic Babylonian Library) for the composite text and line numbering. On the Akitu recitation and the Ashur recension, check a standard reference. | S7: Use MR-01 + MR-03 | U7: Medium until source pass complete | V7: Run model review, then source-pass [v0.20 source-pass] Pin Ee II line numbers, then propose a tier review for Y (motif). | W7: Lambert 2013, Babylonian Creation Myths, Eisenbrauns | Dalley 2000, Myths from Mesopotamia, OUP: Tablet I at p. 234, Tablet II at pp. 243-244, Tablet VI at p. 261 (pages verified via secondary quotation, not opened in-edition) | X7: 2026-07-29 | Y7: Tier 1 | Z7: Tier 1 | AA7: Load-bearing | AB7: None. The irrevocability clause makes 'crisis converted into permanent sovereignty' explicit rather than inferred. | AC7: Fits | AD7: The Assur recension substitutes Ashur for Marduk, so the charter is portable. That supports reading the epic as a general kingship ideology rather than the record of one historical usurpation - which weakens any specific political-event reading. | AE7: Legacy — not yet tagged
A8: OO-002 | B8: OO-01 | C8: Ordering Operator / New Boss | E8: Norse | F8: Odin + brothers | G8: Kill Ymir and order the world from his body. | H8: Younger divine faction converts primordial ancestor into structured world. | I8: New order stabilizes itself through old body's conversion. | J8: Giant line continues as kin/enemy/remainder. | K8: Marduk; Tezcatlipoca/Quetzalcoatl; Indra | L8: Tier 1-2 | M8: Needs source pass | N8: Odin also carries knowledge, sacrifice, war, death; do not reduce him to Marduk. | O8: Comparative candidate | P8: TBD: identify primary text/artifact | Q8: TBD: exact passage, tablet, chapter, hymn, codex plate, or oral-transcription source | R8: TBD: one reputable secondary source | S8: Use MR-01 + MR-03 | U8: Medium until source pass complete | V8: Run model review, then source-pass | Y8: Tier 1 | Z8: Tier 2 | AA8: Supportive | AC8: Not yet tested | AE8: Legacy — not yet tagged
A9: OO-003 | B9: OO-01 | C9: Ordering Operator / New Boss | E9: Nahua / Mexica | F9: Tezcatlipoca / Quetzalcoatl | G9: Rival operators involved in world-formation, earth-body, and cosmic cycles in variants. | H9: Divine rivals reshape prior earth/monster/body into usable world. | I9: World-order emerges through conflict and ritual maintenance. | J9: Earth/body/monster remains as debt-bearing infrastructure. | K9: Marduk; Odin; Enki/Enlil; Hero Twins | L9: Tier 2 | M9: Composite; flag for split; secondary owed | N9: Handle variants carefully; do source pass before locking row. [v0.19.1 source-pass] Supports solar succession + divine competition, NOT one unified overthrow - composite; flag for split. Secondary still owed. Support: partial. Tier unchanged. | O9: Comparative candidate | P9: Historia de los mexicanos por sus pinturas (Tezcatlipoca/Quetzalcoatl orderings; the Suns). | Q9: Hist. de los mexicanos ch. 2 paras 14-16, 22, 29; ch. 3 para 33; chs. 5-7 (the Suns) - supports solar succession + divine competition, NOT one unified overthrow. | R9: NOT FOUND - secondary still owed. (Graulich 1983, entered at PB-003, bears on the Suns/creation context.) | S9: Use MR-01 + MR-03 | U9: Medium until source pass complete | V9: Run model review, then source-pass [v0.19] Source-pass: composite; pin exact version/source before use (Nahua packet). | W9: Primary to confirm (Hist. de los mexicanos chs. 2-7). Secondary owed. | Y9: Tier 3 | Z9: Tier 3 | AA9: Source-pass | AC9: Not yet tested | AE9: Legacy — not yet tagged
A10: OO-004 | B10: OO-01 | C10: Ordering Operator / New Boss | E10: Vedic | F10: Indra | G10: Defeats Vritra and releases waters. | H10: Storm/war chief breaks hoarder/serpent control of life-resource. | I10: Violence legitimates order by freeing controlled resource. | J10: Serpent/hoarder remains as recurring chaos/resource-control figure. | K10: Baal/Yam; Yahweh/Leviathan; Marduk/Tiamat | L10: Tier 1-2 | M10: Needs source pass | N10: Better as resource-release/chaoskampf than corpse-world. | O10: MFM monster taxonomy; comparative candidate | P10: TBD: identify primary text/artifact | Q10: TBD: exact passage, tablet, chapter, hymn, codex plate, or oral-transcription source | R10: TBD: one reputable secondary source | S10: Use MR-01 + MR-03 | U10: Medium until source pass complete | V10: Run model review, then source-pass | Y10: Tier 1 | Z10: Tier 2 | AA10: Supportive | AC10: Not yet tested | AE10: Legacy — not yet tagged
A11: OO-005 | B11: OO-01 | C11: Ordering Operator / New Boss | E11: Levantine / Biblical poetic | F11: Baal / Yahweh storm-war motifs | G11: Storm/king god defeats sea, dragon, Leviathan/Rahab/Yam in poetic or mythic material. | H11: Rule legitimized by victory over unadministered sea/chaos/resource. | I11: Chaoskampf becomes sacred kingship/order language. | J11: Sea/dragon imagery persists as recurring threat. | K11: Marduk/Tiamat; Indra/Vritra; Zeus/Typhon | L11: Tier 1-2 | M11: Cut/Merge - inactive; leads only, nothing Sourced | N11: Avoid flattening distinct traditions; compare motif, not identity. [v0.19.1 source-pass] Nothing verified to enter. Stays Cut/Merge / INACTIVE until split. GPT's pointers (Baal Cycle KTU/CAT; Ps 74, 89, Isa 27, Job 26) are LEADS for the split, not sources - do not mark Sourced. | O11: MFM §7 / Chaoskampf | P11: Leads only (NOT sources): Baal Cycle KTU/CAT 1.1-1.6 (Ugaritic); Ps 74, Ps 89, Isa 27:1, Job 26 (Yahweh storm-war) - for the eventual Baal vs Yahweh split. | Q11: (n/a - inactive until split) | R11: Leads only; nothing verified to enter as a secondary. | S11: Use MR-01 + MR-03 | U11: Medium until source pass complete | V11: Run model review, then source-pass [v0.19] SPLIT: separate into Baal (Ugaritic Baal Cycle) and Yahweh storm-war as parallel rows; do not cite as one figure. [v0.19.1] INACTIVE - do not cite as a live row until split into Baal and Yahweh storm-war parallels. | W11: (none - inactive until split) | Y11: Tier 2 | Z11: Tier 2 | AA11: Cut/Merge | AC11: Not yet tested | AE11: Legacy — not yet tagged
A12: RF-001 | B12: RF-01 | C12: Rebel Blood / Embedded Remainder | D12: rebel-blood | E12: Babylonian / Mesopotamian | F12: Kingu | G12: Rebel/consort killed; blood used to create humanity as labor force. | H12: Defeated refusal becomes material foundation of worker species. | I12: Embedded remainder: the rebel is killed, then built into the system. | J12: Humanity carries the blood/material of the refuser while assigned obedience. | K12: Prometheus; Azazel; sacrificed founding victims | L12: Tier 1-2 | M12: Anchored (v0.20); Lambert 287 supplies a real counter-detail - see counter-reading | N12: One of the strongest project nodes. [v0.20 source-pass] FINDING with teeth: Lambert notes the assembly's charge that Qingu made Tiamat rebel has no antecedent anywhere earlier in the epic. The guilt is retroactive. This is strong support for the embedded-remainder reading AND makes the row structurally a scapegoat case - it belongs to SC-01 as much as RF-01. Consider cross-referencing rather than a single home. | O12: PF case study 1 | P12: Enuma Elis, Tablet VI 1-46. Compare Atra-hasis I (parallel anthropogeny). | Q12: Ee VI 1-8: Marduk's plan - 'let me put blood together and make bones too... the work of the gods shall be imposed on him, and so they shall be at leisure' (VI 8 = the labour-imposition line). Ee VI 29-34: the assembly charges Qingu, he is bound, his blood vessels severed, mankind fashioned from his blood; VI 33-34 attested as 'Ea created mankind, on whom he imposed the service of the gods, and set the gods free'. Ee VI 43-46: organisation of the netherworld and stations of the gods. | R12: Lambert, W. G., Babylonian Creation Myths (Eisenbrauns, 2013) = standard critical edition. Dalley, S., Myths from Mesopotamia, rev. ed. (OUP, 2000) = working translation. Talon, SAACT 4. eBL (electronic Babylonian Library) for the composite text and line numbering. Lambert 2013 pp. 101, 111, 113 on the Qingu passages and p. 287 on the unsupported charge (page refs taken from a secondary index - confirm in-edition). Krebernik on Enlil/Ninurta forerunners. | S12: Use MR-01 + MR-03 | U12: Medium until source pass complete | V12: Run model review, then source-pass [v0.20 source-pass] Confirm Lambert p. 287 in-edition; propose RF-001 <-> SC-01 cross-reference. | W12: Lambert 2013, Babylonian Creation Myths, Eisenbrauns | Dalley 2000, Myths from Mesopotamia, OUP: Tablet I at p. 234, Tablet II at pp. 243-244, Tablet VI at p. 261 (pages verified via secondary quotation, not opened in-edition) | Lambert 2013 pp. 101, 111, 113, 287 [page refs via secondary index] | X12: 2026-07-29 | Y12: Tier 1 | Z12: Tier 1 | AA12: Load-bearing | AB12: None. The remainder is literally the construction material. | AC12: Fits | AD12: Lambert notes the charge against Qingu has no antecedent earlier in the epic: the guilt is retroactive. This strengthens the reading but relocates the row - it is structurally a scapegoat case, so SC-01 has as good a claim on it as RF-01. | AE12: Legacy — not yet tagged
A13: RF-002 | B13: RF-01 | C13: Rebel Blood / Embedded Remainder | D13: stolen-fire | E13: Greek | F13: Prometheus | G13: Steals/gives fire to humans; punished by Zeus. | H13: Unauthorized tech transfer breaks elite monopoly. | I13: State/order punishes independent knowledge worker. | J13: Fire/culture remains with humans despite punishment. | K13: Azazel; Watchers; Māui; Raven; Hephaestus/Wayland | L13: Tier 1-2 | M13: Needs source pass | N13: Technology taboo + captured craftsman cluster. | O13: MFM §5A | P13: TBD: identify primary text/artifact | Q13: TBD: exact passage, tablet, chapter, hymn, codex plate, or oral-transcription source | R13: TBD: one reputable secondary source | S13: Use MR-01 + MR-03 | U13: Medium until source pass complete | V13: Run model review, then source-pass | Y13: Tier 1 | Z13: Tier 1-2 | AA13: Supportive | AC13: Not yet tested | AE13: Mixed — separate layers | AF13: Keep Hesiod and Prometheus Bound separate. The dangerous-marriage secret is tragic-layer evidence; a modern whistleblower trial is invention. | AG13: VA-01
A14: RF-003 | B14: RF-01 | C14: Rebel Blood / Embedded Remainder | D14: fallen-watchers | E14: Enochic Jewish | F14: Azazel / Watchers | G14: Teach forbidden crafts; descend and produce destabilizing offspring; punished. | H14: Elite/outsider knowledge and sexual access become demonized. | I14: Forbidden craft is managed by later moral/theological frame. | J14: Technical knowledge and hybrid anxiety remain inside human culture. | K14: Prometheus; Hephaestus; Apkallu; Nephilim | L14: Tier 1-2 | M14: Needs source pass | N14: Distinguish textual Enoch from later demonology. | O14: MFM §5 / §5A | P14: TBD: identify primary text/artifact | Q14: TBD: exact passage, tablet, chapter, hymn, codex plate, or oral-transcription source | R14: TBD: one reputable secondary source | S14: Use MR-01 + MR-03 | U14: Medium until source pass complete | V14: Run model review, then source-pass | Y14: Tier 1 | Z14: Tier 2 | AA14: Supportive | AC14: Not yet tested | AE14: Legacy — not yet tagged
A15: RF-004 | B15: RF-01 | C15: Rebel Blood / Embedded Remainder | D15: culture-hero | E15: Polynesian | F15: Māui | G15: Trickster/culture hero obtains fire, slows sun, fishes land, or alters cosmic conditions. | H15: Unauthorized intelligence modifies world-order for human use. | I15: System cannot stop useful theft/innovation from becoming culture. | J15: Human world carries trickster alterations. | K15: Prometheus; Raven; Coyote; Quetzalcoatl | L15: Tier 2 | M15: Needs source pass | N15: Variant-heavy; source specific islands/traditions. | O15: Comparative candidate | P15: TBD: identify primary text/artifact | Q15: TBD: exact passage, tablet, chapter, hymn, codex plate, or oral-transcription source | R15: TBD: one reputable secondary source | S15: Use MR-01 + MR-03 | U15: Medium until source pass complete | V15: Run model review, then source-pass [v0.19] Source-pass: needs named iwi/tradition + collector; no pan-Polynesian flattening. | Y15: Tier 2 | Z15: Tier 2 | AA15: Source-pass | AC15: Not yet tested | AE15: Legacy — not yet tagged
A16: RF-005 | B16: RF-01 | C16: Rebel Blood / Embedded Remainder | D16: culture-hero | E16: Pacific Northwest / Indigenous North American | F16: Raven | G16: Steals or releases light/fire; transforms world through cunning. | H16: Low-status or liminal intelligence brings culture by theft. | I16: Unauthorized acquisition becomes origin of human possibility. | J16: Light/fire/world-order remains despite trickster mess. | K16: Prometheus; Māui; Coyote; Anansi | L16: Tier 2 | M16: Secondary verified; stays Quarantine | N16: Must name specific tribal/version sources later. [v0.19.1 source-pass] Tie to Tlingit/Wrangell specifically; do NOT generalize as 'the Raven myth.' Thornton & Thornton 2015 verified (use FULL title; GPT gave only the subtitle). Stays Quarantine (handling discipline, K10). Motif Tier 3 = row-format/source-flattening, not denial of the motif in Tlingit sources. Support: partial (strong for this version). Tier unchanged. | O16: Comparative candidate | P16: Swanton, Tlingit Myths and Texts (BAE Bulletin 39, 1909) - Wrangell Raven (daylight-box release; distribution of water). | Q16: Wrangell Raven cycle - confirm exact myth number in Swanton 1909. | R16: Thornton & Thornton, 'The Mutable, the Mythical, and the Managerial: Raven Narratives and the Anthropocene,' Environment and Society 6:1 (2015): 66-86. [VERIFIED - full title] | S16: Use MR-01 + MR-03 | U16: Medium until source pass complete | V16: Run model review, then source-pass [v0.19] QUARANTINE: do not use until tied to a named nation/version/collector. [v0.19.1] Motif Tier 3 reflects row-format/source-flattening, not denial of the motif in specific nations. | W16: Thornton & Thornton 2015, Environment and Society 6(1):66-86. doi.org/10.3167/ares.2015.060105 | Y16: Tier 3 | Z16: Tier 3 | AA16: Quarantine | AC16: Not yet tested | AE16: Legacy — not yet tagged
A17: RF-006 | B17: RF-01 | C17: Rebel Blood / Embedded Remainder | D17: crippled-maker | E17: Greek (Hephaestus) / cf. Roman Vulcan | F17: Hephaestus — lame smith of Olympus, cast from heaven, mocked and cuckolded by the gods, yet sole maker of all their arms, palaces, and wonders. | G17: Born lame (Homer) — or crippled by the fall when Zeus seizes his leg and hurls him from Olympus for siding with Hera. He lands on Lemnos, returns, and becomes the indispensable artificer: Achilles' armour, Hermes' winged gear, Zeus's aegis, self-moving automatons, the gods' very halls. Forced to wed Aphrodite (to head off a war over her), he is cuckolded by Ares; when he nets the lovers, the gods laugh — at him. | H17: The one who actually MAKES the tools of power is kept structurally low — marked as defective, mocked, denied the status his output earns. The coalition extracts the maker's product while withholding rank; his deformity is the badge that licenses the extraction. But the maker holds quiet leverage no one else has: he makes the chair Hera can't rise from and the net Ares can't break — the one who forges the bindings can bind the bosses. | I17: His craft is absorbed into the order as ITS glory (the gods' arsenal is 'theirs') while he is framed as the comic, ugly, subordinate exception — the value canonized upward, the maker written down. The forced marriage and the laughter are the social machinery that keeps the indispensable producer in his place. | J17: The whole material order of Olympus is HIS work — the remainder is everywhere, embedded in every divine object. And the leverage keeps leaking: the trap-chair extracts a concession from Hera, the net publicly shames the war-god, and he is one of the few exiles who returns. The maker can't be fully written down because the order literally runs on what he alone can make. | K17: Wayland (RF-007, the lamed maker captured by a king); Tubal-Cain (RF-008); Prometheus (RF-002, fire/craft punished); Athena (UF-003 — Zeus's perfect head-born daughter vs Hera's crippled solo son) | L17: Tier 1-2 | M17: Sourced (this pass) | N17: Two origin-versions of the lameness (congenital vs caused-by-fall) — don't collapse them; Homer uses both inconsistently. The 'maker's leverage' reading is Tier 2 but rests on textual episodes (the chair, the net). The Athena cross-link via Hurwit's patriarchal-asymmetry point is itself a scholarly reading; cite it as such. | O17: MFM §5A (smith & technology taboo) — captured-maker pole. PF §1, §3 (capture, embedded remainder). Sub-cluster with Wayland. | P17: Homer, Iliad I.586-594 (Zeus hurls him; lands on Lemnos) and XVIII.368-617 (forging Achilles' armour; he recalls Hera casting him out 'shamed by my lameness'); Odyssey 8.266-366 (Ares/Aphrodite net). | Q17: Iliad I.590-600 (the fall + the gods' laughter as he serves nectar); Iliad XVIII.394-409 (Hera's rejection); Od. 8.266-366 (the net). | R17: J.M. Hurwit on the Hera/Zeus birth-asymmetry (perfect Athena vs crippled Hephaestus); Marie Delcourt, 'Hephaistos ou la legende du magicien' (1957); theoi.com compendium s.v. Hephaistos. | S17: Is 'maker's leverage' textual or romanticized? Verify the chair and net episodes; confirm the indispensability claim (range of objects he makes); keep the two lameness-versions distinct. | U17: MODERATE — the subordination-of-the-maker reading is well-grounded, but don't over-read the 'rebellion' (his leverage is real yet limited; he largely stays inside the order, unlike Wayland). Avoid treating Vulcan=Hephaestus syncretism as identity. | V17: Pull Iliad I + XVIII and Od. 8 line refs (Lattimore/Fagles); confirm Hurwit citation; mark the Athena cross-link as a scholarly reading. | W17: poetryintranslation.com Iliad XVIII; theoi.com/Olympios/Hephaistos; en.wikipedia.org/wiki/Hephaestus (Homer Il. I.586ff, XVIII; Od. 8) | X17: 2026-06-14 | Y17: Tier 1 | Z17: Tier 2 | AA17: Supportive | AC17: Not yet tested | AE17: Mixed — separate layers | AF17: Hephaestus's reluctant enforcement labor, divine status, workshop autonomy, and variant ejection stories must not be harmonized.
A18: RF-007 | B18: RF-01 | C18: Rebel Blood / Embedded Remainder | D18: enslaved-maker | E18: Norse / Germanic / Anglo-Saxon; Völundarkviða (Poetic Edda) | F18: Wayland / Völundr — master smith captured by a king, deliberately hamstrung to keep him producing, who works his revenge entirely through his craft and escapes on self-forged wings. | G18: King Niðhad, envious of Völundr's skill and treasures, seizes him in his sleep, has his hamstrings cut so he cannot flee, and imprisons him on an island to forge for the crown. The king wears Völundr's stolen sword; the princess wears his stolen ring. Völundr lures the king's two sons to the smithy, kills them, and reforges their skulls into goblets, eyes into jewels, teeth into a brooch — gifts sent unwitting to the royal family. He rapes and impregnates the princess, then flies away on wings he has made, taunting the king from the air. | H18: Power that cannot generate the craft itself seizes the body that can and MAIMS it precisely to bind it to production — the crippling is the control mechanism, not an accident. The king appropriates the maker's output (sword, ring) as his own household's adornment. But a bound maker is the most dangerous thing in the workshop: the only hands that can make the king's treasures can also make his catastrophe. | I18: Capture-and-extract in its rawest form — no canonizing theology, just force: enslave the producer, take the product, display it as the crown's. The 'gifts' the maker sends back are the move turned inside out — the order consumes and wears the maker's craft without knowing what it now contains. | J18: The remainder is monstrous and literal — the king eats from goblets made of his own sons, the queen wears their eyes, the princess a brooch of their teeth: the maker's embedded product is the captor's own undoing, hidden in plain sight. And the maker escapes intact via a made object (the wings); the craft meant to bind him is exactly what frees him. In Deor he is remembered as suffering endured and overcome. | K18: Hephaestus (RF-006, the other lamed captured maker — but Hephaestus stays inside the order; Wayland razes it); Tubal-Cain (RF-008); Prometheus (RF-002) | L18: Tier 1-2 | M18: Sourced (this pass) | N18: Brutal content (filicide, rape) — represent plainly, don't aestheticize. Source versions differ (Völundarkviða vs Þiðrekssaga's Velent), but the hamstringing-to-enslave core is constant. The 'crippling AS control' reading is strongly textual here (unlike Hephaestus, where lameness is congenital/accidental). | O18: MFM §5A (smith & technology taboo) — captured-maker pole, violent variant. PF §1 (capture), §3 (embedded remainder). Sub-cluster with Hephaestus. | P18: Völundarkviða (Poetic Edda) — full lay; Þiðrekssaga (Velent episode); Old English Deor (Welund stanza); depicted on the Franks Casket and Ardre stone VIII. | Q18: Völundarkviða strophes on the capture + hamstringing (Niðhad seizes him, cuts the sinews, sets him to the forge) through the revenge and winged escape; Deor ll. 1-13 (Welund's torment). | R18: Ursula Dronke (ed.), 'The Poetic Edda' Vol. II (Mythological Poems), edition + commentary on Völundarkviða; John McKinnell on the smith-legend; Leslie Webster on the Franks Casket. | S18: Confirm the hamstringing-to-prevent-escape and forced-labour framing are explicit in Völundarkviða (Dronke). Distinguish Eddic vs Þiðrekssaga versions. Keep the violence factual, not lurid. | U18: LOW-MODERATE — the captured-and-crippled-maker reading is about as directly textual as the cluster gets; main risk is importing a tidy 'craft-as-liberation' moral the bleak poem doesn't endorse (the escape leaves devastation, not justice). | V18: Pull Dronke's Völundarkviða strophe numbers; cite the Deor stanza; note the Franks Casket panel as material attestation. | W18: en.wikipedia.org/wiki/Wayland_the_Smith; vikingtimes.co.uk Völundarkviða (Poetic Edda; Deor; Þiðrekssaga) | X18: 2026-06-14 | Y18: Tier 1 | Z18: Tier 1 | AA18: Load-bearing | AC18: Not yet tested | AE18: Legacy — not yet tagged
A19: RF-008 | B19: RF-01 | C19: Rebel Blood / Embedded Remainder | D19: marked-lineage | E19: Hebrew Bible (Genesis); later Jewish/Christian interpretation | F19: Tubal-Cain — the Bible's first smith, 'forger of all instruments of bronze and iron,' whose craft is located in the cursed line of Cain rather than the godly line of Seth. | G19: Genesis 4:22 names Tubal-Cain, son of Lamech and Zillah, seventh from Cain, as the originator of metalworking — 'the forger of all instruments of bronze and iron.' His half-siblings are eponyms of the other arts: Jabal (herding/tents), Jubal (the lyre and pipe), with Naamah (weaving, in tradition). The whole technical-cultural toolkit is credited to the Cainite branch, immediately before Lamech's boast of killing and the Flood that wipes the line. | H19: Here the capture is GENEALOGICAL, not physical — no maker is bound, but the craft itself is assigned a bloodline. The dangerous, powerful knowledge (metal = tools AND weapons) is filed under the marked, violent lineage, quarantining the technology by tainting its source. Civilization's indispensable arts are acknowledged and simultaneously fenced off as belonging to the wrong, cursed branch of humanity. | I19: The taboo move: credit the craft, mark the craftsman's line. Later interpretation makes it explicit — Philo reads the metalwork as the 'iron passions' culminating Cain's violence; the placement next to Lamech's blood-boast and before the Flood frames metallurgy as belonging to the doomed, not the saved. The remainder (everyone keeps using metal) is licensed only after the source is morally cordoned. | J19: The craft outlives its quarantine completely — post-Flood humanity still forges, so the knowledge is plainly indispensable and embedded in all later culture; what the narrative retains is only the STAIN on its origin. The smith stays ambivalent ever after: Eliade reads the furnace as sacred rebirth (ore->refined), the same craft both holy and cursed. | K19: Hephaestus (RF-006 — later writers literally identify Tubal-Cain with Vulcan; sister Naamah ~ Venus); Wayland (RF-007); Prometheus (RF-002, gift that is also transgression); Azazel/Watchers (RF-003, forbidden metallurgy/weapon knowledge) | L19: Tier 1-2 | M19: Sourced (this pass) | N19: The 'technology taboo' valence is INTERPRETIVE (Philo onward), NOT stated in the verse — Gen 4:22 itself is fairly neutral, even read positively by some as human skill 'from day one.' Flag the competing reading. This is the §5A taboo POLE, distinct from the captured-maker pole (Tubal-Cain is neither bound nor crippled). Don't confuse with Tubal son of Japheth (Gen 10:2). | O19: MFM §5A (smith & technology taboo) — technology-taboo pole. PF §1, §2 (capture, canonize via genealogy). Sub-type distinct from the captured-maker pair. | P19: Genesis 4:17-24 (the Cainite genealogy; 4:22 Tubal-Cain; 4:23-24 Lamech's boast). Hebrew: loTesh kol-choresh nechosheth u-bharzel. | Q19: Gen 4:22 (the smith) read against 4:23-24 (Lamech's violence) and 4:25-26 (the Sethite alternative); cf. 1 Enoch 8 (Watchers' taught metallurgy). | R19: Philo, 'On the Posterity of Cain'; Mircea Eliade, 'The Forge and the Crucible' (smith ambivalence); Westermann, 'Genesis 1-11'; Gunkel, 'Genesis' (Cainite-vs-Sethite arts). | S19: Separate Tier 1 (verse credits Tubal-Cain with metallurgy) from Tier 2 (the cursed/taboo valence is interpretive). Surface the competing 'neutral/positive' reading. Confirm the seventh-generation and Lamech-boast adjacency. | U19: HIGH if the verse is read as a flat 'metallurgy is cursed' statement — that's a later interpretive layer, and a real counter-tradition reads the Cainite arts as neutral human achievement. The taboo is in the genealogy + reception, not the words. | V19: Confirm Westermann/Gunkel on the Cainite-arts structure; pull the Philo citation; mark the Watchers (1 Enoch 8) cross-link to RF-003. [v0.19.1] Dropped Supportive -> Source-pass: Interp Tier 3 cannot be Supportive/Load-bearing; metallurgy-curse reading needs secondary hardening. | W19: en.wikipedia.org/wiki/Tubal-cain; biblehub.com/genesis/4-22; alc.net.au biblical-forge-of-tubal-cain (Genesis 4:22; Philo; Eliade) | X19: 2026-06-14 | Y19: Tier 1 | Z19: Tier 3 | AA19: Source-pass | AC19: Not yet tested | AE19: Legacy — not yet tagged
A20: DF-001 | B20: DF-01 | C20: Demonized Feminine / Unadministrable Woman | E20: Babylonian / Mesopotamian | F20: Tiamat | G20: Presented as chaos dragon/mother defeated by Marduk. | H20: Prior mother-order is demonized to authorize new male kingship. | I20: Narrative heist: older generative power becomes chaos needing conquest. | J20: Her body remains the world; the demonized feminine is foundational. | K20: Ymir; Tlaltecuhtli; Leviathan; Coyolxauhqui | L20: Tier 1-2 | M20: Anchored (v0.20); tablet/line refs entered, primary NOT opened in-edition | N20: Not 'secretly good'; treat as crime scene / prior order. [v0.19] Cross-listed with PB-001 (same figure, different cluster); cite once. DF reading (demonized feminine) is distinct from PB reading (corpse-world). [v0.20 source-pass] Useful finding: the text itself stages the shift from protective mother to monster, so 'demonised' need not be imported from outside. Caveat recorded in the counter-reading column. Tiers untouched. | O20: MFM §7 / §8 | P20: Enuma Elis, Tablets I-IV. Same primary as PB-001; different reading. | Q20: Ee I: Tiamat refuses Apsu's plan to destroy their children (the sympathetic phase). Ee II-IV: she becomes the monstrous adversary who appoints Qingu and raises the eleven creatures. The demonisation arc is internal to the text and datable within it - that is the row's strongest evidence. Pin the Tablet I lines. | R20: Lambert, W. G., Babylonian Creation Myths (Eisenbrauns, 2013) = standard critical edition. Dalley, S., Myths from Mesopotamia, rev. ed. (OUP, 2000) = working translation. Talon, SAACT 4. eBL (electronic Babylonian Library) for the composite text and line numbering. | S20: Use MR-01 + MR-03 | U20: Medium until source pass complete | V20: Run model review, then source-pass [v0.20 source-pass] Pin Ee I lines for the refusal-of-Apsu passage. | W20: Lambert 2013, Babylonian Creation Myths, Eisenbrauns | Dalley 2000, Myths from Mesopotamia, OUP: Tablet I at p. 234, Tablet II at pp. 243-244, Tablet VI at p. 261 (pages verified via secondary quotation, not opened in-edition) | X20: 2026-07-29 | Y20: Tier 1 | Z20: Tier 2 | AA20: Supportive | AB20: DF-01's 'requires specialist mediation' element is absent. Tiamat is destroyed, not managed. Contrast DF-002 Lamashtu, where the warding apparatus is the entire point. | AC20: Partial fit | AD20: Same contested reading as PB-001: if Tiamat is primarily a cosmological principle, the gendered-administration frame is imported. The row is strongest on the internal protective-mother -> monster shift, weakest on the mediation claim. | AE20: Legacy — not yet tagged
A21: DF-002 | B21: DF-01 | C21: Demonized Feminine / Unadministrable Woman | E21: Mesopotamian | F21: Lamashtu | G21: Female being linked with infant death, miscarriage, disease, childbirth danger. | H21: Birth-threshold terror personified as dangerous female power. | I21: Fear becomes symbol; ritual system mediates danger. | J21: Childbirth terror and family vulnerability remain underneath demon form. | K21: Lilith; Lamia; Strix; Pazuzu warding pair | L21: Tier 1-2 | M21: Needs source pass | N21: Frame as druj-at-threshold, not Christian demon. [v0.19] Paired case with BW-001 (Pazuzu): birth-threshold warding; function-scan, not good-vs-evil. | O21: MFM §10 | P21: TBD: identify primary text/artifact | Q21: TBD: exact passage, tablet, chapter, hymn, codex plate, or oral-transcription source | R21: TBD: one reputable secondary source | S21: Use MR-01 + MR-03 | U21: Medium until source pass complete | V21: Run model review, then source-pass | Y21: Tier 1 | Z21: Tier 1-2 | AA21: Load-bearing | AC21: Not yet tested | AE21: Legacy — not yet tagged
A22: DF-003 | B22: DF-01 | C22: Demonized Feminine / Unadministrable Woman | E22: Jewish / later medieval drift | F22: Lilith | G22: Night demon / refusal figure in later popular story. | H22: Female sexual/autonomous refusal becomes demon grammar. | I22: Later tradition splits administrable woman from dangerous woman. | J22: Older night/demon material becomes autonomy symbol under pressure. | K22: Lamashtu; Lamia; Eve; witch figures | L22: Tier 1-2 | M22: Anchored; Blair is counter-voice; stays Quarantine | N22: Caveat: refusal-submission story is medieval; older Lilith material differs. [v0.19.1 source-pass] Dated strata: ancient night-demon (Isaiah/Talmud) vs medieval first-wife (Ben Sira, geonic c. 7th-10th c.) vs modern reclamation. Blair 2009 recorded as COUNTER-voice (verified thesis: lilith = night bird, not demon). Stays Quarantine. Tier unchanged. | O22: MFM §8 | P22: Isaiah 34:14 (lilit among Edom's ruins); b. Shabbat 151b; b. Niddah 24b; Alphabet of Ben Sira (medieval) for the equality/refusal scene. | Q22: Isa 34:14; b. Shabbat 151b; b. Niddah 24b; Ben Sira refusal scene - verify in-edition. | R22: Blair, De-Demonising the Old Testament (Mohr Siebeck, 2009) - COUNTER-voice: argues lilith is a night bird, NOT a demon. Do NOT cite as support for the demonized-feminine reading. | S22: Use MR-01 + MR-03 | U22: Medium until source pass complete | V22: Run model review, then source-pass [v0.19] SPLIT strata: (a) ancient lilitu night-demon, (b) medieval Alphabet of Ben Sira refusal-wife, (c) modern reclamation. Modern-overlay risk. [v0.19.1] Quarantine = handling discipline, not weak evidence. | W22: Blair 2009 (Mohr Siebeck), ISBN 9783161501319; thesis: era.ed.ac.uk/handle/1842/3480 | Y22: Tier 2 | Z22: Tier 3 | AA22: Quarantine | AC22: Not yet tested | AE22: Legacy — not yet tagged
A23: DF-004 | B23: DF-01 | C23: Demonized Feminine / Unadministrable Woman | E23: Greek | F23: Medusa | G23: Monster woman killed; head becomes weapon/trophy. | H23: Dangerous female face/body is made killable and then usable by hero/order. | I23: Female terror is captured and weaponized by authorized male heroics. | J23: The head keeps power after death. | K23: Lamashtu; Lilith; Coyolxauhqui; Kali caveat | L23: Tier 2 | M23: Partial; primary loci noted; secondary owed | N23: Many variants; avoid modern-only reduction. [v0.19.1 source-pass] Sympathetic rape/transformation backstory is OVIDIAN (Metamorphoses 4), later reception - do NOT fold into primary. If the row leans on it as primary, possible tier-conflict: FLAGGED, tier NOT changed (K9-K11). Secondary still owed. Support: partial. | O23: Comparative candidate | P23: [Pseudo-]Apollodorus, Bibliotheca; Hesiod, Theogony (Gorgon genealogy). NOT primary: Ovid, Metamorphoses 4 (later reception). | Q23: Apollodorus 2.4.2-3 (Medusa beheaded; head set on Athena's aegis/shield); Hesiod, Theog. (Gorgon lineage). | R23: NOT FOUND - secondary still owed. | S23: Use MR-01 + MR-03 | U23: Medium until source pass complete | V23: Run model review, then source-pass [v0.19] Source-pass: interpretation is version/iconography-dependent (Ovid = late reception); pin the version. | W23: Primary editions to confirm (Apollodorus 2.4.2-3; Hesiod Theogony). Secondary owed. | Y23: Tier 2 | Z23: Tier 3 | AA23: Source-pass | AC23: Not yet tested | AE23: Legacy — not yet tagged
A24: DF-005 | B24: DF-01 | C24: Demonized Feminine / Unadministrable Woman | E24: Mexica / Nahua | F24: Coyolxauhqui | G24: Dismembered moon/sister figure defeated by Huitzilopochtli. | H24: Female/sibling rebel body cut apart by solar-war order. | I24: Dismemberment stabilizes warrior/state mythology. | J24: Her broken body remains visible as image/memory/remainder. | K24: Tiamat; Medusa; Tlaltecuhtli | L24: Tier 2 | M24: Secondary verified; confirm FC folios then Sourced | N24: Mesoamerican source pass needed; do not overclaim before variants reviewed. [v0.19.1 source-pass] UPGRADE candidate - closes the Audit-Notes 'needs Sahagun book/chapter' item. Milbrath 1997 supports the political/solar-conquest reading. Keep living-tradition/appropriation care. Sourced only after exact FC Bk 3 folios confirmed in-edition. Tier unchanged (K9-K11). | O24: Comparative candidate | P24: Florentine Codex (Sahagun), Book 3 'The Origin of the Gods' (Coatepec narrative). Artifact: Great Coyolxauhqui monolith, Templo Mayor. | Q24: Bk 3 fols. ~1r-2v (incitement ~1v; decapitation/dismemberment ~2v) - confirm exact folios in-edition (Dibble & Anderson). | R24: Milbrath, 'Decapitated Lunar Goddesses in Aztec Art, Myth, and Ritual,' Ancient Mesoamerica 8 (1997): 185-206. [VERIFIED - supports solar-conquest reading] | S24: Use MR-01 + MR-03 | U24: Medium until source pass complete | V24: Run model review, then source-pass [v0.19] Source-pass: pin Sahagun book/ch. + Coyolxauhqui-stone scholarship; appropriation care (Nahua packet). | W24: Milbrath 1997, Ancient Mesoamerica 8:185-206 (Cambridge). cambridge.org/core/journals/ancient-mesoamerica | Y24: Tier 1 | Z24: Tier 2 | AA24: Source-pass | AC24: Not yet tested | AE24: Legacy — not yet tagged
A25: TR-001 | B25: TR-01 | C25: Trickster / Unauthorized Intelligence | E25: Mesopotamian | F25: Enki | G25: Clever operator helps humans, makes loopholes, works around Enlil's punishments. | H25: Bypass intelligence inside the official order. | I25: Order needs the trickster but cannot fully control him. | J25: Human survival often depends on his side-channel. | K25: Loki; Hermes; Anansi; Coyote; Quetzalcoatl | L25: Tier 1-2 | M25: Anchored (v0.20); the reed-wall loophole is the load-bearing detail | N25: Not pure good; systems operator and loophole-maker. [v0.20 source-pass] Complication recorded in the frame-test columns: in Tablet I, Enki's cleverness serves the senior gods by inventing a replacement labour force. That is the trickster acting FOR management. TR-01's diagnostic only describes the opposite direction. | O25: MFM §4 / user frame | P25: Atra-hasis, Tablet I (the proposal) and Tablet III i (the warning). Lambert & Millard 1969. | Q25: Atra-hasis I: Enki resolves the Igigi strike by proposing the manufacture of a substitute workforce. Atra-hasis III i: bound by an oath not to warn humanity, Enki addresses the reed wall of Atrahasis's hut so that Atrahasis overhears - a loophole, not a breach. Pin both passages; the reed-wall device is the cleanest trickster anchor in the epic. | R25: Lambert & Millard, Atra-hasis: The Babylonian Story of the Flood (1969; repr. Eisenbrauns 1999) = standard edition, with transliteration, translation and cuneiform drawings. Dalley 2000. Foster, Before the Muses. Compare Ee VI, where the same anthropogeny is attributed to Ea/Enki. | S25: Use MR-01 + MR-03 | U25: Medium until source pass complete | V25: Run model review, then source-pass [v0.20 source-pass] Pin III i lines; review whether TR-01's diagnostic needs a second direction. | W25: Lambert & Millard 1969 (repr. Eisenbrauns 1999), Atra-hasis | OB recension copied c. 1650 BCE under Ammi-saduqa; ~1,245 lines across 3 tablets, lacunose in places | X25: 2026-07-29 | Y25: Tier 1-2 | Z25: Tier 2 | AA25: Supportive | AB25: TR-01 predicts intelligence from below moving culture forward. In Atra-hasis I, Enki's cleverness ends a labour strike by manufacturing a replacement workforce - the trickster acting for management. The cluster's diagnostic has no slot for that direction. | AC25: Partial fit | AD25: 'Unauthorized' is arguably the wrong word throughout: Enki is a senior god whose interventions are authorised by his own rank. Read that way, he is not a boundary-crosser from below but a competent administrator outmanoeuvring a peer. | AE25: Legacy — not yet tagged
A26: TR-002 | B26: TR-01 | C26: Trickster / Unauthorized Intelligence | E26: Norse | F26: Loki | G26: Disruptive kin-trickster among gods; causes and solves problems; destabilizes order. | H26: Unlicensed intelligence inside ruling house. | I26: The system tolerates the trickster until remainder becomes existential. | J26: His offspring and consequences exceed the administrative order. | K26: Enki; Coyote; Anansi; Hermes | L26: Tier 1-2 | M26: Needs source pass | N26: Do not make Loki a simple rebel hero; ambivalent function. | O26: Comparative candidate | P26: TBD: identify primary text/artifact | Q26: TBD: exact passage, tablet, chapter, hymn, codex plate, or oral-transcription source | R26: TBD: one reputable secondary source | S26: Use MR-01 + MR-03 | U26: Medium until source pass complete | V26: Run model review, then source-pass | Y26: Tier 1 | Z26: Tier 2 | AA26: Supportive | AC26: Not yet tested | AE26: Legacy — not yet tagged
A27: TR-003 | B27: TR-01 | C27: Trickster / Unauthorized Intelligence | E27: Akan / West African | F27: Anansi | G27: Spider trickster wins stories/knowledge through cunning. | H27: Weak actor beats stronger order through story, deception, wit. | I27: Narrative itself becomes bypass technology. | J27: Stories remain portable power below formal hierarchy. | K27: Coyote; Raven; Loki; Hermes | L27: Tier 1-2 | M27: Needs source pass | N27: Important sub-Saharan line for less-administered monkey intelligence. | O27: Comparative candidate | P27: TBD: identify primary text/artifact | Q27: TBD: exact passage, tablet, chapter, hymn, codex plate, or oral-transcription source | R27: TBD: one reputable secondary source | S27: Use MR-01 + MR-03 | U27: Medium until source pass complete | V27: Run model review, then source-pass [v0.19] Source-pass: needs named Akan/tradition + collector; no flattening. | Y27: Tier 2 | Z27: Tier 2 | AA27: Source-pass | AC27: Not yet tested | AE27: Legacy — not yet tagged
A28: TR-004 | B28: TR-01 | C28: Trickster / Unauthorized Intelligence | E28: Indigenous North American | F28: Coyote | G28: Creator/disruptor; breaks rules, creates features of world, teaches by mistake. | H28: Monkey intelligence as error, hunger, sex, improvisation, and adaptation. | I28: Order emerges through mistakes rather than decree. | J28: Mischief remains as pedagogy. | K28: Anansi; Raven; Loki; Māui | L28: Tier 2 | M28: Citation fixed (Ramsey 1977); stays Quarantine | N28: Must specify nation/version; do not pan-Indigenous flatten. [v0.19.1 source-pass] CITATION FIX: secondary is Ramsey 1977 (Univ. of Washington Press), NOT the GPT 'Toelken, Coyote Was Going There, Utah, 1984' (a hybrid error). NOTE region mismatch: Ramsey = Oregon-country anthology (general Coyote scholarship); the specific earth-diver primary is the Pohonichi Miwok version in Kroeber 1907 (S-Central California) - do not conflate. Pan-Coyote flattening risk. Stays Quarantine. Tier unchanged. | O28: Comparative candidate | P28: Kroeber, 'Indian Myths of South-Central California' (UC Publ. AAE 4:4, 1907) - Pohonichi Miwok earth-diver (Coyote + duck retrieve earth -> world). | Q28: Pohonichi Miwok earth-diver - confirm exact myth/page in Kroeber 1907. | R28: Ramsey (ed.), Coyote Was Going There: Indian Literature of the Oregon Country (Univ. of Washington Press, 1977) - CORRECTED (GPT's 'Toelken, Utah, 1984' was a hybrid error). General Coyote-literature scholarship. | S28: Use MR-01 + MR-03 | U28: Medium until source pass complete | V28: Run model review, then source-pass [v0.19] QUARANTINE: do not use until tied to a named nation/version/collector. [v0.19.1] Motif Tier 3 reflects row-format/source-flattening, not denial of the motif in specific nations. | W28: Ramsey (ed.) 1977 (UW Press), ISBN 9780295957319 / 0295954418. | Y28: Tier 3 | Z28: Tier 3 | AA28: Quarantine | AC28: Not yet tested | AE28: Legacy — not yet tagged
A29: TR-005 | B29: TR-01 | C29: Trickster / Unauthorized Intelligence | E29: Greek | F29: Hermes | G29: Thief, messenger, boundary-crosser, guide, trickster. | H29: Boundary intelligence moves between systems and steals from authority. | I29: The order licenses him as messenger but he remains slippery. | J29: Trade, language, theft, travel, and mediation keep moving. | K29: Loki; Anansi; Eshu; Enki | L29: Tier 1-2 | M29: Needs source pass | N29: Bridge between trickster and official mediator. | O29: Comparative candidate | P29: TBD: identify primary text/artifact | Q29: TBD: exact passage, tablet, chapter, hymn, codex plate, or oral-transcription source | R29: TBD: one reputable secondary source | S29: Use MR-01 + MR-03 | U29: Medium until source pass complete | V29: Run model review, then source-pass | Y29: Tier 1 | Z29: Tier 1-2 | AA29: Supportive | AC29: Not yet tested | AE29: Ancient textual core | AF29: Homeric Hymn: theft, slippery testimony, Zeus's order to resolve, reciprocal exchange, honors. Modern court/non-compete language is analogy. | AG29: CO-01; TH-01; VA-01
A30: SC-001 | B30: SC-01 | C30: Scapegoat / Founding Violence | E30: Hebrew / Biblical | F30: Cain and Abel | G30: Brother kills brother; marked survivor; city/foundation implications. | H30: Fratricide and founding violence at origin of social order. | I30: Violence is marked, remembered, and managed through story. | J30: The mark preserves the wound and protects the survivor. | K30: Romulus/Remus; Osiris/Set; divine succession myths | L30: Tier 1-2 | M30: Needs source pass | N30: Use Girard carefully as contested model. | O30: MFM §6B | P30: TBD: identify primary text/artifact | Q30: TBD: exact passage, tablet, chapter, hymn, codex plate, or oral-transcription source | R30: TBD: one reputable secondary source | S30: Use MR-01 + MR-03 | U30: Medium until source pass complete | V30: Run model review, then source-pass | Y30: Tier 1 | Z30: Tier 2 | AA30: Supportive | AC30: Not yet tested | AE30: Legacy — not yet tagged
A31: SC-002 | B31: SC-01 | C31: Scapegoat / Founding Violence | E31: Roman | F31: Romulus and Remus | G31: Brother kills brother at founding of Rome. | H31: City begins with boundary violence and sibling succession. | I31: Founding murder becomes civic legitimacy. | J31: The dead brother remains under/around the wall. | K31: Cain/Abel; Set/Osiris; fratricide motifs | L31: Tier 1-2 | M31: Needs source pass | N31: Strong sacred geography + boundary claim row. | O31: MFM §6 / §6B | P31: TBD: identify primary text/artifact | Q31: TBD: exact passage, tablet, chapter, hymn, codex plate, or oral-transcription source | R31: TBD: one reputable secondary source | S31: Use MR-01 + MR-03 | U31: Medium until source pass complete | V31: Run model review, then source-pass | Y31: Tier 1 | Z31: Tier 1-2 | AA31: Supportive | AC31: Not yet tested | AE31: Legacy — not yet tagged
A32: SC-003 | B32: SC-01 | C32: Scapegoat / Founding Violence | E32: Egyptian | F32: Osiris / Set / Horus | G32: Brother murders king; body restored; inheritance contest continues through Horus. | H32: Dynastic murder, body restoration, inheritance legitimacy. | I32: Death/return manages succession and kingship theology. | J32: Dead king remains ruler of underworld; wound repeats ritually. | K32: Dionysus; Tammuz; Christ-type readings; Cain/Abel | L32: Tier 1-2 | M32: Needs source pass | N32: Avoid reducing rich devotional/theological layers. [v0.19] Cross-listed with DT-003 (Osiris). Connected narrative leans on Plutarch (late) - date it. | O32: MFM §6B | P32: TBD: identify primary text/artifact | Q32: TBD: exact passage, tablet, chapter, hymn, codex plate, or oral-transcription source | R32: TBD: one reputable secondary source | S32: Use MR-01 + MR-03 | U32: Medium until source pass complete | V32: Run model review, then source-pass | Y32: Tier 1-2 | Z32: Tier 2 | AA32: Supportive | AC32: Not yet tested | AE32: Legacy — not yet tagged
A33: FM-001 | B33: FM-01 | C33: Flood / Reset Memory | E33: Mesopotamian | F33: Atrahasis flood | G33: Humans become too numerous/noisy; gods send plagues/drought/flood; survivor warned. | H33: Population/labor/noise management becomes destruction/reset myth. | I33: Disaster becomes cosmic discipline; survival passes through side-channel warning. | J33: Humanity survives but under new conditions/limits. | K33: Noah; Deucalion; Manu | L33: Tier 1 | M33: Anchored (v0.20); episode sequence firm, line numbers approximate | N33: Strong connection to labor revolt and management crisis. [v0.20 source-pass] Two findings. (1) The labour revolt is in the text and is the causal engine of human creation - this substantiates the 'Atrahasis labor row' the Index lists as OWED, and it is a stronger RF-01 anchor than a flood row. (2) The flood is the THIRD control after plague and drought, and is followed by permanent demographic regulation. 'Reset' understates a graduated population-management sequence; FM-01's framing may need widening. Tiers untouched. | O33: MFM §4 / §11 | P33: Atra-hasis, Old Babylonian recension (scribe Ku-Aya, reign of Ammi-saduqa, c. 1650 BCE). Standard edition: Lambert & Millard 1969. Translations: Dalley 2000; Foster, Before the Muses. | Q33: Tablet I 1-6: 'when the gods instead of man did the work, bore the loads' - the epic opens on a labour crisis, not a creation. I 11-18: casting of lots (Anu/heaven, Enlil/earth, Enki/the sea-bolt). I ~37-90: the Igigi burn their tools and besiege Enlil's Ekur by night; their spokesman declares every god has joined. I ~170-260: Enki proposes a replacement worker; We-ila is slaughtered; Mami mixes clay with his flesh and blood; 'I have imposed your drudgery on man... I have released the yoke'. Tablets I-II: population growth and noise met with graduated checks (plague, then drought, then famine). Tablet III: the flood; Enki's warning; post-flood regulations on childbirth, infant mortality and celibate classes. ALL line numbers approximate - pin in Lambert & Millard. | R33: Lambert & Millard, Atra-hasis: The Babylonian Story of the Flood (1969; repr. Eisenbrauns 1999) = standard edition, with transliteration, translation and cuneiform drawings. Dalley 2000. Foster, Before the Muses. | S33: Use MR-01 + MR-03 | U33: Medium until source pass complete | V33: Run model review, then source-pass [v0.20 source-pass] Pin L&M line numbers; then split the labour-revolt row out of FM-001 into RF-01. | W33: Lambert & Millard 1969 (repr. Eisenbrauns 1999), Atra-hasis | OB recension copied c. 1650 BCE under Ammi-saduqa; ~1,245 lines across 3 tablets, lacunose in places | X33: 2026-07-29 | Y33: Tier 1 | Z33: Tier 1 | AA33: Load-bearing | AB33: None for FM-01 as written - but the flood is the third control after plague and drought, so 'reset' understates a graduated demographic-management sequence. | AC33: Fits | AD33: Reading the post-flood birth restrictions as population policy is a modern frame. The text may be offering cultic aetiology for existing social facts - infant mortality, celibate classes - rather than describing administrative control. | AE33: Legacy — not yet tagged
A34: FM-002 | B34: FM-01 | C34: Flood / Reset Memory | E34: Biblical | F34: Noah flood | G34: World corruption leads to divine flood; one family survives. | H34: Catastrophe is moralized; social reset framed as judgment. | I34: Trauma becomes doctrine and covenantal order. | J34: Survivors carry new obligations and memory of total reset. | K34: Atrahasis; Utnapishtim; Deucalion; Manu | L34: Tier 1 | M34: Needs source pass | N34: Compare without flattening into one universal flood. | O34: MFM §11 | P34: TBD: identify primary text/artifact | Q34: TBD: exact passage, tablet, chapter, hymn, codex plate, or oral-transcription source | R34: TBD: one reputable secondary source | S34: Use MR-01 + MR-03 | U34: Medium until source pass complete | V34: Run model review, then source-pass | Y34: Tier 1 | Z34: Tier 2 | AA34: Supportive | AC34: Not yet tested | AE34: Legacy — not yet tagged
A35: FM-003 | B35: FM-01 | C35: Flood / Reset Memory | E35: Hindu | F35: Manu flood | G35: Manu is warned/saved by fish; flood resets world. | H35: Ecological catastrophe memory plus chosen survivor/culture continuity. | I35: Survival knowledge becomes sacred transmission. | J35: Human line continues through warned survivor. | K35: Atrahasis; Noah; Deucalion | L35: Tier 1-2 | M35: Needs source pass | N35: Good flood memory comparator. | O35: Comparative candidate | P35: TBD: identify primary text/artifact | Q35: TBD: exact passage, tablet, chapter, hymn, codex plate, or oral-transcription source | R35: TBD: one reputable secondary source | S35: Use MR-01 + MR-03 | U35: Medium until source pass complete | V35: Run model review, then source-pass | Y35: Tier 1 | Z35: Tier 2 | AA35: Supportive | AC35: Not yet tested | AE35: Legacy — not yet tagged
A36: SG-001 | B36: SG-01 | C36: Sacred Geography / Land Claim | E36: Greek / Cretan | F36: Zeus on Mount Ida | G36: Divine child hidden/preserved on specific mountain/island landscape. | H36: Succession claim is rooted in place; mountain authorizes future king. | I36: Territory becomes story; story becomes shrine/legitimacy. | J36: The place preserves origin claim and cultic authority. | K36: Cave births; holy mountains; sacred springs | L36: Tier 2 | M36: Parked; passage thinner than the row's reading | N36: Use as property-law-with-incense example. [v0.19.1 source-pass] 'Mount Ida' specifically is later Cretan reception; Theogony supports concealment/preservation, NOT 'place confers sovereignty.' Sacred-geography reading is thinner than the source - FLAGGED for tier review, tier NOT auto-changed (K9-K11). Keep parked. Support: weak. | O36: MFM §6A | P36: Hesiod, Theogony (Rhea hides the infant Zeus in a Cretan cave; the stone is given to Kronos). | Q36: Theog. ~477-484 - supports concealment/preservation, NOT 'place confers sovereignty.' | R36: NOT FOUND - secondary still owed. | S36: Use MR-01 + MR-03 | U36: Medium until source pass complete | V36: Run model review, then source-pass [v0.19] PARK: SG-01 cluster underbuilt; harden with specific land-claim sources (resolve Cretan vs Troad Mount Ida) before citing. | W36: Primary to confirm (Hesiod, Theogony ~477-484). Secondary owed. | Y36: Tier 2 | Z36: Tier 3 | AA36: Source-pass | AC36: Not yet tested | AE36: Legacy — not yet tagged
A37: DT-001 | B37: DT-01 | C37: Death-Admin / Refusal of Closure | D37: trickster-defeat | E37: Maya / K'iche' (Popol Vuh) | F37: The Hero Twins, Hunahpu & Xbalanque — sons of the slain Maize God who descend into Xibalba, let themselves be killed, return, and defeat the Lords of Death by outwitting them, then rise as Sun and Moon. | G37: In the Popol Vuh, the K'iche' Maya epic, the Lords of Xibalba (the underworld) lure the Twins' father and uncle to a deadly ballgame and kill them; from the slain father's severed head, hung in a calabash tree, the maiden Xquic conceives the Twins. Grown, the Twins are summoned to Xibalba and survive a gauntlet of lethal trials (Houses of Knives, Cold, Jaguars, Fire, Bats) by seeing through the Lords' tricks. Knowing the Lords will never stop, they leap into an oven and are burned alive — a voluntary death from which they return, first as fish, then as wandering magician-tricksters who perform a 'kill-and-resurrect' act. Hearing of it, the Lords demand a performance; the Twins trick One Death and Seven Death into asking to be sacrificed too — and do not revive them. Death defeated, the Twins ascend as Sun and Moon. The narrative is attested in the ~1554 K'iche' text AND in hundreds of Classic Maya painted vases (c. 600-900 CE), so its core long predates the colonial-era writing-down. | H37: The death-administration here is a literal bureaucracy of lords who summon, test, and kill — a court that decides who lives, fed by sacrifice. The Twins don't beat it by force (they can't — the Lords just invent new trials) but by CUNNING: they master the rules, then rewrite the game, turning the Lords' own appetite for the spectacle of death against them. It's the trickster's answer to power that can't be out-muscled: out-think it, bait it into its own trap. | I37: This is the cluster's clearest case of the death-admin DEFEATED and DEMOTED rather than captured. The Twins don't just escape — they strip the Lords of Xibalba of their standing: in the full epic the death-lords are demoted, forbidden the great offerings and left only lesser ones. The 'refusal of closure' here reorganizes the sacrificial economy itself — who the dead-powers may demand tribute from. (Note the embedded capture: the Popol Vuh was also the K'iche' ruling lineages' charter, legitimizing their nobles — the epic that demotes Xibalba also props up an earthly elite.) | J37: The pattern that even the death-court can be beaten — by wit, by willingness to die strategically, by changing the rules — and that the powers who deal death can be brought low. It survives in the daily rebirth of the sun (Hunahpu) and the maize cycle: death as something repeatedly overcome, not merely endured. A genuinely anti-authoritarian remainder: the underworld bureaucracy is not eternal or all-powerful. | K37: Within the cluster: Osiris (DT-003), Christian resurrection (DT-006). Trickster cousins outside it: the rebel/trickster figures of RF-01 (Raven, Maui) who also outwit power. NOT a seasonal-fertility 'dying-rising god' in the Frazerian sense (see the cluster caveat). | L37: Tier 1-2 | M37: Sourced (this pass) | N37: The surviving Popol Vuh is a colonial-era alphabetic K'iche' text (recorded ~1554; oldest copy is Ximenez's ~1701 K'iche'/Spanish manuscript), so guard against reading Christian resurrection-theology INTO it — the Classic-period vase imagery (c. 600-900 CE) anchors the pre-contact core and shows the narrative predates any missionary contact. The Twins genuinely die and return (unlike Osiris, who rules the dead), but they apotheose into celestial bodies rather than resuming ordinary life — the 'resurrection' label fits more loosely than the word suggests. A living people's sacred book — analytic lens, not a verdict. | O37: PF Case 3 (refusal of closure) — the DEFEATED-DEATH pole: the death-admin is outwitted and demoted, not (as with Osiris) institutionalized. PF SS1-2. Sub-type = trickster-defeat. | P37: Popol Vuh (K'iche' Maya) — the Xibalba descent sequence; the Dennis Tedlock and Allen J. Christenson translations; the Classic Maya 'Resurrection Plate' and related painted ceramics (c. 600-900 CE). | Q37: Popol Vuh — the ballgame summons; the trials in the Houses of Xibalba; the oven self-sacrifice and return as fish/magicians; the trick that kills One Death & Seven Death; the apotheosis as Sun and Moon. | R37: Dennis Tedlock, 'Popol Vuh' (1985/1996); Allen J. Christenson, 'Popol Vuh' (2003); Michael D. Coe, 'The Maya' & on Classic Maya underworld iconography; Karl Taube on Maya myth. | S37: Is the trickster-defeat reading (death outwitted + Xibalba demoted) grounded in the Popol Vuh, and is the colonial-transmission caveat (don't import Christian resurrection) load-bearing? Confirm the Classic-ceramic attestation for the pre-contact core. | U37: MODERATE — the narrative and the 'death defeated by cunning' reading are well-supported by text + iconography; the risks are (a) importing Christian resurrection-categories via the colonial text, and (b) over-claiming the precise content of the Xibalba 'demotion' beyond what the translations support. The trickster-defeat structure is solid. | V37: Pull the Tedlock/Christenson Xibalba passages + a Classic 'Resurrection Plate' reference; keep the colonial-transmission caveat and the demotion-of-Xibalba detail anchored. | W37: ebsco.com (Maya Hero Twins); mayan.org & study.com (Popol Vuh / Xibalba defeat-by-trickery; Classic ceramics c.600-900 CE) | X37: 2026-06-14 | Y37: Tier 1 | Z37: Tier 1-2 | AA37: Load-bearing | AC37: Not yet tested | AE37: Legacy — not yet tagged
A38: DT-002 | B38: DT-01 | C38: Death-Admin / Refusal of Closure | D38: initiation-gated | E38: Greek (Homeric Hymn to Demeter; Eleusis) | F38: Persephone (Kore) & Demeter — the abducted daughter whose pomegranate-bound, cyclical return from the underworld both explains the seasons and founds the Eleusinian Mysteries, which offered initiates a better afterlife. | G38: In the Homeric Hymn to Demeter, Hades seizes Persephone (with Zeus's tacit consent) while she gathers flowers; her mother Demeter, goddess of grain, searches in grief, neglects the harvest, and brings famine. At Eleusis, disguised, Demeter nurses the prince Demophon (secretly trying to immortalize him in fire until interrupted) and commands a temple and rites be built — the charter of the Mysteries. Zeus relents and sends Hermes to retrieve Persephone, but Hades has tricked her into eating pomegranate seeds ('the food of the dead'), binding her to the underworld for part of each year. The brokered compromise — a third below, two-thirds above — turns Demeter's grief and joy into winter and spring. The rites at Eleusis then promised initiates a release from the fear of death and a blessed lot beyond the grave. | H38: Two power-moves stacked. First, the surface: a marriage-by-abduction sanctioned by the patriarch (Zeus) without the mother's or daughter's consent — the transfer of a young female between male houses, dressed as cosmic order (read alongside DF-01 / UF-01). Second, the death-admin: the underworld's claim on Persephone is irreversible once she's eaten its food, yet not total — she returns, cyclically. The community converts that partial-return into an institution that sells the same deal to mortals: death has a claim on you, but the right rites soften it. | I38: The purest 'administered access to a good death' in the cluster. The myth becomes the founding charter of a mystery-cult that gates a better afterlife behind INITIATION — and the gate is held by hereditary priestly families (the Eumolpidae and Kerykes; the Hierophant who appears 'in a blaze of light'), for nearly two millennia, until the cult is suppressed under a rising Christianity. Release from the fear of death is the product; initiation is the price; a hereditary caste is the mandatory intermediary. (The cult was also appropriated by the Athenian polis — capture layered on capture.) | J38: The genuine consolation the rites offered — that death is survivable, its terror removable — and the seasonal promise that loss is not final (spring returns). What the lens flags is how that consolation was enclosed: a universal fear answered by an initiation administered by a closed priestly lineage. The living signal (death's claim is not total) survives, but gated. | K38: Within the cluster: Osiris (DT-003, administered afterlife), Christian resurrection (DT-006, gated access to the victory). Outside: other mystery-cults (Dionysus / Orphic, Isis) offering a better afterlife; cf. CC-01 (access gated by an authorized intermediary). | L38: Tier 1-2 | M38: Sourced (this pass) | N38: The Hymn survives in a SINGLE damaged medieval manuscript (textual gaps), and the Mysteries' actual content was secret ('ineffable') — so claims about what initiates experienced are partly inference from veiled later accounts (Apuleius, etc.); don't overstate the specifics. The myth is heavily etiological ('the temple of today is the palace of yesterday'), projecting current cult-realities back onto the age of heroes. Persephone also belongs partly to the feminine-capture clusters (marriage-by-abduction) — cross-listed, not relocated. Ancient cult, not a living faith, but handled with the usual care. | O38: PF Case 3 (refusal of closure) — the INITIATION-GATED pole: death's non-finality packaged as an afterlife-blessing gated by priest-controlled initiation. PF SS1-2. Sub-type = initiation-gated. | P38: Homeric Hymn to Demeter (Hymn 2; ~495 lines), esp. the initiation-blessing (lines 480-482); the abduction (opening), the pomegranate-binding, and the seasonal compromise. | Q38: Hymn 480-482 (the initiation-blessing — blessed is the initiate, the uninitiated has no such lot once dead); the pomegranate that binds Persephone; the one-third (underworld) / two-thirds division. | R38: Helene P. Foley, 'The Homeric Hymn to Demeter' (1994); Walter Burkert, 'Greek Religion' & 'Ancient Mystery Cults'; N.J. Richardson, commentary on the Hymn; Kevin Clinton on Eleusinian priesthood. | S38: Is the initiation-gated reading (afterlife-blessing gated by priest-controlled initiation) grounded in the Hymn + Eleusinian evidence, and are the single-manuscript / secret-content caveats load-bearing? Keep the seasonal etiology distinct from the cult's afterlife-claim. | U38: MODERATE — the Hymn, the seasonal etiology, the afterlife-promise, and the hereditary priesthood are all well-attested; the risk is over-claiming the SECRET content of the Mysteries (unrecoverable) or flattening the rich myth to only the capture-reading (it is also a seasonal etiology and a mother-daughter story). The initiation-gated structure is solid; the interior of the rite is not. | V38: Pull Hymn 480-482 + the pomegranate and compromise lines (Foley); cite Burkert on the hereditary priesthood; keep the secret-content and single-manuscript caveats anchored. | W38: britannica.com (Eleusinian Mysteries); chs.harvard.edu & classicalia.co.uk (Hymn: pomegranate, seasonal compromise, initiation-blessing, hereditary priesthood) | X38: 2026-06-14 | Y38: Tier 1 | Z38: Tier 2 | AA38: Supportive | AC38: Not yet tested | AE38: Ancient textual core | AF38: Hymn to Demeter supports abduction, famine, negotiation, partial return, and rites; a universal exit clause is invention. | AG38: TH-01; CO-01
A39: DT-003 | B39: DT-01 | C39: Death-Admin / Refusal of Closure | D39: administered-return | E39: Ancient Egyptian; Pyramid/Coffin Texts -> Plutarch | F39: Osiris — murdered and dismembered king reassembled by Isis, who cannot return to the living and instead becomes Lord of the Duat and Judge of the Dead. | G39: Set, jealous of his brother the good king Osiris, traps him in a chest, drowns him, then dismembers the body (14 or 42 pieces) and scatters it. Isis, with Nephthys, Anubis, and Thoth, gathers the parts, embalms him (the first mummy), and revives him just long enough to conceive Horus. The resurrection is incomplete — Osiris cannot rejoin the living. He descends to the Duat and becomes its king: the judge before whom every soul is weighed in the Hall of Two Truths. | H39: A succession-murder (brother kills brother for the throne) is processed into a cosmology of death itself. The victim doesn't get his old life back — he is promoted sideways into running the realm of the dead. The community's terror of mortality is resolved by installing a relatable former king as its permanent administrator: death becomes a court with a known judge, not a void. | I39: The purest demonstration of capture in the cluster — the refusal of death's closure (Osiris overcomes Set's murder) is INSTITUTIONALIZED into the very apparatus that administers death. His story becomes the Book of the Dead; mummification re-enacts his reassembly; 'becoming an Osiris' is the entry rite for every corpse. The escape from death is canonized AS the death-bureaucracy, requiring a whole priesthood to operate it. | J39: What survives is the promise that death is survivable and judged, not arbitrary — embedded in every Egyptian funeral for three millennia. But it survives only in administered form: eternal life is real yet conditional, granted by a verdict, mediated by rites only the mortuary priesthood can perform. The remainder (death can be beaten) is delivered exclusively through the institution that monetizes the beating. | K39: Dumuzi (DT-004); Baal (DT-005); Persephone (DT-002); Inanna's descent (UF-001); Hero Twins (DT-001) | L39: Tier 1-2 | M39: Sourced (this pass) | N39: Osiris does NOT 'rise' to earthly life — he rules the dead; the 'resurrection' label is loose (see the cluster-level caveat on the contested 'dying-and-rising god' category, J.Z. Smith vs Frazer). No single ancient text tells the whole myth; the connected version is Plutarch's, late (c.100 CE) and Hellenized — don't read Plutarch back onto the Old Kingdom uncritically. [v0.19] Cross-listed with SC-003 (Osiris). | O39: PF Case 3 (resurrection as refusal of closure) — the CAPTURED pole (refusal becomes the administration). PF §1-2 (capture, canonize). Sub-type = administered-return. | P39: Pyramid Texts (Old Kingdom) & Coffin Texts (Middle Kingdom); Great Hymn to Osiris (18th Dyn.); Contendings of Horus and Set (20th Dyn.); Plutarch, De Iside et Osiride (c.100 CE). | Q39: Pyramid Texts Osiris/judgment spells; Book of the Dead spell 125 (the Weighing of the Heart / negative confession); Plutarch sections 12-19 (the murder, dismemberment, Isis). | R39: J. Gwyn Griffiths, 'The Origins of Osiris and His Cult'; Griffiths (ed.), 'Plutarch's De Iside et Osiride'; Jan Assmann, 'Death and Salvation in Ancient Egypt.' | S39: Is 'refusal becomes administration' over-clever or textual? Verify the 'becoming Osiris' funerary practice and the judge-of-the-dead role; keep the partial/non-earthly nature of his return explicit; distinguish Plutarch from the Egyptian sources. | U39: MODERATE — the death-administration reading is strongly supported by the actual mortuary cult; main risk is the 'resurrection' framing (he doesn't return to life) and retrojecting Plutarch's tidy narrative onto two millennia of varied sources. | V39: Pull Book of the Dead spell 125 + a Pyramid Text Osiris spell; cite Assmann on the funerary economy; foreground the Smith/Frazer caveat. | W39: en.wikipedia.org/wiki/Osiris_myth; ancient-philosophia.org/myths/osiris-myth (Pyramid/Coffin Texts; Plutarch De Iside) | X39: 2026-06-14 | Y39: Tier 1 | Z39: Tier 1-2 | AA39: Supportive | AC39: Not yet tested | AE39: Legacy — not yet tagged
A40: DT-004 | B40: DT-01 | C40: Death-Admin / Refusal of Closure | D40: death-debt | E40: Sumerian/Akkadian; Descent of Inanna / Ishtar | F40: Dumuzi / Tammuz — the shepherd-king sent to the underworld as Inanna's substitute, released only half the year while his sister Geshtinanna serves the other half. | G40: Inanna descends to the underworld, is stripped at seven gates, killed, and hung on a hook; Enki's creatures revive her — but the underworld's law forbids leaving without a substitute. The galla demons escort her up to claim one. She spares those found mourning her in sackcloth; finding Dumuzi instead enthroned in fine robes and NOT grieving, she fixes the eye of death on him. He flees, is caught, and is dragged below. His sister Geshtinanna offers herself; the verdict splits the year — Dumuzi half below, Geshtinanna half — and the seasons follow. | H40: Here death is run as a LEDGER. The underworld is a creditor that books every exit against a replacement — no release without a body to balance it. Survival is a transfer of debt: Inanna lives because Dumuzi is handed over; Dumuzi gets half a life because Geshtinanna covers the rest. Mortality is reframed not as void but as an account that must be settled, with substitutions permitted — the original 'pay the death-tax' system. | I40: The closure is never refused outright — it is NEGOTIATED and administered. The galla are bailiffs; the half-year compromise is a settlement; the whole apparatus presumes an authority that adjudicates who owes what to death. Grief itself is audited (mourners are exempt; the un-grieving Dumuzi is liable), turning even mourning into a compliance test. | J40: Life returns, but only as a managed alternation — the green half of the year is real, yet permanently mortgaged to the barren half. The refusal of closure survives as seasonal partial-return, not victory: nobody beats the ledger, they only reschedule it. The remainder is the rhythm itself — death holds the lien, life is the interest paid back each spring. | K40: Persephone (DT-002, the pomegranate-seed debt — near-identical structure); Osiris (DT-003); Baal (DT-005); Inanna (UF-001, the descending goddess herself) | L40: Tier 1-2 | M40: Sourced (this pass) | N40: Two text versions (Sumerian Inanna's Descent / Akkadian Ishtar's Descent) differ; the substitute-and-half-year resolution is the Sumerian tradition (incl. Dumuzi's Dream, Return of Dumuzi). 'Resurrection' is again loose — this is seasonal alternation by substitution, not a rising (cluster-level Smith/Frazer caveat applies). Dumuzi also appears as an antediluvian king (Sumerian King List) — keep the god/king strands distinct. | O40: PF Case 3 (refusal of closure) — the DEBT pole (return purchased by substitution). PF §4 (black ledger / debt). Sub-type = death-debt. | P40: Inanna's Descent to the Netherworld (Sumerian, ETCSL 1.4.1); Ishtar's Descent (Akkadian); Dumuzid's Dream (ETCSL 1.4.3); The Return of Dumuzid. | Q40: Inanna's Descent lines on the seven gates + 'no one ascends from the underworld unmarked' + the substitute scene; the Geshtinanna half-year resolution. | R40: Wolkstein & Kramer, 'Inanna: Queen of Heaven and Earth'; Dina Katz, 'The Image of the Netherworld in the Sumerian Sources'; Jacobsen, 'The Treasures of Darkness.' | S40: Confirm the 'no exit without a substitute' rule and the mourning-audit are explicit in the Sumerian text (ETCSL). Distinguish Sumerian vs Akkadian endings. Keep 'debt/ledger' as interpretation of an explicit textual rule, not imposed. | U40: LOW-MODERATE — the substitution-rule is directly in the text, so the 'ledger' read is well-anchored; risk is over-pressing the economic metaphor or treating the half-year as a universal 'resurrection.' | V40: Pull ETCSL 1.4.1 line refs for the substitute rule; cite Katz on netherworld law; foreground the Smith/Frazer caveat. | W40: en.wikipedia.org/wiki/Descent_of_Inanna_into_the_Underworld; worldhistory.org/article/215 (ETCSL 1.4.1; Wolkstein & Kramer) | X40: 2026-06-14 | Y40: Tier 1 | Z40: Tier 1-2 | AA40: Load-bearing | AC40: Not yet tested | AE40: Legacy — not yet tagged
A41: DT-005 | B41: DT-01 | C41: Death-Admin / Refusal of Closure | D41: death-combat | E41: Ugaritic / Canaanite; Baal Cycle (Ras Shamra) | F41: Baal Hadad — storm-king who cannot refuse Death's summons, is swallowed by Mot, and is restored only after his sister Anat butchers Death himself — a victory that resets every year. | G41: After winning kingship and building his palace on Mount Zaphon, Baal is challenged by Mot (Death), who demands he descend and submit. Even the storm-god cannot refuse: Baal goes down, is swallowed, dies, and the earth withers into drought. Anat searches, recovers his body, then confronts Mot directly — splitting him with a sword, burning, grinding, and winnowing him like grain across a field. An omen of oil and honey signals Baal's revival; the sun-goddess Shapash enforces the verdict; Baal returns to life and kingship — and the cycle will repeat. | H41: Death here is not a court or a ledger but an OPPONENT — a rival king (Mot) with his own dominion, who must be met by force. The community's answer to mortality is martial: power confronts Death as a peer, and survival is won by an ally willing to dismember Death itself. Yet the framing concedes that even the highest power must answer Death's summons first — you can beat Death, but only after Death has its turn, and only until next season. | I41: The refusal is real but ritualized into ETERNAL RE-ENACTMENT — Baal's death-and-return is the seasonal liturgy (drought = absence, rain = return), an annual drama the cult stages and depends on. Death is defeated on schedule, which is to say never finally; the cosmic order is maintained precisely by the repeating crisis, and the apparatus exists to manage the recurrence. | J41: What survives is rain, fertility, kingship — restored each year by a victory over Death. But the victory is structurally temporary: Mot is destroyed and yet returns; Baal reigns and yet must die again. The refusal of closure survives as a permanent rhythm of loss-and-recovery, cosmologically necessary rather than triumphant — order guaranteed by the very cycle that keeps killing the god. | K41: Dumuzi (DT-004) & Osiris (DT-003) — the sources themselves group these as structurally akin while noting they are not identical; Anat (cf. the avenging/uncontained feminine, UF-01); Persephone (DT-002) | L41: Tier 1-2 | M41: Sourced (this pass) | N41: The cross-figure 'dying-and-rising god' grouping is contested (J.Z. Smith vs Frazer) — flag at cluster level; the sources here explicitly note Baal/Tammuz/Osiris 'share a structural logic' but 'are not identical myths.' Tablets are fragmentary (KTU 1.1-1.6, lacunae); 'Baal' is a title (lord) as well as a name — note the Hadad identification. [v0.19] Related to OO-005 (Baal): keep the seasonal/never-final win; do not flatten into generic 'resurrection'. | O41: PF Case 3 (refusal of closure) — the COMBAT pole (Death personified and defeated by force, cyclically). PF §1, §6 (capture; the managed recurrence). Sub-type = death-combat. | P41: The Baal Cycle, KTU 1.1-1.6 (Ugaritic), esp. KTU 1.5-1.6 (Mot swallows Baal; Anat destroys Mot; Baal's return); 14th-13th c. BCE, Ras Shamra. | Q41: KTU 1.5 VI (Mot seizes and swallows Baal) -> KTU 1.6 II (Anat splits/burns/grinds Mot) -> KTU 1.6 III (oil-and-honey dream; Baal revives) -> 1.6 VI (Shapash's judgment). | R41: Mark S. Smith, 'The Ugaritic Baal Cycle' (Vols I-II); Dennis Pardee, 'Ritual and Cult at Ugarit'; N. Wyatt, 'Religious Texts from Ugarit.' | S41: Verify Baal 'cannot refuse' Mot's summons and Anat's dismemberment of Mot are textual (KTU 1.5-1.6). Keep the victory's cyclical/temporary nature explicit. Treat 'combat with Death' as the text's own personification, not a metaphor added. | U41: LOW-MODERATE on the myth (textually solid); MODERATE on comparison — resist flattening Baal into a generic 'resurrection'; the win is seasonal and never final, which is the point. | V41: Pull KTU 1.5-1.6 column refs (M.S. Smith edition); cite Pardee on the seasonal cult; foreground the Smith/Frazer caveat once at cluster level. | W41: en.wikipedia.org/wiki/Baal_Cycle; grokipedia.com/page/Baal_Cycle (KTU 1.1-1.6; M.S. Smith) | X41: 2026-06-14 | Y41: Tier 1 | Z41: Tier 2 | AA41: Supportive | AC41: Not yet tested | AE41: Legacy — not yet tagged
A42: DT-006 | B42: DT-01 | C42: Death-Admin / Refusal of Closure | D42: vindicated-return | E42: Early Christianity / New Testament; 1st c. CE | F42: The resurrection of Jesus — a crucified Galilean preacher proclaimed, within a few years of his execution, to have been raised bodily by God and vindicated over death; the founding claim of Christianity and the most influential instance of the 'refusal of closure' pattern this cluster tracks. | G42: Jesus of Nazareth is executed by Roman crucifixion (a fact even secular scholars call near-certain), buried, and — 'on the third day' — proclaimed risen, appearing to his followers. The earliest witness is not the later Gospels but a creed Paul says he 'received' and passed on (1 Cor 15:3-8: died for sins, buried, raised, appeared to Cephas, the Twelve, 500+, James, all the apostles), which a broad range of scholars — including secular ones — date to within a few years of the crucifixion (c. AD 30-36), very early rather than a slow legendary accretion. Unlike the seasonal gods, the resurrection is framed as singular and final: Christ 'dies no more; death has no more dominion over him' (Rom 6:9), a victory accomplished 'once for all' (Heb 9-10). | H42: Strip to the social-memory layer and the surface event is stark primate politics: an occupying imperial power (Rome) publicly executes a dissident — crucifixion, the maximal display of who-decides-who-lives — to close a perceived threat. The community's response refuses that closure: it insists the executed one was vindicated by the highest authority, that the powers who killed him did NOT get the last word. Whatever one makes of the claim's truth, its SOCIAL function is the inversion of a state execution into a verdict against the executioners — the cross, a Roman terror-instrument, becomes the central symbol of the vindicated victim. | I42: Here the pattern differs from Osiris. The refusal is not itself the bureaucracy (as with Osiris) — it is held as a singular, unrepeatable, historical-claimed event, and the priesthood-function grows up to administer ACCESS to it: the institution (clergy, sacraments, creed, canon) positions itself as the mandatory channel through which the victory is mediated to everyone else. The living signal — an innocent vindicated against worldly power — is canonized into an administered economy of salvation with an authorized interpreter at the gate. (This is the structural observation the lens makes; it says nothing about whether the underlying event occurred.) | J42: The most potent embedded remainder in the set: the claim that imperial execution is not the final word, that a tortured nobody can be the one God vindicates — a charge that has fueled both quietist consolation and genuinely subversive movements (abolition, liberation theology, civil-rights preaching) for two millennia. BUT the cluster's recurring irony is sharpest here: the same subversive remainder became the official cult of the empire that had wielded the cross (Constantine onward) — the refusal captured into the very kind of power it once indicted. | K42: Within the cluster: Osiris (DT-003, administered-return), Dumuzi (DT-004), Baal (DT-005) — but see the warning: a DIRECT 'dying-and-rising god' parallel is exactly what scholarship rejects. Better structural cousins: the vindicated-martyr pattern (2 Maccabees 7) and Jewish resurrection-hope (Daniel 12:2). | L42: Tier 1-2 | M42: Sourced (this pass) | N42: HIGHEST-CARE ROW IN THE MATRIX. (1) Central confession of ~2.4 billion living Christians; the analysis is strictly of how the NARRATIVE functions as social memory and within the capture lens — NOT a verdict on whether the resurrection happened. (2) THE CRUX: do NOT extend the cluster's grouping into a 'Jesus = Osiris / Dumuzi dying-rising god' claim — the Frazerian move J.Z. Smith (and Mark S. Smith) dismantled as 'uncritical comparison,' now broadly the scholarly consensus; even Mettinger, the category's main modern defender, grants Frazer's conception is indefensible and treats the resurrection as no borrowing. Its own structure (singular, bodily, 'once for all,' eschatological) is unlike the seasonal pattern. (3) 1 Cor 15 is very early creedal material, so 'late pagan borrowing' is doubly unsupported. (4) The execution was a Roman crucifixion; the 'collective Jewish guilt' / deicide reading of the Passion is a documented engine of antisemitism, rejected here and repudiated by major churches (Nostra Aetate, 1965). Analytic lens, not a debunking. | O42: PF Case 3 (resurrection as refusal of closure) — the keystone instance; the refusal canonized into an administered economy of salvation (PF SS1-2). Sub-type = vindicated-return (singular victory, distinct from Osiris's administered-return and the cyclical modes). | P42: 1 Corinthians 15:3-8 (the pre-Pauline creed); the Passion / empty-tomb narratives (Mark 15-16; Matt 28; Luke 24; John 20-21); Romans 6:9-10 and Hebrews 9:26-28, 10:10 (the 'once for all' framing); cf. Daniel 12:2; 2 Maccabees 7. | Q42: 1 Cor 15:3-8 ('delivered' / 'received'; the appearance list); Rom 6:9 ('death no longer has dominion'); Heb 9:28-10:10 (ephapax, 'once for all'); Mark 16:6 ('he is risen; he is not here'). | R42: Jonathan Z. Smith, 'Dying and Rising Gods' (Encyclopedia of Religion, 1987) & on Frazer; Mark S. Smith; Tryggve Mettinger, 'The Riddle of Resurrection' (2001); Dale Allison, 'The Resurrection of Jesus' (2021); Bart Ehrman & Gerd Ludemann on the early creed's dating. | S42: Is the structural (narrative -> administered-access) reading kept distinct from any truth-claim, and is the anti-'dying-rising-parallel' caveat (Smith) load-bearing? Confirm the creed-dating and 'once for all' anchors. Treat as a living faith; do not debunk. | U42: VERY HIGH — the highest in the matrix, on two axes. (a) Reductive comparative overreach (the 'just another dying-rising myth' claim) — explicitly rejected here on scholarly grounds (J.Z. Smith). (b) Mistaking functional analysis for a verdict on the faith — the lens describes how the narrative operates institutionally; it makes NO claim about the event's historicity or truth, and must not be read as doing so. Keep both guards visible whenever this row is cited. | V42: Pull 1 Cor 15:3-8 + Rom 6:9 + Heb 10:10; pull J.Z. Smith's 'Dying and Rising Gods' article and Mettinger's qualification; keep the truth-agnostic framing and the anti-parallel caveat both load-bearing. [v0.19] Not load-bearing. Cite only with both guards visible (anti-reductive + functional-not-verdict). Interpretation capped at Tier 2-3. [v0.19.1] Quarantine = handling discipline; motif evidence remains Tier 1. | W42: bmcr.brynmawr.edu (Mettinger rev.; J.Z. & M. Smith on the category); vridar.org (Smith vs Mettinger summary); medium.com/interfaith-now & beliefmap.org (1 Cor 15 creed dating; Ehrman / Ludemann) | X42: 2026-06-14 | Y42: Tier 1 | Z42: Tier 2-3 | AA42: Quarantine | AC42: Not yet tested | AE42: Legacy — not yet tagged
A43: BW-001 | B43: BW-01 | C43: Birth Threshold / Warding Power | E43: Mesopotamian | F43: Pazuzu | G43: Dangerous wind/demon figure used protectively against Lamashtu. | H43: Terrifying warding force used against worse threshold danger. | I43: Priesthood/ritual apparatus mediates danger through amulet/ward. | J43: Not good vs evil: harsh asha mask against druj at birth threshold. | K43: Lamashtu; protective grotesques; apotropaic figures | L43: Tier 1-2 | M43: Needs source pass | N43: Avoid Christian demon frame; function matters. [v0.19] Paired case with DF-002 (Lamashtu). BW-01 cluster underbuilt (single row). | O43: MFM §10 | P43: TBD: identify primary text/artifact | Q43: TBD: exact passage, tablet, chapter, hymn, codex plate, or oral-transcription source | R43: TBD: one reputable secondary source | S43: Use MR-01 + MR-03 | U43: Medium until source pass complete | V43: Run model review, then source-pass | Y43: Tier 1 | Z43: Tier 1-2 | AA43: Load-bearing | AC43: Not yet tested | AE43: Legacy — not yet tagged
A44: AD-001 | B44: AD-01 | C44: Asha / Druj Functional Lens | E44: Zoroastrian / Iranian lens | F44: Asha vs Druj | G44: Truth/order/alignment versus lie/distortion/rupture. | H44: Moral-cosmic function better than good/evil creature classes. | I44: Order becomes suspect when it turns into mandatory capture. | J44: Coherence survives outside simple lawful-good/lawful-evil categories. | K44: Lamashtu/Pazuzu; lawful order/capture; chaos/refusal | L44: Tier 1-2 | M44: Needs source pass | N44: Use as lens, not as claim that all traditions are Zoroastrian. | O44: User frame + comparative candidate | P44: TBD: identify primary text/artifact | Q44: TBD: exact passage, tablet, chapter, hymn, codex plate, or oral-transcription source | R44: TBD: one reputable secondary source | S44: Use MR-01 + MR-03 | U44: Medium until source pass complete | V44: Run model review, then source-pass [v0.19] Reclassified Methodology-only: AD-01 is a diagnostic lens, not an evidence-bearing myth cluster. | Y44: n/a (lens) | Z44: n/a (lens) | AA44: Methodology-only | AC44: Not yet tested | AE44: Legacy — not yet tagged
A45: AD-002 | B45: AD-01 | C45: Asha / Druj Functional Lens | E45: Cross-cultural diagnostic | F45: Lawful order as potential capture | G45: Order can appear benevolent while suppressing bypass/refusal. | H45: Lawful good and lawful evil both risk fascism when law becomes mandatory obedience. | I45: Priesthood-function: living signal becomes administrable structure/debt/enforcement. | J45: Remainder persists as refusal, humor, local practice, trickster intelligence. | K45: Asha/Druj; priesthood-function; anti-capture protocols | L45: Tier 1 | M45: Internal framework | N45: This is diagnostic architecture, not ancient-source claim. | O45: PF core diagnostic | P45: TBD: identify primary text/artifact | Q45: TBD: exact passage, tablet, chapter, hymn, codex plate, or oral-transcription source | R45: TBD: one reputable secondary source | S45: Use MR-01 + MR-03 | U45: Medium until source pass complete | V45: Run model review, then source-pass [v0.19] Reclassified Methodology-only: framework concept, not an evidence row. | Y45: n/a (lens) | Z45: n/a (lens) | AA45: Methodology-only | AC45: Not yet tested | AE45: Legacy — not yet tagged
A46: CC-001 | B46: CC-01 | C46: Sacred Contract / Covenant Capture | D46: vassal-treaty | E46: Ancient Near East — Hittite / Israelite | F46: Covenant as vassal treaty (suzerainty-treaty form ported to the sacred) | G46: Yahweh 'rescues' Israel from Egypt and binds them: obey the stipulations for blessing, disobey for curse, with heaven and earth as witnesses. Framed as divine love and election. | H46: A political-legal instrument — the suzerain/vassal treaty between two UNequal parties — is lifted into the sacred. Seat the deity in the great-king slot and the people in the vassal slot, and the whole community becomes a subject population with no negotiating position: loyalty or rebellion, nothing between. | I46: Capture + narrative heist: a contract is made cosmically permanent and unchallengeable. Because the great king is invisible, an interpreter becomes structurally necessary — the priest reads the treaty, declares the stipulations, pronounces blessing and curse, mediates suzerain and vassal. Political contract -> sacred contract -> mandatory intermediary. | J46: The contract FORM itself survives as the grammar of obligation; covenant theology's fixation on loyalty, betrayal, and punishment is the treaty's enforcement clause surviving as doctrine. The legal-political DNA stays legible under the sacred surface. | K46: Hittite suzerainty treaties (Mursili II – Duppi-Tessub); neo-Assyrian Vassal-Treaties of Esarhaddon; Deuteronomy / Exod 20 / Josh 24; cf. debt + Black Ledger (PF §4) | L46: Tier 1-2 | M46: Sourced (this pass) | N46: Founding row of CC-01 (Sacred Contract / Covenant Capture). Keep separable: the FORM-parallel is mainstream/strong; 'priesthood as mandatory interpreter' and 'conscious heist' are framework gloss, NOT stated by the treaty form. Reads Tier 1 (form) / Tier 2 (capture-intent & dating); bucketed 1-2. Dating contested (see Overclaim Risk). | O46: MFM §7A; PF §1, §4 (capture, Black Ledger) | P46: Treaty of Mursili II with Duppi-Tessub of Amurru (Goetze trans., Pritchard ANET p.203); Vassal-Treaties of Esarhaddon (Wiseman 1958); Deuteronomy (overall structure); Exod 20:2; Deut 28; Josh 24 | Q46: Treaty preamble formula ('These are the words of the Sun Mursili, the great king...') vs Exod 20:2; treaty curse-section vs Deut 28; deposition/reading clause vs Deut 31:9-13 | R46: Mendenhall, 'Covenant Forms in Israelite Tradition,' Biblical Archaeologist XVII (1954) 50-76, and Law and Covenant in Israel and the ANE (1955); Kline, 'The Two Tables of the Covenant' (WTJ); Korosec, Hethitische Staatsvertraege (1931); neo-Assyrian counter-model assoc. w/ Weinfeld, Deuteronomy and the Deuteronomic School (1972) — VERIFY attribution | S46: MR-01 (run, below) + MR-05 (priesthood-function scan) | T46: MR-01 verdict: FORM-parallel = Tier 1, well attested (Mendenhall/Korosec; Mursili preamble ~ Exod 20:2). Capture-intent gloss + Hittite-vs-Assyrian dating = Tier 2 / contested. Strongest counter = neo-Assyrian model (Esarhaddon treaties): if Deut's form is 7th-c. Assyrian not Bronze-Age Hittite, the row stays valid but relocates in time and LOSES any 'deep/early memory' claim. Note: even proponents disagree on which verses map to which treaty element. | U46: MED-HIGH if 'heist' is read as conscious scribal borrowing or as proof of priestly conspiracy. Form-correspondence =/= conscious dependence; could reflect a shared ANE legal koine. Do NOT let this row carry an early-vs-late dating claim — that debate is unresolved. | V46: Confirm Weinfeld / neo-Assyrian attribution; pull the two preamble texts (Mursili vs Exod 20:2) side by side; add sibling rows to CC-01 (debt-bondage, loyalty-oath). | W46: thegospelcoalition.org/themelios (covenant-treaty-and-prophecy); meredithkline.com (Two Tables of the Covenant) | X46: 2026-06-14 | Y46: Tier 1 | Z46: Tier 2 | AA46: Load-bearing | AC46: Not yet tested | AE46: Legacy — not yet tagged
A47: CC-002 | B47: CC-01 | C47: Sacred Contract / Covenant Capture | D47: debt-release | E47: Hebrew Bible (Holiness & Deuteronomic Codes); ANE debt-cancellation | F47: The Jubilee & the Year of Release — debt-slavery limited and periodically cancelled because the people and the land already belong to YHWH. | G47: Leviticus 25 mandates that every 50th year (after seven sabbatical cycles) the shofar sounds, debts are forgiven, Israelite debt-slaves freed, and ancestral land returned to its original families; Deuteronomy 15 sets a 7-year 'release' (šĕmiṭṭâ) cancelling debts and freeing debt-servants ('do not send them away empty-handed'). The rationale is ownership: 'they are my servants whom I brought out of Egypt' (Lev 25:42), and the land 'is mine' (Lev 25:23) — so no Israelite is permanently sold and no land permanently alienated. | H47: Two creditors are stacked. Human creditors can bind the poor into bondage — real, enforceable debt — but a HIGHER creditor (the deity) holds a prior lien on every person and every acre, and that senior claim periodically voids the junior ones. The poor survive not because debt is abolished but because all human debt is subordinated to a master-debt owed to God: you cannot be permanently owned by your neighbor because you are already owned by YHWH. | I47: The black ledger made statutory — life, land, and labor booked as obligations, with the ultimate account held by the divine party to the covenant. The release valve (Jubilee/šĕmiṭṭâ) prevents permanent capture by human elites while CANONIZING permanent capture by the covenant itself; freedom is reframed as a transfer of ownership from a human master to the divine one (servants of YHWH, not of men). | J47: Genuinely protective — the cluster's most double-edged case. The same logic that asserts total divine ownership also installs a real, recurring check on predatory wealth, land-monopoly, and hereditary debt-slavery; 'proclaim liberty (dĕrôr) throughout the land' (Lev 25:10) is emancipatory, not only proprietary. The remainder is a structural mercy embedded in the contract — even if, as the texts concede, the Jubilee may never have been fully observed. | K47: Covenant-as-vassal-treaty (CC-001); Esarhaddon's oath (CC-003); ANE 'clean slate' edicts (mīšarum / andurārum); Nehemiah 5 (debt remission) | L47: Tier 1-2 | M47: Sourced (this pass) | N47: AMBIVALENT — read as capture (divine master-debt) AND as liberation (anti-predation mercy); hold both, don't flatten to either (guards against the totalizing-lens failure). The Hebrew dĕrôr ('liberty') is a loanword from Akkadian andurārum, the Mesopotamian royal debt-cancellation term — strong evidence the institution draws on ANE statecraft. NB: no biblical record the Jubilee was ever actually practiced (possible ideal/utopian law). Living Jewish & Christian scripture — analytic lens, not a verdict on the tradition. | O47: PF §4 (black ledger / debt) — the ECONOMIC mechanism of covenant capture. Sub-type = debt-release. | P47: Leviticus 25:8-55 (Jubilee, Holiness Code); Deuteronomy 15:1-18 (the release year); Exodus 21:1-6 & 23:10-11 (earlier slave/fallow law); cf. Isaiah 61:1; Nehemiah 5. | Q47: Lev 25:10 (proclaim dĕrôr), 25:23 (the land is mine), 25:42 (they are my servants); Deut 15:1-2, 12-15 (release + 'not empty-handed'). | R47: Michael Hudson, '...and forgive them their debts' (Bronze-Age clean-slate background); Moshe Weinfeld, 'Social Justice in Ancient Israel'; Jacob Milgrom, 'Leviticus' (AB) on Lev 25. | S47: Hold the capture/liberation tension explicitly — does the row honor both? Confirm the andurārum->dĕrôr loan and the divine-ownership rationale (Lev 25:23, 42). Note the 'never observed' caveat. | U47: HIGH if read as purely sinister 'capture' — the protective/anti-predation function is real and central; equally HIGH if read as purely liberatory — the divine-ownership claim is the frame. The honest reading is the doubled creditor. | V47: Pull Lev 25 + Deut 15 verse refs (Milgrom); cite Hudson on mīšarum; keep the ambivalence load-bearing. | W47: oxfordbiblicalstudies 'Release from Debt'; cadtm.org 'Long Tradition of Debt Cancellation' (Lev 25; Deut 15; andurārum) | X47: 2026-06-14 | Y47: Tier 1 | Z47: Tier 2 | AA47: Supportive | AC47: Not yet tested | AE47: Legacy — not yet tagged
A48: CC-003 | B48: CC-01 | C48: Sacred Contract / Covenant Capture | D48: loyalty-oath | E48: Neo-Assyrian (Akkadian); cf. Deuteronomy | F48: Esarhaddon's Succession Treaty (adê) — the 672 BCE imperial loyalty oath whose curse-formulae closely parallel Deuteronomy 28, raising the question whether the covenant's enforcement-apparatus is theologized Assyrian statecraft. | G48: In 672 BCE the Assyrian king Esarhaddon had his empire (and, on the maximal reading, vassals) swear an adê — a loyalty oath/treaty binding them to uphold the succession of his heir Ashurbanipal, enforced by a long catalogue of horrifying curses on oath-breakers. The treaty has the familiar shape — historical prologue, stipulations, blessings and curses — and several of its curse-motifs (siege-cannibalism, scattering / exile) align strikingly with the curses of Deuteronomy 28:20-44. | H48: This is the bare political instrument behind the sacred contract: a ruler manufacturing binding loyalty by making subjects SWEAR, under self-cursing oath, to a succession that serves him — obligation produced by terror of the curse. When the same machinery turns up in a covenant with a god, the question sharpens: is the divine covenant a unique revelation, or the standard Near Eastern loyalty-oath with the suzerain's name changed to YHWH? | I48: The strongest counter-row in the cluster, built as evidence against the deep-memory claim. If Deuteronomy's curse-apparatus borrows from the EST (Weinfeld; Steymans; Levinson & Stackert), then the covenant's enforcement layer is datable 7th-century imperial technology — capture and canonization caught in the act: a political oath-form sacralized into scripture between 672 and 622 BCE. | J48: The parallel cuts both ways and the debate is live — so this row deliberately sharpens rather than settles. What survives either way is the formal kinship: covenant and loyalty-oath share a curse-grammar, whether by direct borrowing or by common Near Eastern inheritance. The remainder is the discomfort the resemblance produces for any 'wholly unique covenant' reading. | K48: Covenant-as-vassal-treaty (CC-001 — its direct counterpart); Hittite treaties; debt-bondage / Jubilee (CC-002); Deuteronomy 28 | L48: Tier 1-2 | M48: Sourced (this pass) | N48: LIVE SCHOLARLY DEBATE — the direct-borrowing thesis (Weinfeld 1965; Steymans 1995; Levinson & Stackert 2012) is strong but CONTESTED: the 2012 Tell Tayinat find prompted a challenge arguing the empire-wide oath may not have bound western vassals like Judah, questioning how Judahite scribes accessed the adê. Present BOTH sides; do not assert borrowing as settled. The structural treaty-parallel is broadly accepted even where direct dependence is disputed. | O48: PF §1-2 (capture, canonize) — the FORM / ENFORCEMENT mechanism; the strongest counterargument to CC-001 made into a row. Sub-type = loyalty-oath. | P48: Esarhaddon's Succession Treaty / Vassal Treaties of Esarhaddon (SAA 2 6), 672 BCE; the Tell Tayinat copy (2012); read against Deuteronomy 28:20-44 & 13. | Q48: EST §56 curses vs Deut 28:20-44; the Tayinat §§53-55 (deities from Palestine); the divine-witness / curse list (SAA 2 6:414-465). | R48: Moshe Weinfeld, 'Deuteronomy and the Deuteronomic School' & 'The Loyalty Oath in the ANE' (UF 8); H.U. Steymans (1995); Levinson & Stackert (2012); contra: the Tell Tayinat-based reassessment of vassal inclusion. | S48: Present the borrowing thesis AND its challenge fairly; separate the strong structural parallel from the disputed direct-dependence claim. Verify the 672 BCE date and the specific Deut 28 curse parallels. | U48: HIGH if 'Deuteronomy copied Esarhaddon' is stated as fact — it is a leading but contested hypothesis; the safe claim is formal / structural kinship within the ANE treaty tradition. Don't let the row's rhetorical force outrun the evidence. | V48: Pull SAA 2 6 curse lines + Deut 28 parallels (Levinson & Stackert); cite the Tayinat reassessment as the counter; keep the debate visible. | W48: bibleinterp.arizona.edu Deuteronomy/Esarhaddon curses; academia.edu 'Esarhaddon's Succession Treaty at Tell Tayinat' (SAA 2 6; Deut 28) | X48: 2026-06-14 | Y48: Tier 1 | Z48: Tier 2 | AA48: Load-bearing | AC48: Not yet tested | AE48: Legacy — not yet tagged
A49: UF-001 | B49: UF-01 | C49: Uncontained / Co-opted Feminine | D49: harnessed-autonomy | E49: Mesopotamian — Sumerian (Inanna) / Akkadian-Babylonian-Assyrian (Ishtar) | F49: Inanna / Ishtar — Queen of Heaven: love, sex, war, sovereignty, Venus, descent | G49: One goddess of sexual love AND war AND political power; she descends to the netherworld and returns, seizes the me (divine offices), proposes to Gilgamesh and looses the Bull of Heaven when refused, and legitimizes kings through the sacred marriage. Patron of Eanna at Uruk. | H49: A single female figure holds every domain a later patriarchal order prefers to split and parcel out — eros, violence, fertility, sovereignty, death-passage. She is power before it has been made administratively safe: the 'furnace with a face,' not the virgin/mother/whore grid. | I49: NOT demonization here but CO-OPTION. The sacred-marriage rite harnesses her sexual-divine authority to legitimize male kingship (king-as-Dumuzi joins priestess-as-Inanna); her power sanctions the throne rather than being monstered. Capture by elevation-and-attachment, not by splitting. | J49: The unsplit goddess persists in the hymns and the Descent; her refusal to be reduced to wife/mother survives even inside the rite that instrumentalizes her. Later syncretism (Astarte, Aphrodite, Venus) carries fragments forward. | K49: Kali (DF-006, also un-demonized in tradition); Astarte / Aphrodite / Venus (lossy); cf. sovereignty-legitimation (OO-01) | L49: Tier 1-2 | M49: Sourced (this pass) | N49: Founding row of UF-01 (Uncontained / Co-opted Feminine), split out from DF-01. The CO-OPTION pole: power harnessed via sacred-marriage kingship-legitimation, not demonized. Keep syncretism (Ishtar = Astarte = Aphrodite = Venus) marked, not flattened. | O49: MFM §9 ('furnace with a face'); §8 (feminine under capture); PF §1 (capture) | P49: Inanna's Descent to the Netherworld (Sum.) / Descent of Ishtar (Akk.); Inanna and Enki (the me); Exaltation of Inanna (nin-me-sara, Enheduanna); Gilgamesh Tablet VI (proposal, Bull of Heaven); Dumuzi-Inanna love songs / Iddin-Dagan A; Uruk Vase; Burney 'Queen of the Night' relief (attribution debated) | Q49: Descent (her seven me / death + return); Gilgamesh VI 1-79 (proposal + lover-list); Iddin-Dagan A (sacred-marriage legitimation); Enheduanna's exaltation lines | R49: Rivkah Harris, 'Inanna-Ishtar as Paradox and a Coincidence of Opposites,' History of Religions 30/3 (1991) 261-78; Jacobsen, The Treasures of Darkness; Bahrani, Women of Babylon ('alterity'); Abusch, 'Ishtar's Proposal and Gilgamesh's Refusal,' HR 26 (1986); Frymer-Kensky, In the Wake of the Goddesses; Meador (Enheduanna); sacred-marriage/kingship: Steinkeller (1999), Jones JAOS 123 (2003), Lapinkivi (2004, critical on literal rite) | S49: MR-01 (run, below) + MR-04 (counterexample hunt — she partly IS one for DF-01) | T49: MR-01: Tier 1 for the coincidence-of-opposites (Harris) — fuses sex/war/sovereignty/descent, breaks virgin/mother/whore. She is NOT demonized: exalted for millennia. The capture that hit her was CO-OPTION (sacred-marriage legitimation of male kingship). DF-01 split DONE: she anchors UF-01's co-option pole; Kali (UF-002) the uncontained pole. | U49: HIGH if read as 'demonized goddess' — she wasn't. Don't flatten Ishtar = Astarte = Aphrodite = Venus (Harris warns outsiders level her distinctively Mesopotamian features). Sacred-marriage LITERAL enactment is debated (symbolic vs physical; Lapinkivi) — assert the legitimation-function + hymns, flag the enactment. Enheduanna authorship = attribution. | V49: Pull Descent + Gilgamesh VI + Iddin-Dagan A passages; confirm Frymer-Kensky / Lapinkivi cites; populate UF-01 (Athena, Durga, Sekhmet). | W49: jstor.org/stable/1062957 (Harris); en.wikipedia.org/wiki/Inanna; oracc.museum.upenn.edu/amgg (Inana/Istar) | X49: 2026-06-14 | Y49: Tier 1 | Z49: Tier 2 | AA49: Supportive | AC49: Not yet tested | AE49: Mixed — separate layers | AF49: Keep distinct Inanna/Ishtar sources and living reception; TH-001 treats only the named descent composition. | AG49: TH-01
A50: UF-002 | B50: UF-01 | C50: Uncontained / Co-opted Feminine | D50: uncontained | E50: Hindu | F50: Kali | G50: Terrifying goddess of time, death, blood, liberation, fierce motherhood. | H50: Fierce feminine power resists polite/administered womanhood. | I50: Not simply demonized; ritualized power that can exceed control. | J50: The furnace with a face: whole feminine not split into safe roles. | K50: Inanna/Ishtar; Tiamat; Durga; Sekhmet | L50: Tier 1-2 | M50: Secondary verified; confirm primary (motif) | N50: Member of UF-01 (Uncontained / Co-opted Feminine) — the uncontained/unsplit 'furnace with a face' pole (paradox, not kingship co-option). Not a demon in her own tradition. [v0.19.1 source-pass] Primary anchored to Devi Mahatmya ch. 7 (+ ch. 11 stuti); Kinsley ch. 8 verified. The modern 'resistance to administered womanhood' reading stays flagged as interpretive. Living-tradition care. Tier unchanged. | O50: MFM §9 | P50: Devi Mahatmya (Markandeya Purana), the Candi. | Q50: Ch. 7 (Kali springs from Durga's brow, slays Canda & Munda -> Camunda); ch. 11 (Narayani Stuti) - confirm chapter numbering in chosen recension. | R50: Kinsley, Hindu Goddesses (Univ. of California Press, 1988), ch. 8 (Kali). [VERIFIED - confirm page] | S50: Use MR-01 + MR-03 | U50: Medium until source pass complete | V50: Run model review, then source-pass [v0.19] Source-pass: too broad; narrow to a specific text/tradition (Devi Mahatmya vs Tantric vs Bengali devotional). | W50: Kinsley 1988, Hindu Goddesses (UC Press). doi.org/10.1525/9780520908833 | Y50: Tier 2 | Z50: Tier 3 | AA50: Source-pass | AC50: Not yet tested | AE50: Legacy — not yet tagged
A51: UF-003 | B51: UF-01 | C51: Uncontained / Co-opted Feminine | D51: constituted | E51: Greek (Athena) / cf. Roman Minerva | F51: Athena / Pallas — virgin patron of Athens; wisdom, craft, strategic war; born from Zeus's head | G51: Zeus swallows the pregnant Metis ('wiser than all gods') to forestall a prophesied son who would overthrow him; Athena is born fully armed from his head. Virgin (Parthenos), patron of Athens, protector of kings, champion of male heroes; in the Eumenides she casts the deciding vote acquitting the matricide Orestes and tames the Furies into civic goddesses. | H51: Female intelligence (Metis) is ingested by the sovereign and reissued as a motherless, armed daughter loyal to the throne. She is power authored to serve the order, not a power the order had to subdue — the de-sexualized inverse of Inanna. | I51: CO-OPTION at the limit — and she becomes its agent. The Metis-swallowing narrates the ORIGIN of co-option (sovereign absorbs female cunning); in the Eumenides she enacts it: votes 'for the male,' founds the Areopagus court, converts the old female Furies into tamed civic goddesses. Capture so complete it turns constitutive. | J51: Metis persists inside Zeus as his 'wise counsel' (Metieta); the Furies survive as the honored Semnai Theoi — old female power not destroyed but subordinated and incorporated. The remainder is the absorbed thing still working under new management. | K51: Inanna/Ishtar (UF-001, harnessed-sexuality pole); Kali (UF-002, uncontained pole); cf. sovereign-deputy (OO-01); Minerva (Roman, lossy) | L51: Tier 1-2 | M51: Sourced (this pass) | N51: SPECTRUM within UF-01: Athena is the CONSTITUTED/manufactured pole (authored pre-harnessed) vs Inanna the HARNESSED-autonomy pole (a real sovereign goddess later co-opted) vs Kali the UNCONTAINED pole (not co-opted at all). Arguably the cluster's self-portrait: a co-opted figure who becomes an AGENT of co-option (tames the Furies). OO-01 adjacency is real (sovereign's deputy). Don't read her as a 'suppressed goddess' — her elevation IS the capture. Keep Athena=Minerva marked. | O51: MFM §8-9 (feminine under capture / co-option); PF §1, §3 (capture, embedded remainder) | P51: Hesiod, Theogony 886-900, 924-929 (Metis swallowed; birth from head); Aeschylus, Eumenides (the vote; 'no mother bore me / I honor the male'; Areopagus founding; Furies -> Semnai Theoi); Apollodorus, Bibliotheca 1.20; Parthenon east-pediment birth scene; Tier-3 lead: Linear B a-ta-na potnia (Knossos) | Q51: Theogony Metis-swallowing + head-birth lines; Eumenides Athena's vote-speech + the Furies' transformation; Apollo's 'mother is not the true parent' argument | R51: R.P. Winnington-Ingram, 'Clytemnestra and the Vote of Athena,' JHS 68 (1948); Froma Zeitlin, 'The Dynamics of Misogyny: Myth and Mythmaking in the Oresteia,' Arethusa 11 (1978) — VERIFY; Detienne & Vernant, Cunning Intelligence in Greek Culture and Society (Metis) | S51: MR-01 (run, below) + MR-04 (boundary: OO-01 vs UF-01) | T51: MR-01: Tier 1 for the events (Metis/birth, the Eumenides vote, virgin patron). Strongest, most textually explicit UF-01 row — and the cluster's self-portrait: the Metis myth narrates the ORIGIN of co-option, and in the Eumenides she becomes its agent (co-opts the Furies). Distinction within UF-01: constituted (Athena) vs harnessed-autonomy (Inanna) vs uncontained (Kali). Hold the Eumenides DUAL reading: founding of jury-law AND naturalization of father-right. Tier-3 caveat: no autonomous pre-patriarchal Athena as fact. | U51: HIGH if read as 'suppressed/demonized goddess' — she was venerated; her elevation IS the capture. Don't assert a pre-patriarchal Minoan/Mycenaean autonomous Athena (Linear B a-ta-na is a lead, not proof — Tier 3). The 'I honor the male' line is Aeschylus's dramatic argument; the play also reads as rule-of-law founding. Don't flatten Athena=Minerva. | V51: Pull Theogony + Eumenides passages; confirm Zeitlin cite; decide whether UF-01 needs a sub-tag for the constituted/harnessed/uncontained spectrum; consider OO-01 cross-link | W51: theoi.com/Olympios/AthenaMyths (Hesiod); cambridge.org JHS 'Clytemnestra and the Vote of Athena'; en.wikipedia.org/wiki/Metis_(mythology) | X51: 2026-06-14 | Y51: Tier 1 | Z51: Tier 2 | AA51: Supportive | AC51: Not yet tested | AE51: Mixed — separate layers | AF51: Metis birth and Eumenides court belong to different texts. Athena is not herself a pre-office rebel captured by promotion. | AG51: AD-01
A52: UF-004 | B52: UF-01 | C52: Uncontained / Co-opted Feminine | D52: constituted | E52: Hindu (Shakta) / pan-Indian; Devi Mahatmya | F52: Durga / Mahishasuramardini — warrior goddess assembled from the pooled energy of the male gods to kill the buffalo-demon Mahishasura, whom no man or male god could defeat. | G52: Mahishasura wins a boon (no man / no male god can kill him), routs the devas, seizes heaven. The gods fail individually; they pool their tejas (radiance) into one blaze from which Durga emerges — ten-armed, lion-mounted, each god handing her his own weapon. She matches the shape-shifting demon form for form and beheads him. | H52: The dominant coalition meets an opponent it structurally cannot beat with its own (male-coded) tools, so it manufactures a specialist from outside its own ranks, equips her from the collective arsenal, and points her at the threat. The boon's blind spot — it never imagined feminine power — is exactly the gap the coalition exploits. Power outsourced to the category the rulers discounted. | I52: The made-for-purpose instrument is folded back under the pantheon's authority: she acts 'for' the gods, her victory restores THEIR heaven, and the framing keeps her derivative of them (their combined Shakti) even as she does what they could not. | J52: The theology refuses the containment. In Shaktism she is read not as the gods' tool but as Adi Shakti, the primordial power the gods are themselves expressions of — 'both a derivative of the male divinities and the true source of their inner power... greater than any of them' (Britannica). She is also notably not a consort: independent, unsplit. | K52: Athena (UF-003, manufactured war-goddess of the male sovereign); Kali (UF-002, emerges from Durga's own brow); Inanna (UF-001) | L52: Tier 1-2 | M52: Sourced (this pass) | N52: APPROPRIATION CAUTION — living Hindu tradition. The 'constituted' tag captures the Devi Mahatmya assembly-narrative ONLY; it is not the tradition's own verdict, which inverts it (Devi as supreme). Do not flatten supreme-Devi theology into 'tool the gods built.' | O52: MFM §9 (co-opted feminine); PF §1, §3 (capture, framing). Sub-type pairs with Athena (constituted). | P52: Devi Mahatmya / Durga Saptashati (Markandeya Purana, chs 81-93), 5th-6th c. CE — Mahishasura episode (tejas-assembly, arming, slaying). | Q52: Devi Mahatmya ch. 2 (assembly from combined tejas; each god's weapon) through ch. 3 (slaying of Mahishasura); the boon-of-Brahma frame. | R52: Britannica s.v. 'Durga' (derivative-yet-source formulation); Coburn, 'Devi-Mahatmya: The Crystallization of the Goddess Tradition' (1984); Coburn, 'Encountering the Goddess' (1991). | S52: Does the constituted reading survive the Shakta inversion? Test whether 'gods assemble her' is the load-bearing narrative or a frame the theology overrides; check that appropriation-caution is honored. | U52: HIGH if the assembly-narrative is presented as the meaning of Durga while ignoring the equally-textual supreme-Devi theology — that is both bad reading and appropriation. The inversion is the row's load-bearing caveat. | V52: Pull Devi Mahatmya ch. 2-3 verse refs (Coburn translation); confirm dating; keep Shakta-supremacy framing visible alongside the constituted tag. | W52: en.wikipedia.org/wiki/Mahishasura; britannica.com/topic/Durga (Devi Mahatmya, Markandeya Purana chs 81-93) | X52: 2026-06-14 | Y52: Tier 1 | Z52: Tier 2 | AA52: Supportive | AC52: Not yet tested | AE52: Legacy — not yet tagged
A53: UF-005 | B53: UF-01 | C53: Uncontained / Co-opted Feminine | D53: uncontained | E53: Ancient Egyptian (New Kingdom); Book of the Heavenly Cow | F53: Sekhmet — lioness 'Eye of Ra,' deployed by the sun-god to punish rebellious humanity, whose bloodlust exceeds his control and must be tricked into stopping with blood-red beer. | G53: Aging Ra learns humanity is plotting against him; on the gods' counsel he sends his Eye (Hathor) to punish them. She slaughters them, becomes the lioness Sekhmet, and is seized by rage that will not stop. Ra repents (he still means to rule them) and orders her to halt, but she will not. He floods the fields with 7,000 jars of ochre-reddened beer; she drinks it for blood, falls drunk, and is led back pacified. | H53: The sovereign deploys a detachable enforcer against an internal revolt, and the enforcer's violence overruns the political objective: the ruler wants the rebellion crushed but the population kept; the weapon wants only to kill. Deterrence becomes its own runaway — the instrument whose interests diverge from the principal who unleashed it. | I53: Containment is reasserted not by overpowering her but by DECEPTION and ritual management — the priesthood's specialty. The annual feast re-enacts the pacification (red beer) every year: the uncontrollable is administered through recurring ceremony, and her violence is rebranded as protection ('destroyer of rebellion,' tied to kingship). | J53: The myth itself records that the sovereign LOST control — the trick is an admission that raw force could not be commanded back. Egyptologists frame the Eye as the 'Distant Goddess' who escapes his control to wreak havoc before being forced to return: the escape is canonical, not a flaw in the telling. A variant has her storm off offended at the deception, dimming the sun until Thoth coaxes her home. | K53: Kali (UF-002, the uncontainable that is no one's weapon); Inanna (UF-001); cf. Ishtar's descent (power that withdraws and destabilizes the order) | L53: Tier 1-2 | M53: Sourced (this pass) | N53: Distinct flavor of 'uncontained' from Kali: Sekhmet is DEPLOYED (Ra's weapon) and then overflows — co-option's failure mode — whereas Kali is uncontained from the outset and instrumentalized by no one. Keep the distinction in the sub-type note; do not collapse them. | O53: MFM §9 (co-opted / uncontained feminine); PF §1 (capture), §3 (administered remainder). Sub-type = uncontained (deployed-and-overflows variant). | P53: Book of the Heavenly Cow ('The Destruction of Mankind'), inscribed in New Kingdom royal tombs — Tutankhamun (KV62 outer shrine), Seti I, Ramesses II / III / VI. | Q53: BHC opening through the red-beer pacification; the 'Send out your Eye' counsel; the 7,000 jars / Elephantine red-ochre passage. | R53: World History Encyclopedia, 'Book of the Heavenly Cow' (Distant Goddess typology); Hornung, 'Conceptions of God in Ancient Egypt'; Lichtheim, 'Ancient Egyptian Literature' Vol. II. | S53: Is the 'overflow / failure-of-control' reading textual or imposed? Verify Ra's recall attempt and her refusal are in the source; confirm the Distant-Goddess framing is standard Egyptology, not a stretch. | U53: MODERATE — the text is explicit about deployment, overflow, and trickery, so the read is well-grounded; risk is over-psychologizing the goddess or treating the 'Eye' as a single stable deity rather than a role (Hathor / Sekhmet / others fill it). | V53: Pull BHC lines (Lichtheim or Hornung edition); note the Bast / Sekhmet Lower/Upper-Egypt pairing; confirm the kingship-association cite. | W53: worldhistory.org/Book_of_the_Heavenly_Cow; the-past.com 'Book of the Heavenly Cow' (BHC, NK royal tombs) | X53: 2026-06-14 | Y53: Tier 1 | Z53: Tier 1-2 | AA53: Load-bearing | AC53: Not yet tested | AE53: Legacy — not yet tagged
A54: UF-006 | B54: UF-01 | C54: Uncontained / Co-opted Feminine | D54: harnessed-autonomy | E54: Phrygian / Anatolian -> Roman (Magna Mater); historical import 204 BCE | F54: Cybele / Magna Mater — Anatolian Great Mother imported to Rome by act of state during the war with Hannibal, reinvented as an ancestral Trojan goddess, her ecstatic wildness then fenced off by law. | G54: With Hannibal in Italy and prodigies reported (stone-showers, failed harvest, 205 BCE), the Senate consulted the Sibylline Books, which said an 'Idaean mother of Pessinus' would free Italy. In 204 BCE her black meteorite was carried from Asia Minor to the Palatine and Rome adopted her as a state goddess; Hannibal soon withdrew. Her eunuch priests (galli) imitated Attis's self-castration in ecstatic public rites. | H54: A polity under existential threat reaches OUTSIDE its own pantheon and imports a foreign source of power for raison d'etat — then domesticates it: rewrites her as 'ours / ancestral' (Trojan, via Aeneas) to launder the foreignness, and quarantines the parts that threaten the social order (citizen bodies). Adopt the power, regulate the wildness, claim the lineage. | I54: Textbook capture-and-canonize: the state installs the cult officially (temple, calendar, the Megalensia games) while drawing a hard line around its dangerous core — freeborn Roman citizens are barred from becoming galli, a senate decree restricts the begging processions, and Augustus enshrines a law against castration. The power is licensed; the ecstasy is confined to non-citizens and managed festival days. | J54: The wildness never fully assimilates. The galli persist as a standing scandal (Catullus 63 dramatizes Attis's self-mutilation and gender-ambiguity), and Greek and Roman writers keep debating the cult's morality. The regulation is itself the evidence that something un-Roman and uncontainable was being held at arm's length. | K54: Inanna (UF-001 — and her gala priests, plausibly cognate to the galli); Attis (the dying-and-rising consort); cf. Dionysus (imported ecstatic cult, similarly regulated) | L54: Tier 1-2 | M54: Sourced (this pass) | N54: Best-documented case in the cluster — datable political history (Livy, Cicero), not myth-internal inference. The 'what happened' is solidly Tier 1; the 'why = harness-and-regulate' is Tier 2 but rests on documented restrictions. Sub-type pairs with Inanna (harnessed-autonomy) via a different mechanism: state import + cultic regulation vs sacred-marriage legitimation. | O54: MFM §9 (co-opted feminine); PF §1 (capture), §2 (canonize), §4 (enforce). Sub-type = harnessed-autonomy. | P54: Livy, Ab Urbe Condita 29.10-14 (the import); Ovid, Fasti 4.179-372 (Megalensia, the stone, the procession); Catullus 63 (Attis). | Q54: Livy 29.10-11 (Sibylline consult, embassy to Pergamon / Pessinus, reception of the stone); the senate decree barring citizen galli; the Augustan castration ban. | R54: Lynn Roller, 'In Search of God the Mother: The Cult of Anatolian Cybele' (1999); Mary Beard, 'The Roman and the Foreign'; Beard/North/Price, 'Religions of Rome' Vol. I. | S54: Are the citizen-restriction and castration-law claims firmly attested (which sources, how late)? Distinguish securely-dated facts (204 BCE import) from contested specifics (restriction wording, its date). Confirm the Trojan-reinvention point. | U54: LOW-MODERATE on the history (well attested); MODERATE on specifics — some restriction details come from later sources and should be dated, not flattened into 'Rome immediately fenced her off.' The gala<->galli etymology is 'plausible, not conclusive' (Wikipedia): flag Tier 3, do not assert. | V54: Pull Livy 29.10-14 + Ovid Fasti 4 line refs; date the citizen-gallus restriction and Augustan law precisely; mark the gala<->galli link as Tier 3. | W54: en.wikipedia.org/wiki/Cybele; en.wikipedia.org/wiki/Galli (Livy 29.10-14; Ovid Fasti 4) | X54: 2026-06-14 | Y54: Tier 1 | Z54: Tier 1-2 | AA54: Load-bearing | AC54: Not yet tested | AE54: Legacy — not yet tagged
A55: DV-001 | B55: DV-01 | C55: Divination / Gatekeeping the Divine Will | D55: binary-query | E55: Babylonian / Assyrian (Akkadian); 1st-millennium BCE | F55: The tamītu oracle-query — the gods' verdicts obtainable only through a credentialed diviner who frames an exact yes/no question and reads the answer in a sacrificed animal's entrails (extispicy). | G55: A tamītu is a formal yes/no question put jointly to Shamash (sun-god of justice) and Adad (storm-god), the gods 'of the verdict.' Because the answer is binary, a professional diviner (bārû) had to frame the query with exhaustive precision — naming the person, the timeframe, every contingency — then perform the rite and read the verdict in the liver and entrails of a sacrificed sheep. The corpus (Lambert's edition, 54 tablets/fragments) preserves royal campaign questions, succession questions, even a husband's query about a wife's fidelity. | H55: Whoever runs the channel to the divine runs the relationship. A layperson cannot even ASK correctly — the rite and the exact wording are the diviner's expertise — so the bārû is an unavoidable intermediary between the king and the gods' approval. The technical difficulty of the procedure is itself the gatekeeping: the harder the channel is to operate, the more indispensable its operator. | I55: The mandatory-interpreter mechanism in its most procedural form. Divine will is real and consequential (you do not march, marry, or crown without it), but it is accessible only through a credentialed technician performing an exact ritual — the signal is routed through a gate only the diviner can open. Sub-type binary-query: the answer is reduced to yes/no, which makes the diviner's framing of the question the place where all the real power sits. | J55: The record itself — the queries preserve unusually candid detail (a king's full battle plan, a husband's suspicion) because the case had to be stated exactly for the gods. What survives is a snapshot of what people most needed to know and could not control, fossilized in the very form of the question. | K55: Within the cluster: Delphi (DV-002), Roman augury (DV-003), Shang oracle bones (DV-004). Mesopotamian extispicy generally; cf. Urim & Thummim / the oracular ephod (Israelite binary divination). | L55: Tier 1-2 | M55: Sourced | N55: Now the Mesopotamian ANCHOR of the divination cluster (relocated from CC-01, where it was always flagged as the loose fit — a divination genre, not a covenant). The tamītu texts are well-edited (Lambert); the priesthood-function reading is the interpretive layer. The bārû genuinely believed the gods answered — the lens describes the STRUCTURE (a credentialed gate on divine will), not an accusation of fraud (analyze the function, not the operator). | O55: DV-01 founding case — divination as the mandatory-interpreter gate. PF SS1 (capture: the signal routed through a credentialed channel). Sub-type = binary-query. | P55: tamītu corpus — W.G. Lambert, 'Babylonian Oracle Questions' (Mesopotamian Civilizations 13, 2007), 54 tablets/fragments; 1st-millennium BCE (some 2nd-millennium). | Q55: Representative tamiātu (royal campaign queries; the 'is my wife truthful' query); the extispicy prayer to Shamash (asking that an oracle be given as the answer). | R55: W.G. Lambert, 'Babylonian Oracle Questions' (2007); Ulla Koch, 'Mesopotamian Divination Texts'; Stefan Maul, 'The Art of Divination in the Ancient Near East.' | S55: Confirm the diviner-monopoly + binary-answer facts (Lambert). Keep the 'structure not fraud' framing. The anchor of DV-01. | U55: MODERATE — the texts are well-edited and the diviner-as-gate reading is well-supported; the risk is over-reading the diviners as cynical manipulators (most believed) rather than describing the structural monopoly. The binary-query structure is solid. | V55: Pull a sample tamītu from Lambert; cite Maul/Koch on the diviner's role; anchor the cross-cluster parallels (Delphi, Rome, Shang). | W55: eisenbrauns.org Babylonian Oracle Questions; thetorah.com 'Practice of Divination in the ANE' (Lambert 2007; tamītu corpus) | X55: 2026-06-14 | Y55: Tier 1 | Z55: Tier 1-2 | AA55: Load-bearing | AC55: Not yet tested | AE55: Legacy — not yet tagged
A56: DV-002 | B56: DV-01 | C56: Divination / Gatekeeping the Divine Will | D56: ambiguous-utterance | E56: Greek; Delphi, oracle of Apollo (Archaic-Roman era) | F56: The Delphic oracle — Apollo's will spoken through the entranced Pythia in cryptic form, then shaped and interpreted by the temple priests; for over a millennium the most authoritative oracle in the Greek world. | G56: At the Temple of Apollo at Delphi, the Pythia — a priestess — sat on a tripod in the inner chamber (adyton), entered a trance, and uttered Apollo's responses to questions from individuals and city-states. Her words were famously cryptic; the temple priests recorded and edited them into hexameter verse, and they required interpretation. Leaders sought the oracle's approval before founding colonies, going to war, or making laws. Croesus of Lydia, told that if he attacked Persia 'a great empire would fall,' attacked — and destroyed his own; when he complained, the priestess answered that Apollo had foretold truly and could not be blamed if men interpreted to their own liking. Before Salamis, the Athenians were told they'd be saved by 'wooden walls,' which Themistocles read as the navy. | H56: Power flows to whoever controls the meaning of the god's words. The oracle's genius was AMBIGUITY: the Pythia speaks obscurely, the priests render it, and the response can be read several ways — which means the oracle is never wrong. Built-in deniability converts into permanent authority: outcomes confirm the oracle whatever happens (Croesus's empire was 'a great empire'). The institution accrued staggering wealth (cities built treasuries to display offerings) and steered colonization and war for a thousand years. | I56: The interpreter-gate with deniability engineered in. The signal (divine guidance) arrives deliberately equivocal and MUST be interpreted — by the priesthood, and after the fact by events — so the oracle's authority can never be falsified. Sub-type ambiguous-utterance: vagueness is not a bug but the mechanism that makes the mandatory interpreter unaccountable and indispensable. | J56: A model of how a prediction-institution survives being wrong — by never committing to a falsifiable claim. The famous responses (recorded by Herodotus and others) outlive the cult as proverbs about the danger of hearing what you want. What's enclosed: human deliberation about the gravest choices (war, colony, law) routed through a priestly chokepoint that took a cut, literal and political. | K56: Within: tamītu (DV-001), Roman augury (DV-003), Shang oracle bones (DV-004). Other Greek oracles (Dodona, Didyma); cf. modern unfalsifiable forecasting. | L56: Tier 1-2 | M56: Sourced (this pass) | N56: The INSTITUTION (Pythia, priestly interpretation, the political/colonizing role, the treasuries, the 1000-year span) is well-attested; the famous individual responses (Croesus, 'wooden walls') come mainly from Herodotus and are part history, part shaped narrative — cite them as tradition, not transcript. The 'intoxicating fumes from a chasm' explanation is debated (a proposed ethylene/geology theory is contested); don't assert the trance's cause. Analyze the structure, not the sincerity of the Pythia. | O56: DV-01 — the AMBIGUOUS-UTTERANCE pole: the equivocal oracle that cannot be falsified. PF SS1-2. Sub-type = ambiguous-utterance. | P56: Herodotus, 'Histories' (Croesus 1.46-56; the 'wooden walls' 7.140-143); Plutarch's Delphic dialogues; the collected oracular responses (Parke & Wormell catalogue). | Q56: Hdt. 1.53 (the 'great empire will fall' response) & 1.91 (Apollo's self-defense to Croesus); Hdt. 7.141 ('wooden walls'); Plutarch, 'De Pythiae oraculis.' | R56: H.W. Parke & D.E.W. Wormell, 'The Delphic Oracle' (1956); Joseph Fontenrose, 'The Delphic Oracle' (1978, skeptical re-examination); Michael Scott, 'Delphi' (2014). | S56: Is the ambiguous-utterance / unfalsifiability reading grounded, and are the Herodotus-as-tradition and contested-fumes caveats load-bearing? Keep the institution distinct from the legendary responses. | U56: MODERATE — the institution and the ambiguity-mechanism are well-attested; the risks are (a) treating the legendary responses as verbatim history, and (b) asserting the contested physiological cause of the trance. The deniability-structure is solid. | V56: Pull Hdt. 1.53/1.91 + 7.141 and a Plutarch passage; cite Fontenrose on the responses' historicity; keep the fumes caveat. | W56: open.edu OpenLearn (Croesus/Themistocles at Delphi); thearchaeologist.org & ancientmysteries.org (Pythia, priestly interpretation, ambiguity, political role) | X56: 2026-06-14 | Y56: Tier 1 | Z56: Tier 1-2 | AA56: Supportive | AC56: Not yet tested | AE56: Mixed — separate layers | AF56: Oracle traditions and literary responses vary; mediated signal does not by itself prove intentional censorship. | AG56: VA-01
A57: DV-003 | B57: DV-01 | C57: Divination / Gatekeeping the Divine Will | D57: state-veto | E57: Roman (and Etruscan); Republic & Empire | F57: Roman state divination — the augurs reading bird-signs and the haruspices reading entrails (a liver-craft learned from the Etruscans) to certify or block public acts; divination as the procedural gate on the Roman state. | G57: No major public business — assemblies, elections, legislation, a magistrate taking office, an army marching — could proceed in Rome without favorable auspices. The college of augurs 'took the auspices' (watching birds within a ritually-defined templum); haruspices read the liver and entrails of sacrificed animals (the liver mapped as a microcosm of the cosmos to the gods — see the bronze Liver of Piacenza). Unfavorable signs could LEGALLY delay or reverse decisions; through obnuntiatio a magistrate could announce adverse omens to suspend public business, and contested auspices could void an act after the fact (in 163 BCE a consul's forgotten auspice retroactively invalidated an election). Cicero, himself an augur, wrote a skeptical examination of it all ('On Divination'). | H57: This is divination weaponized as institutional VETO. The augurs functioned 'less as a means of predicting the future and more as a system for regulating action' — a religious chokepoint wired directly into politics, the military, and legitimacy. And it was manipulable: politically motivated augurs could fabricate unfavorable omens to delay an election they disliked. Whoever can declare the gods displeased can stop the state. | I57: The interpreter as state-gatekeeper. Divine consent is procedurally required for public action, and only the priestly colleges can certify it — so the augural reading is a switch that turns the legitimate state on or off. Sub-type state-veto: the divination's content barely matters; what matters is the institutional power to validate or annul, held by a credentialed college. | J57: The bare machinery of legitimacy-by-divine-consent — and the candid Roman awareness that it was machinery (Cicero's skepticism; the old jab that two haruspices could hardly look at each other without laughing). The form persisted as a control-mechanism even as belief thinned: proof that the priesthood-function can outlive the faith that founded it, surviving as pure procedure. | K57: Within: tamītu (DV-001), Delphi (DV-002), Shang oracle bones (DV-004). Etruscan disciplina; cf. any procedural 'sign-off' that gates state power. | L57: Tier 1-2 | M57: Sourced (this pass) | N57: The political-procedural function (auspices required; obnuntiatio; invalidating elections) is very well-attested; the material anchor (the Etruscan Liver of Piacenza) is solid. Be precise: obnuntiatio = announcing adverse omens to OBSTRUCT business, not to obtain favorable ones. Cicero's 'De Divinatione' shows the Romans themselves debated whether any of it worked — so the row reads the political STRUCTURE, not a claim that the augurs (or their critics) were right about the gods. | O57: DV-01 — the STATE-VETO pole: divination as the procedural gate on public power. PF SS1-2. Sub-type = state-veto. | P57: Cicero, 'De Divinatione' & 'De Natura Deorum'; Livy (auspices invalidating acts); the Etruscan Bronze Liver of Piacenza (c. 100 BCE). | Q57: Cicero, 'De Div.' 1-2 (the case for and against); the 163 BCE forgotten-auspice / invalidated-election episode; the Piacenza liver's god-mapped regions. | R57: Mary Beard, John North & Simon Price, 'Religions of Rome' (1998); Jerzy Linderski, 'The Augural Law' (ANRW, 1986); Veit Rosenberger on Roman divination. | S57: Is the state-veto reading (auspices/obnuntiatio gating public acts) grounded, and is the Cicero-skepticism caveat load-bearing? Define obnuntiatio precisely. Keep structure distinct from truth-claim. | U57: LOW-MODERATE on the political function (very well-documented); the risk is overstating how OFTEN it changed outcomes vs. served as ritual cover, and mis-defining the technical terms. The veto-structure is solid. | V57: Pull Cicero 'De Div.' framing + the 163 BCE Livy episode + a Piacenza-liver reference; cite Beard/North/Price and Linderski. | W57: en.wikipedia.org/wiki/Augur & /Augury (auspices, obnuntiatio, college of augurs, Piacenza liver); unrv.com (auspices as regulation, haruspicy, pax deorum) | X57: 2026-06-14 | Y57: Tier 1 | Z57: Tier 1 | AA57: Load-bearing | AC57: Not yet tested | AE57: Legacy — not yet tagged
A58: DV-004 | B58: DV-01 | C58: Divination / Gatekeeping the Divine Will | D58: royal-monopoly | E58: Chinese; Shang dynasty (c. 1250-1046 BCE), Yinxu/Anyang | F58: Shang oracle-bone divination (pyro-osteomancy) — the king as chief diviner cracking ox scapulae and turtle plastrons with a hot rod and reading the cracks to consult the ancestors and the high god Di; the practice that underpinned royal legitimacy and produced the earliest Chinese writing. | G58: Shang diviners (and increasingly the king himself) inscribed a question on a polished ox shoulder-blade or turtle plastron, applied a heated rod to drilled pits until hairline cracks formed, and read the cracks for the answer — often simply whether a day was auspicious (ji) or not (xiong). Questions covered sacrifices, war, harvest, weather, hunting, childbirth, even the cause of a royal toothache. A typical bone records the date and diviner, the charge (the proposition), the king's prognostication ('the king read the cracks and said: auspicious'), and sometimes the verification (what actually happened). Tens of thousands survive from the royal archives at Yinxu; their inscriptions are the oldest known Chinese script and even confirmed the Shang kings were historical. | H58: Divination here is not consulted by power — it IS the power. The Shang king is the chief priest who holds exclusive access to the ancestor cult that underpinned royal legitimacy; only he (or his diviners) can mediate between the living and the ancestors. By late Shang the king himself reads the cracks and pronounces the verdict — so the channel to the divine and the throne are the same office. To monopolize the ancestors is to monopolize legitimacy. | I58: The purest fusion of the interpreter and the ruler. Where Delphi's priests and Rome's augurs are intermediaries serving power, the Shang king ABSORBS the interpreter-function into kingship: he is the mandatory channel to Di and the ancestors, and his prognostication is by definition correct. Sub-type royal-monopoly: access to the divine is not gated by a separate priesthood but engrossed by the sovereign, who thereby makes his authority literally unquestionable. | J58: The bones themselves — and a staggering fact: the earliest Chinese writing exists BECAUSE of royal divination. Writing enters Chinese history as the record of the king's exclusive conversation with the ancestors; 'divine memory became written history.' The remainder is the script of a civilization, born inside a monopoly on the supernatural — a reminder that the technologies of record can originate as instruments of sacred-political control. | K58: Within: tamītu (DV-001), Delphi (DV-002), Roman augury (DV-003). Later Chinese mantic traditions (the Yijing/I Ching); cf. any ruler who is also high priest (sacral kingship). | L58: Tier 1-2 | M58: Sourced (this pass) | N58: Exceptionally well-attested materially (~150,000 inscribed pieces from Yinxu; the corpus is the earliest Chinese writing and confirmed the Shang's historicity). The king-as-head-diviner monopoly is strongest for the LATE Shang; earlier, named diviners did more of the reading. The fine theology of Di and the crack-reading is partly inferred. Read the structure (a sacred-political monopoly), not a verdict on whether the ancestors answered. | O58: DV-01 — the ROYAL-MONOPOLY pole: the interpreter-function absorbed into kingship; divination as the foundation of legitimacy (and of writing). PF SS1-2. Sub-type = royal-monopoly. | P58: The oracle-bone inscriptions (jiaguwen) from Yinxu/Anyang (c. 1250-1046 BCE), esp. the Wu Ding-era corpus; David N. Keightley's editions. | Q58: Representative inscriptions — the four-part form (preface / charge / prognostication / verification); the 'hunt at Wu, no disasters' bone (king reads: 'auspicious'); the 'sacrifice to Ancestor Ding' bone (king reads: 'misfortune'). | R58: David N. Keightley, 'Sources of Shang History' (1978) & 'The Ancestral Landscape' (2000); Robert Eno on the oracle inscriptions; Sarah Allan on early Chinese cosmology. | S58: Is the royal-monopoly reading (king as chief diviner; divination as legitimacy; writing born of divination) grounded in the inscriptions/Keightley, and is the late-Shang qualification load-bearing? Keep structure distinct from truth-claim. | U58: MODERATE — the material record and the political role are very strong; the risks are flattening the king-monopoly across all of Shang (it intensified late) and over-specifying the theology. The royal-monopoly structure is solid. | V58: Pull Keightley on the diviner/king's role + two sample inscriptions; cite Eno; anchor the writing-from-divination point. | W58: worldhistory.org Oracle Bones (king as head diviner); thearchaeologist.org & chinaknowledge.de (pyromancy, ancestors/Di, earliest writing, royal archives) | X58: 2026-06-14 | Y58: Tier 1 | Z58: Tier 1 | AA58: Load-bearing | AC58: Not yet tested | AE58: Legacy — not yet tagged
A59: DR-001 | B59: DR-01 | C59: Distributed Remainder / Surviving the Center's Fall | D59: portable-holiness | E59: Second Temple -> Rabbinic Judaism; 70 CE | F59: The Pharisees -> Rabbinic Judaism — when the Temple and its priesthood were destroyed, Jewish religious life survived because the Pharisaic stream had already made holiness portable: study, synagogue, prayer, and law that needed no central altar. | G59: In 70 CE Rome destroyed the Second Temple, ending the sacrificial cult and the priestly aristocracy (the Sadducees, tied to the Temple, did not survive). Of the first-century movements, the Pharisees — a lay movement centered on Torah study, oral tradition, synagogue, and applying holiness to everyday life — endured. The Talmud tells of Yohanan ben Zakkai smuggled from besieged Jerusalem in a coffin, securing from Vespasian an academy at Yavneh; there the Sanhedrin was reconstituted and Judaism shifted from a practice built around the Temple and its priestly rites to one centered on study and the observance of law. Atonement moved from sacrifice to charity and deeds of loving-kindness; worship moved to every local synagogue. | H59: The most centralized capture-apparatus imaginable — one Temple, one priestly caste, one place where the sacrifices (the administered debt) must be brought — was destroyed, and the signal did not die. It survived because a parallel, DISTRIBUTED form was already running: holiness you can practice anywhere, mediated by no caste, carried in text and habit. When the center fell, the remainder didn't need rebuilding; it was already everywhere. | I59: This is the anti-capture move in its clearest form — authority and access dispersed from a single mandatory center (Temple / priest) to a portable, replicable practice (study / synagogue / law) available to every household. No single place is indispensable; no caste monopolizes mediation. The remainder reactivates by going distributed rather than being re-captured into a new central cult. | J59: An entire religion — and the template for surviving the loss of one's center: a tradition whose holiness is portable cannot be killed by destroying its building. BUT the counterpoint is not permanent — over generations the distributed authority re-concentrated into a structured rabbinic estate (later tradition vesting broad authority in the rabbis), the recurring pattern by which the remainder that escapes capture becomes a new center. | K59: Reformation 'priesthood of all believers' (DR-002); post-Buddha Sangha (DR-003); cf. the capture clusters it inverts (CC-01 covenant; the Temple cult as priesthood-function) | L59: Tier 1-2 | M59: Sourced (this pass) | N59: HANDLE WITH CARE — present the Pharisees accurately (a lay reform movement that made holiness portable), NOT through the later Christian-polemical 'legalist / hypocrite' trope, which is historically false and fed antisemitism. Tier-2 caveats: the neat Pharisee->rabbi->Judaism continuity is partly later rabbinic self-narration (Cohen, 'The Significance of Yavneh'); Yohanan is not always identified as a Pharisee; the distributed outcome was not inevitable (other contenders existed); the coffin / Vespasian story is a Talmudic legend (Gittin 56a), not plain history. Living Jewish tradition — analytic lens, not a verdict. [v0.19] DR-01 = systems-history / countermeasure architecture; adjacent to primary myth evidence, not myth-motif evidence. | O59: PF Case 2 (distributed remainder / the center falls) — founding case of the COUNTERPOINT (anti-capture). Sub-type = portable-holiness. | P59: Mishnah (Pirkei Avot 1, the chain of transmission); Talmud Bavli Gittin 56a-b (Yohanan & Vespasian); the Yavneh traditions; Deut 33:4 (Torah as the congregation's inheritance). | Q59: Gittin 56a (escape + the Yavneh request); m. Avot 1:1 (Sinai->elders->prophets->great assembly chain); the 'deeds of loving-kindness' atonement teaching (Avot de-Rabbi Natan 4). | R59: Shaye J.D. Cohen, 'From the Maccabees to the Mishnah' & 'The Significance of Yavneh'; Jacob Neusner, 'From Politics to Piety'; E.P. Sanders, 'Judaism: Practice and Belief.' | S59: Is the portable-holiness reading textual and is the Pharisee portrayal accurate (non-polemical)? Foreground the Cohen caveats (rabbinization of history; contingency of outcome). Keep the re-concentration tension visible. | U59: HIGH on two fronts — (a) reproducing anti-Pharisee polemic (guard against it explicitly); (b) telling the survival as a clean, inevitable, fully-intentional plan rather than a contingent outcome partly narrated in hindsight. The portable-holiness structure is solid; the tidiness is the risk. | V59: Pull Gittin 56a + m. Avot 1; cite Cohen on Yavneh; keep both the accuracy-caution and the re-concentration caveat load-bearing. | W59: en.wikipedia.org/wiki/Rabbinic_period; myjewishlearning.com 'Johanan ben Zakkai'; cojs.org Cohen 'Significance of Yavneh' | X59: 2026-06-14 | Y59: Tier 1 | Z59: Tier 2 | AA59: Supportive | AC59: Not yet tested | AE59: Legacy — not yet tagged
A60: DR-002 | B60: DR-01 | C60: Distributed Remainder / Surviving the Center's Fall | D60: priesthood-of-all | E60: Western Christianity; 16th-c. Reformation | F60: The Reformation 'priesthood of all believers' — Luther's claim that every Christian has direct access to God and may read Scripture, breaking the clergy's monopoly on mediation and interpretation. | G60: The medieval Church held that God's grace was mediated through the sacraments and the priests authorized to administer them, and that only the Church's magisterium could authoritatively interpret Scripture. From 1520, Luther argued the holy / profane split between clergy and laity was wholly human and artificial: every baptized Christian is a priest with direct access to God through Christ, the one mediator (priesthood of all believers), and Scripture — not papal tradition — is the final authority, to be read by all (sola scriptura). The printing press and vernacular Bibles (Luther's German; Tyndale's English NT, 1526) put the text in ordinary hands, making faith a personal, literate practice rather than one mediated entirely through ritual and priestly authority. | H60: A mandatory-interpreter monopoly — grace and meaning available only through a credentialed caste — was broken not by destroying the institution but by DISTRIBUTING its function: declaring every believer a priest and every reader an interpreter. The gatekept channel to the divine was forced open; the technology (cheap print, vernacular text) made the distribution irreversible. | I60: The interpreter-capture directly attacked and dispersed: no human mediator is required (priesthood of all), no clerical monopoly on the text (sola scriptura). What the priesthood-function centralizes — access, mediation, authorized interpretation — the Reformation hands to everyone with a Bible. | J60: Mass literate access to the sacred text, and the principle that mediation can be dispersed. BUT, as with every case in this cluster, the distribution re-concentrated: Luther kept an ordained 'ministry,' Protestantism splintered into denominations with their own clergy, confessions, and interpretive authorities — new monopolies forming inside the movement that had broken the old one. | K60: Pharisees / rabbinic Judaism (DR-001); post-Buddha Sangha (DR-003); cf. the Catholic mediation-system it inverts (a priesthood-function apparatus) | L60: Tier 1-2 | M60: Sourced (this pass) | N60: Well-documented history (Luther's 1520 texts extant). Caveats: 'priesthood of all believers' did NOT mean abolishing clergy — Luther retained a reformed ministry (representatives of the congregation), so this is democratization, not anarchy. Avoid the (ironically common) move of using 'the Pharisees' as the foil for the medieval clergy — that's the same polemic DR-001 corrects. Living Christian traditions (Catholic & Protestant) — descriptive, not partisan. [v0.19] DR-01 = systems-history / countermeasure architecture; adjacent to primary myth evidence, not myth-motif evidence. | O60: PF Case 2 family (distributed remainder) — the COUNTERPOINT; the interpreter-monopoly broken. Sub-type = priesthood-of-all. | P60: Luther, 'To the Christian Nobility of the German Nation' (1520) & 'The Freedom of a Christian' (1520); the 95 Theses (1517); Luther's German Bible; Tyndale NT (1526). | Q60: 'To the Christian Nobility' on the artificial clergy / laity split & priesthood of all; sola scriptura statements (Diet of Worms, 1521); 1 Peter 2:9 (the proof-text). | R60: Roger E. Olson, 'The Story of Christian Theology'; Alister McGrath, 'Reformation Thought'; Britannica s.v. 'priesthood of all believers.' | S60: Confirm the priesthood-of-all + sola-scriptura + print-distribution facts. Keep the 'reformed ministry retained' and the re-concentration (denominationalism) caveats visible. Don't import the anti-Pharisee trope. | U60: LOW-MODERATE on the history; MODERATE on the reading — resist framing it as pure, permanent decentralization (clergy retained; new authorities formed). The distribution is real; its permanence is not. | V60: Pull the 1520 'Christian Nobility' passage + 1 Pet 2:9; cite McGrath; note the denominational re-concentration. | W60: britannica.com 'priesthood of all believers'; museeprotestant.org 'sola scriptura' (Luther 1520; Tyndale 1526) | X60: 2026-06-14 | Y60: Tier 1 | Z60: Tier 2 | AA60: Supportive | AC60: Not yet tested | AE60: Legacy — not yet tagged
A61: DR-003 | B61: DR-01 | C61: Distributed Remainder / Surviving the Center's Fall | D61: teaching-as-teacher | E61: Early Buddhism; Mahaparinibbana Sutta (DN 16) | F61: The Buddha's parinirvana — dying, he appoints no successor and instead names the Dhamma and Vinaya his successor, telling the Sangha to 'be islands / lamps unto yourselves' with the teaching, not any person, as the refuge. | G61: In the Mahaparinibbana Sutta the dying Buddha tells Ananda he has no thought that he should lead the community or that it depends on him, and so gives no instruction appointing a leader. Instead of naming an individual successor, he identifies the Dhamma and Vinaya he has taught as the successor, and sets impersonal criteria (the Mahapadesa) for authenticating any future teaching: judge a claim not by the authority of who reports it, but by its consistency with the teaching already known. His parting instruction: be islands unto yourselves, with the Dhamma as your island, your refuge, seeking no other refuge. | H61: At the moment a charismatic founder dies — the classic trigger for a succession-grab and a new central authority — the Buddha PREEMPTS the capture: he refuses to be indispensable, refuses to anoint a successor-monopoly, and relocates authority into the teaching itself and into each practitioner. There is no one to capture the office, because the office is dissolved into text, code, and personal practice. | I61: The mandatory-interpreter is forestalled by design. Authority is impersonal (the Dhamma / Vinaya), self-validating by criteria rather than by an authorized person, and internalized (each is a lamp unto themselves via their own practice). No caste is needed to mediate; no successor inherits the power to define truth. | J61: A tradition that locates authority in teaching-plus-practice rather than office — explicitly a Way said to go beyond priesthood. BUT the cluster's tension holds here too: the Sangha promptly organized (Mahakassapa convening the First Council to fix the canon), and Buddhism developed monastic hierarchies, lineages, and ordination authorities — distributed authority re-concentrating into new institutional centers over time. | K61: Pharisees / rabbinic Judaism (DR-001); Reformation (DR-002); cf. founder-cults that DID centralize after a death (contrast) | L61: Tier 1-2 | M61: Sourced (this pass) | N61: The textual content (no successor; Dhamma / Vinaya as successor; atta-dipa; Mahapadesa) is solidly in DN 16. Caveats: DN 16 is the tradition's account, redacted over time — not a verbatim deathbed transcript; some popular renderings ('work out your own salvation') are looser than the text. The re-concentration (councils, lineage authority) is part of the same history. Living Buddhist tradition — descriptive, not reductive. [v0.19] DR-01 = systems-history; adjacent to primary myth evidence. Living-tradition care (Buddhism). | O61: PF Case 2 family (distributed remainder) — the COUNTERPOINT; authority distributed at the founder's death. Sub-type = teaching-as-teacher. | P61: Mahaparinibbana Sutta (Digha Nikaya 16); the Mahapadesa passage (DN 16 / AN 4.180); the atta-dipa passage (also Samyutta Nikaya 47.9, 47.13). | Q61: DN 16 — the 'no leader / Dhamma-and-Vinaya as successor' passage; the 'be islands unto yourselves' passage; the Mahapadesa four criteria. | R61: Rupert Gethin, 'The Foundations of Buddhism'; Richard Gombrich, 'Theravada Buddhism'; Maurice Walshe / Bhikkhu Bodhi trans. of the Digha Nikaya. | S61: Confirm the no-successor + Dhamma/Vinaya-as-successor + atta-dipa + Mahapadesa points in DN 16. Flag DN 16's redactional nature and the re-concentration. Keep it descriptive of a living tradition. | U61: MODERATE — the anti-capture reading is well-grounded in the text, but don't overstate it as 'Buddhism has no authority structures' (it developed many) or treat DN 16 as historical reportage. The teaching-as-authority structure is the textual claim. | V61: Pull DN 16 passages (Walshe / Bodhi) + the Mahapadesa; cite Gethin; note the First Council re-concentration. | W61: accesstoinsight.org dn.16 (Maha-parinibbana Sutta); dhammatalks.org DN16 (DN 16; Mahapadesa) | X61: 2026-06-14 | Y61: Tier 1 | Z61: Tier 2 | AA61: Supportive | AC61: Not yet tested | AE61: Legacy — not yet tagged
A62: VA-001 | B62: VA-01 | C62: Voice / Authorship / Signal Capture | D62: Origination disabled; repetition retained | E62: Roman literary myth | F62: Echo (Ovid) | G62: Juno punishes Echo for distracting her with talk: Echo can thereafter repeat only the endings of another speaker's words. Rejected by Narcissus, her body wastes away while her voice remains. | H62: A speaker can be stripped of initiative and left useful only as a transmission medium; even so, selective repetition leaves a small compositional remainder. | I62: Capture separates authorship from circulation: the channel survives, but it is licensed to carry only prior speech. | J62: Echo chooses fragments that answer Narcissus; after her body disappears, signal persists without a controllable body. | K62: Cassandra (truth without credibility); Longus's dismembered Echo; distributed remainder | L62: Tier 1-2 | M62: Anchored (v0.21); primary passage located | N62: Roman, Latin, and late relative to archaic Greek sources. Do not merge this punishment with Longus's separate Pan/Echo narrative. | O62: Ovid, Metamorphoses 3.359-401 | P62: Ovid, Metamorphoses, Book 3 | Q62: 359-369; 385-401 | R62: Ovid commentary on Echo/Narcissus; Shane Butler, The Ancient Phonograph | S62: Separate what Ovid says about constrained speech from the modern authorship-capture reading. What agency remains in Echo's selections? | T62: High-value story bridge: a channel can outlive a punished speaker without becoming a trustworthy archive by default. | U62: Do not call Echo an ancient free-speech activist or Gaia's uncensorable archive. | V62: Verify against a cited critical edition and add exact translation used. | W62: https://www.perseus.tufts.edu/hopper/text?doc=Perseus%3Atext%3A1999.02.0029%3Abook%3D3 | X62: 2026-08-18 | Y62: Tier 1 | Z62: Tier 2 | AA62: Load-bearing | AB62: The frame might predict total silencing; Ovid instead preserves repeatable sound and limited reply. | AC62: Fits | AD62: The episode is also an aetiology of echo and a tragedy of failed reciprocity, not a theory of institutional censorship. | AE62: Ancient variant / reception | AF62: Ancient core: Juno restricts Echo to repeating final words and Echo's body fades. Fictional layer: courtroom routing, badges, distributed testimony, or deliberate archival resistance.
A63: VA-002 | B63: VA-01 | C63: Voice / Authorship / Signal Capture | D63: Truth retained; credibility disabled | E63: Greek tragedy | F63: Cassandra | G63: Cassandra speaks true prophecy, but Apollo's punishment makes her warnings disbelieved; in Agamemnon she recognizes the house's violence and her own death while the chorus fails to act. | H63: A system need not suppress a message if it can disable the speaker's credibility in advance. | I63: Authentication capture: truth circulates, but the social rule for recognizing truth has been sabotaged. | J63: The testimony remains accurate and becomes legible to the audience even when useless to those inside the scene. | K63: Echo; rejected whistleblower; Delphi's mediated oracle | L63: Tier 1-2 | M63: Anchored (v0.21); primary passage located | N63: Keep the divine-sexual bargain and House of Atreus tragedy visible; 'epistemic injustice' is a modern analytic term. | O63: Aeschylus, Agamemnon 1202-1213 and following | P63: Aeschylus, Agamemnon | Q63: 1202-1213; continue through the recognition and death prophecy | R63: Commentaries on Cassandra in Agamemnon; scholarship on tragic prophecy and credibility | S63: What in the text disables belief, and what does the audience know that the chorus cannot use? | T63: This is stronger than generic silencing: the signal is audible, true, and institutionally inert. | U63: Do not reduce Cassandra to a modern whistleblower or treat disbelief as a bureaucratic policy. | V63: Pin line numbering and translation; add one academic commentary. | W63: https://www.theoi.com/Text/AeschylusAgamemnon.html | X63: 2026-08-18 | Y63: Tier 1 | Z63: Tier 2 | AA63: Supportive | AB63: The frame predicts control of circulation; Cassandra's speech circulates freely but fails at credibility. | AC63: Fits | AD63: Her fate belongs to divine punishment and tragic family history rather than an organized media system. | AE63: Ancient textual core | AF63: Ancient core: true prophecy is made unbelievable. Fictional layer: formal witness rules, verification protocols, or a public tribunal that restores standing. | AG63: DV-01
A64: VA-003 | B64: VA-01 | C64: Voice / Authorship / Signal Capture | D64: Oral overload converted into sovereign record | E64: Sumerian literary tradition | F64: Enmerkar's tablet | G64: When a messenger can no longer repeat Enmerkar's long message, the lord kneads clay and writes the words on a tablet; the recorded message remains part of a coercive contest with Aratta. | H64: Durable writing solves transmission failure, but the stabilized signal belongs to royal command rather than distributed speech. | I64: Record-making can reduce dependence on memory while increasing the center's control over wording, recurrence, and proof. | J64: The message becomes portable and repeatable beyond one messenger's capacity. | K64: Jeremiah/Baruch; Shang records; administrative inscription | L64: Tier 1-2 | M64: Anchored (v0.21); ETCSL passage located | N64: Do not call this the universal invention of writing or a liberation of voice. The composition and manuscripts are historically complex. | O64: Enmerkar and the Lord of Aratta 500-535 | P64: ETCSL 1.8.2.3 | Q64: 500-535; compare coercive context 108-207 | R64: Assyriological work on Enmerkar, literacy, and the messenger episode | S64: Does durable inscription distribute authority, centralize it, or do both at once in this episode? | T64: Excellent counter-pressure on any equation of writing with emancipation. | U64: Avoid treating literary aetiology as a simple historical account of writing's invention. | V64: Verify translation and manuscript caveat in a current scholarly edition. | W64: https://etcsl.orinst.ox.ac.uk/section1/tr1823.htm | X64: 2026-08-18 | Y64: Tier 1 | Z64: Tier 2 | AA64: Supportive | AB64: The frame predicts captured intermediaries; here the medium changes because the messenger reaches a cognitive limit. | AC64: Partial fit | AD64: Writing solves a memory problem while transmitting a king's ultimatum; it centralizes command as much as it frees the messenger. | AE64: Ancient textual core | AF64: Ancient core: a too-long oral message is put on clay. Fictional layer: a neutral public ledger, anti-censorship network, or democratic archive. | AG64: DV-01; DR-01
A65: VA-004 | B65: VA-01 | C65: Voice / Authorship / Signal Capture | D65: Speaker, scribe, reader, and record separated | E65: Hebrew Bible / court narrative | F65: Jeremiah and Baruch | G65: Jeremiah dictates a scroll to Baruch; Baruch reads it; the king cuts and burns it; Jeremiah dictates a replacement with additional words. | H65: Destroying one artifact does not end a message when composition, memory, scribal labor, and community are distributed across people. | I65: The court attempts record destruction; prophetic authorization regenerates the text through a trusted scribe. | J65: The signal survives material destruction and returns in expanded form. | K65: Echo; Enmerkar; distributed remainder | L65: Tier 1-2 | M65: Anchored (v0.21); chapter located | N65: Treat as theological court narrative, not a neutral transcript of administrative history. Preserve Jewish and Christian interpretive contexts. | O65: Jeremiah 36:1-32 | P65: Book of Jeremiah, chapter 36 | Q65: Whole chapter; especially 1-8, 20-26, 27-32 | R65: Critical commentaries on Jeremiah 36, scribal transmission, and textual growth | S65: Map who originates, writes, reads, destroys, remembers, and authorizes the replacement. Where is agency concentrated? | T65: A high-quality case because the record is both authorized and resilient; distribution is not the same as leaderless authorship. | U65: Do not turn Baruch into an autonomous modern publisher or the chapter into a generic free-press parable. | V65: Add a Jewish-studies source and specify the translation used. | W65: https://www.sefaria.org/Jeremiah.36?lang=bi | X65: 2026-08-18 | Y65: Tier 1 | Z65: Tier 2 | AA65: Supportive | AB65: The frame predicts a priestly choke point; the passage instead shows a prophet-authorized scribal chain. | AC65: Fits | AD65: Authority remains with God and the prophet; Baruch is a commissioned scribe, not a decentralized authorial collective. | AE65: Ancient textual core | AF65: Ancient core: dictation, public reading, royal destruction, and regenerated scroll. Fictional layer: anonymous publication infrastructure or a constitutional right to copy. | AG65: DR-01
A66: VA-005 | B66: VA-01 | C66: Voice / Authorship / Signal Capture | D66: Counterexample: Speech as sovereign agent | E66: Rigvedic / living Hindu reception | F66: Vāc | G66: In Rigveda 10.125, Speech speaks in the first person as a cosmic power who moves among gods, sustains beings, and empowers whom she chooses. | H66: The hymn resists the assumption that speech is merely a channel owned by ruler, priest, or speaker. | I66: Counterexample to a capture-only model: ritual speech can appear as agent and source of authorization, not passive infrastructure. | J66: Speech retains cosmic agency and cannot be reduced to a message carrier. | K66: Echo; Sarasvati/Vāc reception only with tradition-specific sourcing | L66: Tier 1-2 | M66: Anchored (v0.21); hymn located | N66: Living-tradition care. Do not translate theological self-assertion into modern individual free speech or a single pan-Hindu doctrine. | O66: Rigveda 10.125 (Devīsūkta / Vāc hymn) | P66: Rigveda 10.125 | Q66: Entire hymn | R66: Jamison and Brereton, The Rigveda (2014); tradition-specific scholarship on Vāc | S66: Does this hymn break the cluster's assumption that voice must belong to a human author or institution? | T66: The row is here to stop VA-01 from becoming a universal story of censorship. | U66: No 'Eastern goddess of free speech' shorthand; keep translation and reception specific. | V66: Verify with Jamison-Brereton and add a living-tradition scholarly source. | W66: https://rigveda-online.github.io/10/125.html | X66: 2026-08-18 | Y66: Tier 1 | Z66: Tier 2 | AA66: Supportive | AB66: The frame predicts a speaker and a captured medium; the hymn presents Speech herself as acting power. | AC66: Counterexample | AD66: This is ritual and theological self-assertion, not a manifesto for modern individual expression. | AE66: Ancient textual core | AF66: Ancient core: Vāc speaks as cosmic agency. Fictional layer: recruiting her as a constitutional witness or spokesperson for a modern rights regime. | AG66: UF-01; AD-01
A67: VA-006 | B67: VA-01 | C67: Voice / Authorship / Signal Capture | D67: Wild music and amplified collective signal | E67: Greek to Imperial reception | F67: Pan and panic signal | G67: Early Pan is a pastoral musician; Herodotus reports his claimed aid to Athens; much later Polyainos describes a mass nocturnal shout amplified by terrain and Echo that routs an enemy. | H67: Unowned landscape and collective sound can amplify a signal beyond any single author, but the result may be coercive rather than emancipatory. | I67: A leader organizes people, terrain, fear, and repetition into psychological force. | J67: The effect depends on bodies and acoustic terrain Pan does not fully own. | K67: Echo; rumor/Fama; battlefield signal | L67: Tier 2 | M67: Needs source pass; chronology separated | N67: Do not back-project the late panic stratagem into the Homeric Hymn or claim Pan defeated Typhon with a shout. | O67: Homeric Hymn 19; Herodotus 6.105; Polyainos 1.2 | P67: Hymn to Pan; Histories; Stratagems | Q67: HH 19.1-49; Hdt. 6.105; Polyainos 1.2 | R67: Oxford Classical Dictionary, Pan; scholarship on panikon/panic chronology | S67: Build a source-layer table: pastoral music, Athenian cult claim, and late military amplification. Which layer supports which inference? | T67: Useful only when chronology is the point; otherwise it becomes a fabricated timeless Pan package. | U67: High risk of fusing sources centuries apart and confusing Aigipan with Pan. | V67: Verify each passage in edition and decide whether to keep as one layered row or split. | W67: https://www.perseus.tufts.edu/hopper/text?doc=Perseus%3Atext%3A1999.01.0126%3Abook%3D6%3Achapter%3D105 | X67: 2026-08-18 | Y67: Tier 1-2 | Z67: Tier 2 | AA67: Source-pass | AB67: The frame predicts a voice captured by a center; the late stratagem is collective amplification directed by a leader. | AC67: Partial fit | AD67: Early Pan is primarily pastoral, musical, sexual, and epiphanic; weaponized panic is a later reception layer. | AE67: Mixed — separate layers | AF67: Ancient layers must remain dated and separate. Fictional layer: Pan as architect of mass communications, Typhon-defeating shout, or permanent commander of Echo. | AG67: TR-01; TH-01
A68: VA-007 | B68: VA-01 | C68: Voice / Authorship / Signal Capture | D68: Body destroyed; imitative signal dispersed | E68: Imperial Greek literary reception | F68: Echo (Longus) | G68: In Longus, Pan retaliates after Echo rejects him; maddened herders tear her apart, Earth receives the pieces, and the dispersed voice continues imitating sounds. | H68: Violence can destroy a speaker's body while multiplying an uncontrollable remainder through the environment. | I68: Possessive retaliation tries to convert an autonomous musician into silence; the landscape preserves effects it does not authenticate. | J68: The voice persists without the body, but imitation alone does not guarantee memory, truth, or intention. | K68: Ovid's Echo; Philomela; distributed remainder | L68: Tier 1-2 | M68: Anchored (v0.21); passage located | N68: Longus is Greek-language but later than Ovid; do not call this the older Greek version or fuse it with Juno's punishment. | O68: Longus, Daphnis and Chloe 3.23.1-4 | P68: Daphnis and Chloe, Book 3 | Q68: 3.23.1-4 | R68: Commentary on Longus 3.23; studies of Echo and pastoral violence | S68: What survives: authorial intention, sound pattern, or only an acoustic effect? Keep those distinct. | T68: The row supplies a darker story bridge than Ovid, but its remainder is ambiguous rather than automatically liberatory. | U68: Do not say Gaia deliberately safeguards an archive; Earth receiving the fragments is not a constitutional act. | V68: Verify text/translation and add a modern commentary. | W68: https://en.wikisource.org/wiki/Daphnis_and_Chloe_%28Thornley_translation%29/Book_3 | X68: 2026-08-18 | Y68: Tier 1 | Z68: Tier 2 | AA68: Supportive | AB68: The frame predicts preserved meaning; the tale guarantees continuing sound, not faithful content. | AC68: Partial fit | AD68: The episode is pastoral horror and sound-aetiology; persistence need not equal political resistance. | AE68: Later literary reception | AF68: Ancient literary core: Pan's retaliation, dismemberment, Earth receiving fragments, imitative sound surviving. Fictional layer: a conscious distributed archive or Echo commanding every repeated voice. | AG68: DR-01; DF-01
